Workbook

Sheet 打印界面
A1: 鞋城商铺缴费收据 | K1: 1
A2: 租金期间:2026.1.1-2026.1.31 | G2: =IFERROR(VLOOKUP(K1,'2026.01'!A:Y,2,0),0) -> NO:001
A3: 铺号 | B3: =IFERROR(VLOOKUP(K1,'2026.01'!A:Y,6,0),0) -> 1001-01（临一） | D3: 铺主 | E3: =IFERROR(VLOOKUP(K1,'2026.01'!A:Y,7,0),0) -> 何具达 | G3: 备注
A4: 项目 | B4: 本月读数 | C4: 上月读数 | D4: 本月用量 | E4: 单价 | F4: 本月金额 | G4: 请各商户于当月10日前到管理处交费及换单。如有疑问，请致电：020-22250555
A5: 电费 | B5: =IFERROR(VLOOKUP(K1,'2026.01'!A:Y,14,0),0) -> 21255 | C5: =IFERROR(VLOOKUP(K1,'2026.01'!A:Y,13,0),0) -> 21125 | D5: =IFERROR(VLOOKUP(K1,'2026.01'!A:Y,15,0),0) -> 130 | E5: =IFERROR(VLOOKUP(K1,'2026.01'!A:Y,18,0),0) -> 0.8 | F5: =IFERROR(VLOOKUP(K1,'2026.01'!A:Y,20,0),0) -> 104
A6: 水费 | F6: =IFERROR(VLOOKUP(K1,'2026.01'!A:Y,24,0),0) -> 34
A7: 垃圾费 | F7: =IFERROR(VLOOKUP(K1,'2026.01'!A:Y,12,0),0) -> 160
A8: 租金 | F8: =IFERROR(VLOOKUP(K1,'2026.01'!A:Y,9,0),0) -> 3052
A9: 管理费 | F9: =IFERROR(VLOOKUP(K1,'2026.01'!A:Y,10,0),0) -> 210
A10: 管理费（设施服务费1） | F10: =IFERROR(VLOOKUP(K1,'2026.01'!A:Y,19,0),0) -> 91
A11: 管理费（设施服务费2） | F11: =IFERROR(VLOOKUP(K1,'2026.01'!A:Y,22,0),0) -> 164
A12: 应交合计 | F12: =IFERROR(VLOOKUP(K1,'2026.01'!A:Y,25,0),0) -> 3815
A13: 金额大写 | B13: =IF(F12<0,"金额为负，无效",INT(F12)) -> 3815 | E13: 收款人
A15: 鞋城商铺缴费收据 | K15: 2
A16: 租金期间:2026.1.1-2026.1.31 | G16: =IFERROR(VLOOKUP(K15,'2026.01'!A:Y,2,0),0) -> NO:002
A17: 铺号 | B17: =IFERROR(VLOOKUP(K15,'2026.01'!A:Y,6,0),0) -> 1001 | D17: 铺主 | E17: =IFERROR(VLOOKUP(K15,'2026.01'!A:Y,7,0),0) -> 邓凤强 | G17: 备注
A18: 项目 | B18: 本月读数 | C18: 上月读数 | D18: 本月用量 | E18: 单价 | F18: 本月金额 | G18: 请各商户于当月10日前到管理处交费及换单。如有疑问，请致电：020-22250555
A19: 电费 | B19: =IFERROR(VLOOKUP(K15,'2026.01'!A:Y,14,0),0) -> 5545 | C19: =IFERROR(VLOOKUP(K15,'2026.01'!A:Y,13,0),0) -> 5427 | D19: =IFERROR(VLOOKUP(K15,'2026.01'!A:Y,15,0),0) -> 118 | E19: =IFERROR(VLOOKUP(K15,'2026.01'!A:Y,18,0),0) -> 0.8 | F19: =IFERROR(VLOOKUP(K15,'2026.01'!A:Y,20,0),0) -> 94
A20: 水费 | F20: =IFERROR(VLOOKUP(K15,'2026.01'!A:Y,24,0),0) -> 34
A21: 垃圾费 | F21: =IFERROR(VLOOKUP(K15,'2026.01'!A:Y,12,0),0) -> 160
A22: 租金 | F22: =IFERROR(VLOOKUP(K15,'2026.01'!A:Y,9,0),0) -> 4200
A23: 管理费 | F23: =IFERROR(VLOOKUP(K15,'2026.01'!A:Y,10,0),0) -> 500
A24: 管理费（设施服务费1） | F24: =IFERROR(VLOOKUP(K15,'2026.01'!A:Y,19,0),0) -> 83
A25: 管理费（设施服务费2） | F25: =IFERROR(VLOOKUP(K15,'2026.01'!A:Y,22,0),0) -> 183
A26: 应交合计 | F26: =IFERROR(VLOOKUP(K15,'2026.01'!A:Y,25,0),0) -> 5254
A27: 金额大写 | B27: =IF(F26<0,"金额为负，无效",INT(F26)) -> 5254 | E27: 收款人
A29: 鞋城商铺缴费收据 | K29: 3
A30: 租金期间:2026.1.1-2026.1.31 | G30: =IFERROR(VLOOKUP(K29,'2026.01'!A:Y,2,0),0) -> NO:003
A31: 铺号 | B31: =IFERROR(VLOOKUP(K29,'2026.01'!A:Y,6,0),0) -> 1002 | D31: 铺主 | E31: =IFERROR(VLOOKUP(K29,'2026.01'!A:Y,7,0),0) -> 苏建柳 | G31: 备注
A32: 项目 | B32: 本月读数 | C32: 上月读数 | D32: 本月用量 | E32: 单价 | F32: 本月金额 | G32: 请各商户于当月10日前到管理处交费及换单。如有疑问，请致电：020-22250555
A33: 电费 | B33: =IFERROR(VLOOKUP(K29,'2026.01'!A:Y,14,0),0) -> 8503 | C33: =IFERROR(VLOOKUP(K29,'2026.01'!A:Y,13,0),0) -> 8496 | D33: =IFERROR(VLOOKUP(K29,'2026.01'!A:Y,15,0),0) -> 7 | E33: =IFERROR(VLOOKUP(K29,'2026.01'!A:Y,18,0),0) -> 0.8 | F33: =IFERROR(VLOOKUP(K29,'2026.01'!A:Y,20,0),0) -> 6
A34: 水费 | F34: =IFERROR(VLOOKUP(K29,'2026.01'!A:Y,24,0),0) -> 34
A35: 垃圾费 | F35: =IFERROR(VLOOKUP(K29,'2026.01'!A:Y,12,0),0) -> 160
A36: 租金 | F36: =IFERROR(VLOOKUP(K29,'2026.01'!A:Y,9,0),0) -> 1500
A37: 管理费 | F37: =IFERROR(VLOOKUP(K29,'2026.01'!A:Y,10,0),0) -> 0
A38: 管理费（设施服务费1） | F38: =IFERROR(VLOOKUP(K29,'2026.01'!A:Y,19,0),0) -> 5
A39: 管理费（设施服务费2） | F39: =IFERROR(VLOOKUP(K29,'2026.01'!A:Y,22,0),0) -> 183
A40: 应交合计 | F40: =IFERROR(VLOOKUP(K29,'2026.01'!A:Y,25,0),0) -> 1888
A41: 金额大写 | B41: =IF(F40<0,"金额为负，无效",INT(F40)) -> 1888 | E41: 收款人
A43: 鞋城商铺缴费收据 | K43: 4
A44: 租金期间:2026.1.1-2026.1.31 | G44: =IFERROR(VLOOKUP(K43,'2026.01'!A:Y,2,0),0) -> NO:004
A45: 铺号 | B45: =IFERROR(VLOOKUP(K43,'2026.01'!A:Y,6,0),0) -> 1003/1004 | D45: 铺主 | E45: =IFERROR(VLOOKUP(K43,'2026.01'!A:Y,7,0),0) -> 李鹏飞 | G45: 备注
A46: 项目 | B46: 本月读数 | C46: 上月读数 | D46: 本月用量 | E46: 单价 | F46: 本月金额 | G46: 请各商户于当月10日前到管理处交费及换单。如有疑问，请致电：020-22250555
A47: 电费 | B47: =IFERROR(VLOOKUP(K43,'2026.01'!A:Y,14,0),0) -> 16639 | C47: =IFERROR(VLOOKUP(K43,'2026.01'!A:Y,13,0),0) -> 16619 | D47: =IFERROR(VLOOKUP(K43,'2026.01'!A:Y,15,0),0) -> 20 | E47: =IFERROR(VLOOKUP(K43,'2026.01'!A:Y,18,0),0) -> 0.8 | F47: =IFERROR(VLOOKUP(K43,'2026.01'!A:Y,20,0),0) -> 16
A48: 水费 | F48: =IFERROR(VLOOKUP(K43,'2026.01'!A:Y,24,0),0) -> 85
A49: 垃圾费 | F49: =IFERROR(VLOOKUP(K43,'2026.01'!A:Y,12,0),0) -> 320
A50: 租金 | F50: =IFERROR(VLOOKUP(K43,'2026.01'!A:Y,9,0),0) -> 3000
A51: 管理费 | F51: =IFERROR(VLOOKUP(K43,'2026.01'!A:Y,10,0),0) -> 0
A52: 管理费（设施服务费1） | F52: =IFERROR(VLOOKUP(K43,'2026.01'!A:Y,19,0),0) -> 14
A53: 管理费（设施服务费2） | F53: =IFERROR(VLOOKUP(K43,'2026.01'!A:Y,22,0),0) -> 413
A54: 应交合计 | F54: =IFERROR(VLOOKUP(K43,'2026.01'!A:Y,25,0),0) -> 3848
A55: 金额大写 | B55: =IF(F54<0,"金额为负，无效",INT(F54)) -> 3848 | E55: 收款人
A57: 鞋城商铺缴费收据 | K57: 5
A58: 租金期间:2026.1.1-2026.1.31 | G58: =IFERROR(VLOOKUP(K57,'2026.01'!A:Y,2,0),0) -> NO:005
A59: 铺号 | B59: =IFERROR(VLOOKUP(K57,'2026.01'!A:Y,6,0),0) -> 1005 | D59: 铺主 | E59: =IFERROR(VLOOKUP(K57,'2026.01'!A:Y,7,0),0) -> 黄腾凌 | G59: 备注
A60: 项目 | B60: 本月读数 | C60: 上月读数 | D60: 本月用量 | E60: 单价 | F60: 本月金额 | G60: 请各商户于当月10日前到管理处交费及换单。如有疑问，请致电：020-22250555
A61: 电费 | B61: =IFERROR(VLOOKUP(K57,'2026.01'!A:Y,14,0),0) -> 3354 | C61: =IFERROR(VLOOKUP(K57,'2026.01'!A:Y,13,0),0) -> 3318 | D61: =IFERROR(VLOOKUP(K57,'2026.01'!A:Y,15,0),0) -> 36 | E61: =IFERROR(VLOOKUP(K57,'2026.01'!A:Y,18,0),0) -> 0.8 | F61: =IFERROR(VLOOKUP(K57,'2026.01'!A:Y,20,0),0) -> 29
A62: 水费 | F62: =IFERROR(VLOOKUP(K57,'2026.01'!A:Y,24,0),0) -> 43
A63: 垃圾费 | F63: =IFERROR(VLOOKUP(K57,'2026.01'!A:Y,12,0),0) -> 160
A64: 租金 | F64: =IFERROR(VLOOKUP(K57,'2026.01'!A:Y,9,0),0) -> 1200
A65: 管理费 | F65: =IFERROR(VLOOKUP(K57,'2026.01'!A:Y,10,0),0) -> 200
A66: 管理费（设施服务费1） | F66: =IFERROR(VLOOKUP(K57,'2026.01'!A:Y,19,0),0) -> 25
A67: 管理费（设施服务费2） | F67: =IFERROR(VLOOKUP(K57,'2026.01'!A:Y,22,0),0) -> 228
A68: 应交合计 | F68: =IFERROR(VLOOKUP(K57,'2026.01'!A:Y,25,0),0) -> 1885
A69: 金额大写 | B69: =IF(F68<0,"金额为负，无效",INT(F68)) -> 1885 | E69: 收款人
A71: 鞋城商铺缴费收据 | K71: 6
A72: 租金期间:2026.1.1-2026.1.31 | G72: =IFERROR(VLOOKUP(K71,'2026.01'!A:Y,2,0),0) -> NO:006
A73: 铺号 | B73: =IFERROR(VLOOKUP(K71,'2026.01'!A:Y,6,0),0) -> 1006 | D73: 铺主 | E73: =IFERROR(VLOOKUP(K71,'2026.01'!A:Y,7,0),0) -> 刘展 | G73: 备注
A74: 项目 | B74: 本月读数 | C74: 上月读数 | D74: 本月用量 | E74: 单价 | F74: 本月金额 | G74: 请各商户于当月10日前到管理处交费及换单。如有疑问，请致电：020-22250555
A75: 电费 | B75: =IFERROR(VLOOKUP(K71,'2026.01'!A:Y,14,0),0) -> 4587 | C75: =IFERROR(VLOOKUP(K71,'2026.01'!A:Y,13,0),0) -> 4555 | D75: =IFERROR(VLOOKUP(K71,'2026.01'!A:Y,15,0),0) -> 32 | E75: =IFERROR(VLOOKUP(K71,'2026.01'!A:Y,18,0),0) -> 0.8 | F75: =IFERROR(VLOOKUP(K71,'2026.01'!A:Y,20,0),0) -> 26
A76: 水费 | F76: =IFERROR(VLOOKUP(K71,'2026.01'!A:Y,24,0),0) -> 0
A77: 垃圾费 | F77: =IFERROR(VLOOKUP(K71,'2026.01'!A:Y,12,0),0) -> 160
A78: 租金 | F78: =IFERROR(VLOOKUP(K71,'2026.01'!A:Y,9,0),0) -> 1200
A79: 管理费 | F79: =IFERROR(VLOOKUP(K71,'2026.01'!A:Y,10,0),0) -> 200
A80: 管理费（设施服务费1） | F80: =IFERROR(VLOOKUP(K71,'2026.01'!A:Y,19,0),0) -> 22
A81: 管理费（设施服务费2） | F81: =IFERROR(VLOOKUP(K71,'2026.01'!A:Y,22,0),0) -> 228
A82: 应交合计 | F82: =IFERROR(VLOOKUP(K71,'2026.01'!A:Y,25,0),0) -> 1836
A83: 金额大写 | B83: =IF(F82<0,"金额为负，无效",INT(F82)) -> 1836 | E83: 收款人
A85: 鞋城商铺缴费收据 | K85: 7
A86: 租金期间:2026.1.1-2026.1.31 | G86: =IFERROR(VLOOKUP(K85,'2026.01'!A:Y,2,0),0) -> NO:007
A87: 铺号 | B87: =IFERROR(VLOOKUP(K85,'2026.01'!A:Y,6,0),0) -> 1007 | D87: 铺主 | E87: =IFERROR(VLOOKUP(K85,'2026.01'!A:Y,7,0),0) -> 王正庚 | G87: 备注
A88: 项目 | B88: 本月读数 | C88: 上月读数 | D88: 本月用量 | E88: 单价 | F88: 本月金额 | G88: 请各商户于当月10日前到管理处交费及换单。如有疑问，请致电：020-22250555
A89: 电费 | B89: =IFERROR(VLOOKUP(K85,'2026.01'!A:Y,14,0),0) -> 765 | C89: =IFERROR(VLOOKUP(K85,'2026.01'!A:Y,13,0),0) -> 759 | D89: =IFERROR(VLOOKUP(K85,'2026.01'!A:Y,15,0),0) -> 6 | E89: =IFERROR(VLOOKUP(K85,'2026.01'!A:Y,18,0),0) -> 0.8 | F89: =IFERROR(VLOOKUP(K85,'2026.01'!A:Y,20,0),0) -> 5
A90: 水费 | F90: =IFERROR(VLOOKUP(K85,'2026.01'!A:Y,24,0),0) -> 43
A91: 垃圾费 | F91: =IFERROR(VLOOKUP(K85,'2026.01'!A:Y,12,0),0) -> 160
A92: 租金 | F92: =IFERROR(VLOOKUP(K85,'2026.01'!A:Y,9,0),0) -> 1200
A93: 管理费 | F93: =IFERROR(VLOOKUP(K85,'2026.01'!A:Y,10,0),0) -> 0
A94: 管理费（设施服务费1） | F94: =IFERROR(VLOOKUP(K85,'2026.01'!A:Y,19,0),0) -> 4
A95: 管理费（设施服务费2） | F95: =IFERROR(VLOOKUP(K85,'2026.01'!A:Y,22,0),0) -> 228
A96: 应交合计 | F96: =IFERROR(VLOOKUP(K85,'2026.01'!A:Y,25,0),0) -> 1640
A97: 金额大写 | B97: =IF(F96<0,"金额为负，无效",INT(F96)) -> 1640 | E97: 收款人
A99: 鞋城商铺缴费收据 | K99: 8
A100: 租金期间:2026.1.1-2026.1.31 | G100: =IFERROR(VLOOKUP(K99,'2026.01'!A:Y,2,0),0) -> NO:008
A101: 铺号 | B101: =IFERROR(VLOOKUP(K99,'2026.01'!A:Y,6,0),0) -> 1008/1009 | D101: 铺主 | E101: =IFERROR(VLOOKUP(K99,'2026.01'!A:Y,7,0),0) -> 潭日标 | G101: 备注
A102: 项目 | B102: 本月读数 | C102: 上月读数 | D102: 本月用量 | E102: 单价 | F102: 本月金额 | G102: 请各商户于当月10日前到管理处交费及换单。如有疑问，请致电：020-22250555
A103: 电费 | B103: =IFERROR(VLOOKUP(K99,'2026.01'!A:Y,14,0),0) -> 3682 | C103: =IFERROR(VLOOKUP(K99,'2026.01'!A:Y,13,0),0) -> 3460 | D103: =IFERROR(VLOOKUP(K99,'2026.01'!A:Y,15,0),0) -> 222 | E103: =IFERROR(VLOOKUP(K99,'2026.01'!A:Y,18,0),0) -> 0.8 | F103: =IFERROR(VLOOKUP(K99,'2026.01'!A:Y,20,0),0) -> 178
A104: 水费 | F104: =IFERROR(VLOOKUP(K99,'2026.01'!A:Y,24,0),0) -> 94
A105: 垃圾费 | F105: =IFERROR(VLOOKUP(K99,'2026.01'!A:Y,12,0),0) -> 320
A106: 租金 | F106: =IFERROR(VLOOKUP(K99,'2026.01'!A:Y,9,0),0) -> 2500
A107: 管理费 | F107: =IFERROR(VLOOKUP(K99,'2026.01'!A:Y,10,0),0) -> 0
...

Sheet 2026.01
A1: 国大鞋城2026年1月份收费明细表 | M1: 1 2 3楼有中央空调 要分摊电费 | N1: 1 2 3楼有中央空调 要分摊电费
B2: 序号 | C2: 楼层 | F2: 档口号 | G2: 商户名 | H2: 面积 | I2: 租金 | J2: 管理费 | M2: 上月电表读数 | N2: 本月电表读数 | O2: 用电量 | P2: 电费分摊 | Q2: 本月用电 | R2: 电费单价 | S2: 市场服务费 | T2: 用电金额 | U2: 照明+空调公摊 | V2: 金额 | W2: 水费公摊 | X2: 水费 | Y2: 本月合计 | Z2: 前期欠款 | AA2: 折扣金额 | AE2: 预交款 | AI2: 应交合计 | AJ2: 滞纳金 | AK2: 实收款 | AQ2: 其他折扣 | AV2: 未交金额
D3: 档口 | E3: 面积 | K3: 租金及管理费 | L3: 垃圾费 | AA3: 租金 | AB3: 管理费 | AC3: 水电费 | AD3: 小计 | AE3: 期初 | AF3: 本月预收 | AG3: 本月抵扣 | AH3: 期末（剩余未抵） | AK3: 收款日期 | AL3: 现金 | AM3: 微信 | AN3: 银行 | AO3: 建行 | AP3: 小计 | AQ3: 协议减免 | AR3: 租金折扣 | AS3: 空调折扣 | AT3: 押金抵扣 | AU3: 小计 | AW3: 备注
A4: =SUBTOTAL(2,$Y$4:Y4) -> 1 | B4: NO:001 | C4: 一楼商铺 | D4: 1001-01（临一） | E4: 19.5 | F4: 1001-01（临一） | G4: 何具达 | H4: =E4 -> 19.5 | I4: 3052 | J4: 210 | K4: =I4+J4 -> 3262 | L4: 160 | M4: 21125 | N4: 21255 | O4: =N4-M4 -> 130 | P4: =ROUND(H4*0,0) -> 0 | Q4: =O4+P4 -> 130 | R4: 0.8 | S4: =ROUND(Q4*0.7,0) -> 91 | T4: =ROUND(Q4*R4,0) -> 104 | U4: =ROUND(H4*5.6,0) -> 109 | V4: =ROUND(U4*1.5,0) -> 164 | W4: =ROUND(H4*0.2,0) -> 4 | X4: =ROUND(W4*8.5,0) -> 34 | Y4: =I4+J4+L4+S4+T4+V4+X4 -> 3815 | AD4: =AA4+AB4+AC4 -> 0 | AH4: =AE4+AF4-AG4 -> 0 | AI4: =Y4+Z4+AJ4-AD4-AG4 -> 3815 | AP4: =AL4+AN4+AM4+AO4 -> 0 | AU4: =SUM(AQ4:AT4) -> 0 | AV4: =AI4-AP4-AU4 -> 3815
A5: =SUBTOTAL(2,$Y$4:Y5) -> 2 | B5: NO:002 | C5: 一楼商铺 | D5: 1001 | E5: 21.87 | F5: 1001 | G5: 邓凤强 | H5: =E5 -> 21.87 | I5: 4200 | J5: 500 | K5: =I5+J5 -> 4700 | L5: 160 | M5: 5427 | N5: 5545 | O5: =N5-M5 -> 118 | P5: =ROUND(H5*0,0) -> 0 | Q5: =O5+P5 -> 118 | R5: 0.8 | S5: =ROUND(Q5*0.7,0) -> 83 | T5: =ROUND(Q5*R5,0) -> 94 | U5: =ROUND(H5*5.6,0) -> 122 | V5: =ROUND(U5*1.5,0) -> 183 | W5: =ROUND(H5*0.2,0) -> 4 | X5: =ROUND(W5*8.5,0) -> 34 | Y5: =I5+J5+L5+S5+T5+V5+X5 -> 5254 | AD5: =AA5+AB5+AC5 -> 0 | AH5: =AE5+AF5-AG5 -> 0 | AI5: =Y5+Z5+AJ5-AD5-AG5 -> 5254 | AP5: =AL5+AN5+AM5+AO5 -> 0 | AU5: =SUM(AQ5:AT5) -> 0 | AV5: =AI5-AP5-AU5 -> 5254
A6: =SUBTOTAL(2,$Y$4:Y6) -> 3 | B6: NO:003 | C6: 一楼商铺 | D6: 1002 | E6: 21.87 | F6: 1002 | G6: 苏建柳 | H6: =E6 -> 21.87 | I6: 1500 | K6: =I6+J6 -> 1500 | L6: 160 | M6: 8496 | N6: 8503 | O6: =N6-M6 -> 7 | P6: =ROUND(H6*0,0) -> 0 | Q6: =O6+P6 -> 7 | R6: 0.8 | S6: =ROUND(Q6*0.7,0) -> 5 | T6: =ROUND(Q6*R6,0) -> 6 | U6: =ROUND(H6*5.6,0) -> 122 | V6: =ROUND(U6*1.5,0) -> 183 | W6: =ROUND(H6*0.2,0) -> 4 | X6: =ROUND(W6*8.5,0) -> 34 | Y6: =I6+J6+L6+S6+T6+V6+X6 -> 1888 | AD6: =AA6+AB6+AC6 -> 0 | AH6: =AE6+AF6-AG6 -> 0 | AI6: =Y6+Z6+AJ6-AD6-AG6 -> 1888 | AP6: =AL6+AN6+AM6+AO6 -> 0 | AU6: =SUM(AQ6:AT6) -> 0 | AV6: =AI6-AP6-AU6 -> 1888
A7: =SUBTOTAL(2,$Y$4:Y7) -> 4 | B7: NO:004 | C7: 一楼商铺 | D7: 1003-1004 | E7: =21.87+27.15 -> 49.02 | F7: 1003/1004 | G7: 李鹏飞 | H7: 49.02 | I7: 3000 | K7: =I7+J7 -> 3000 | L7: 320 | M7: =7009+9610 -> 16619 | N7: =7029+9610 -> 16639 | O7: =N7-M7 -> 20 | P7: =ROUND(H7*0,0) -> 0 | Q7: =O7+P7 -> 20 | R7: 0.8 | S7: =ROUND(Q7*0.7,0) -> 14 | T7: =ROUND(Q7*R7,0) -> 16 | U7: =ROUND(H7*5.6,0) -> 275 | V7: =ROUND(U7*1.5,0) -> 413 | W7: =ROUND(H7*0.2,0) -> 10 | X7: =ROUND(W7*8.5,0) -> 85 | Y7: =I7+J7+L7+S7+T7+V7+X7 -> 3848 | AD7: =AA7+AB7+AC7 -> 0 | AH7: =AE7+AF7-AG7 -> 0 | AI7: =Y7+Z7+AJ7-AD7-AG7 -> 3848 | AP7: =AL7+AN7+AM7+AO7 -> 0 | AU7: =SUM(AQ7:AT7) -> 0 | AV7: =AI7-AP7-AU7 -> 3848
A8: =SUBTOTAL(2,$Y$4:Y8) -> 5 | B8: NO:005 | C8: 一楼商铺 | D8: 1005 | E8: 27.15 | F8: 1005 | G8: 黄腾凌 | H8: 27.15 | I8: 1200 | J8: 200 | K8: =I8+J8 -> 1400 | L8: 160 | M8: 3318 | N8: 3354 | O8: =N8-M8 -> 36 | P8: =ROUND(H8*0,0) -> 0 | Q8: =O8+P8 -> 36 | R8: 0.8 | S8: =ROUND(Q8*0.7,0) -> 25 | T8: =ROUND(Q8*R8,0) -> 29 | U8: =ROUND(H8*5.6,0) -> 152 | V8: =ROUND(U8*1.5,0) -> 228 | W8: =ROUND(H8*0.2,0) -> 5 | X8: =ROUND(W8*8.5,0) -> 43 | Y8: =I8+J8+L8+S8+T8+V8+X8 -> 1885 | AD8: =AA8+AB8+AC8 -> 0 | AH8: =AE8+AF8-AG8 -> 0 | AI8: =Y8+Z8+AJ8-AD8-AG8 -> 1885 | AP8: =AL8+AN8+AM8+AO8 -> 0 | AU8: =SUM(AQ8:AT8) -> 0 | AV8: =AI8-AP8-AU8 -> 1885
A9: =SUBTOTAL(2,$Y$4:Y9) -> 6 | B9: NO:006 | C9: 一楼商铺 | D9: 1006 | E9: 27.15 | F9: 1006 | G9: 刘展 | H9: 27.15 | I9: 1200 | J9: 200 | K9: =I9+J9 -> 1400 | L9: 160 | M9: 4555 | N9: 4587 | O9: =N9-M9 -> 32 | P9: =ROUND(H9*0,0) -> 0 | Q9: =O9+P9 -> 32 | R9: 0.8 | S9: =ROUND(Q9*0.7,0) -> 22 | T9: =ROUND(Q9*R9,0) -> 26 | U9: =ROUND(H9*5.6,0) -> 152 | V9: =ROUND(U9*1.5,0) -> 228 | W9: 0 | X9: =ROUND(W9*8.5,0) -> 0 | Y9: =I9+J9+L9+S9+T9+V9+X9 -> 1836 | AD9: =AA9+AB9+AC9 -> 0 | AH9: =AE9+AF9-AG9 -> 0 | AI9: =Y9+Z9+AJ9-AD9-AG9 -> 1836 | AP9: =AL9+AN9+AM9+AO9 -> 0 | AU9: =SUM(AQ9:AT9) -> 0 | AV9: =AI9-AP9-AU9 -> 1836
A10: =SUBTOTAL(2,$Y$4:Y10) -> 7 | B10: NO:007 | C10: 一楼商铺 | D10: 1007 | E10: 27.15 | F10: 1007 | G10: 王正庚 | H10: =E10 -> 27.15 | I10: 1200 | K10: =I10+J10 -> 1200 | L10: 160 | M10: 759 | N10: 765 | O10: =N10-M10 -> 6 | P10: =ROUND(H10*0,0) -> 0 | Q10: =O10+P10 -> 6 | R10: 0.8 | S10: =ROUND(Q10*0.7,0) -> 4 | T10: =ROUND(Q10*R10,0) -> 5 | U10: =ROUND(H10*5.6,0) -> 152 | V10: =ROUND(U10*1.5,0) -> 228 | W10: =ROUND(H10*0.2,0) -> 5 | X10: =ROUND(W10*8.5,0) -> 43 | Y10: =I10+J10+L10+S10+T10+V10+X10 -> 1640 | AD10: =AA10+AB10+AC10 -> 0 | AH10: =AE10+AF10-AG10 -> 0 | AI10: =Y10+Z10+AJ10-AD10-AG10 -> 1640 | AP10: =AL10+AN10+AM10+AO10 -> 0 | AU10: =SUM(AQ10:AT10) -> 0 | AV10: =AI10-AP10-AU10 -> 1640
A11: =SUBTOTAL(2,$Y$4:Y11) -> 8 | B11: NO:008 | C11: 一楼商铺 | D11: 1008 | E11: 27.15 | F11: 1008/1009 | G11: 潭日标 | H11: =E11*2 -> 54.3 | I11: 2500 | K11: =I11+J11 -> 2500 | L11: 320 | M11: 3460 | N11: 3682 | O11: =N11-M11 -> 222 | P11: =ROUND(H11*0,0) -> 0 | Q11: =O11+P11 -> 222 | R11: 0.8 | S11: =ROUND(Q11*0.7,0) -> 155 | T11: =ROUND(Q11*R11,0) -> 178 | U11: =ROUND(H11*0,0) -> 0 | V11: =ROUND(U11*1.5,0) -> 0 | W11: =ROUND(H11*0.2,0) -> 11 | X11: =ROUND(W11*8.5,0) -> 94 | Y11: =I11+J11+L11+S11+T11+V11+X11 -> 3247 | AD11: =AA11+AB11+AC11 -> 0 | AH11: =AE11+AF11-AG11 -> 0 | AI11: =Y11+Z11+AJ11-AD11-AG11 -> 3247 | AP11: =AL11+AN11+AM11+AO11 -> 0 | AU11: =SUM(AQ11:AT11) -> 0 | AV11: =AI11-AP11-AU11 -> 3247
A12: =SUBTOTAL(2,$Y$4:Y12) -> 9 | B12: NO:009 | C12: 一楼商铺 | D12: 1009 | E12: 27.15 | F12: 1009 | G12: 潭日标 | K12: =I12+J12 -> 0 | L12: 0 | M12: 3552 | N12: 3625 | O12: =N12-M12 -> 73 | P12: =ROUND(H12*0,0) -> 0 | Q12: =O12+P12 -> 73 | R12: 0.8 | S12: =ROUND(Q12*0.7,0) -> 51 | T12: =ROUND(Q12*R12,0) -> 58 | U12: =ROUND(H12*5.6,0) -> 0 | V12: =ROUND(U12*1.5,0) -> 0 | W12: =ROUND(H12*0.2,0) -> 0 | X12: =ROUND(W12*8.5,0) -> 0 | Y12: =I12+J12+L12+S12+T12+V12+X12 -> 109 | AD12: =AA12+AB12+AC12 -> 0 | AH12: =AE12+AF12-AG12 -> 0 | AI12: =Y12+Z12+AJ12-AD12-AG12 -> 109 | AP12: =AL12+AN12+AM12+AO12 -> 0 | AU12: =SUM(AQ12:AT12) -> 0 | AV12: =AI12-AP12-AU12 -> 109
A13: =SUBTOTAL(2,$Y$4:Y13) -> 10 | B13: NO:010 | C13: 一楼商铺 | D13: 1010 | E13: 23.77 | F13: 1010 | G13: 王长梅 | H13: =E13 -> 23.77 | I13: 1500 | K13: =I13+J13 -> 1500 | L13: 160 | M13: 8464 | N13: 8551 | O13: =N13-M13 -> 87 | P13: =ROUND(H13*0,0) -> 0 | Q13: =O13+P13 -> 87 | R13: 0.8 | S13: =ROUND(Q13*0.7,0) -> 61 | T13: =ROUND(Q13*R13,0) -> 70 | U13: =ROUND(H13*5.6,0) -> 133 | V13: =ROUND(U13*1.5,0) -> 200 | W13: =ROUND(H13*0.2,0) -> 5 | X13: =ROUND(W13*8.5,0) -> 43 | Y13: =I13+J13+L13+S13+T13+V13+X13 -> 2034 | AD13: =AA13+AB13+AC13 -> 0 | AH13: =AE13+AF13-AG13 -> 0 | AI13: =Y13+Z13+AJ13-AD13-AG13 -> 2034 | AP13: =AL13+AN13+AM13+AO13 -> 0 | AU13: =SUM(AQ13:AT13) -> 0 | AV13: =AI13-AP13-AU13 -> 2034
A14: =SUBTOTAL(2,$Y$4:Y14) -> 11 | B14: NO:011 | C14: 一楼商铺 | D14: 1011 | E14: 27.15 | F14: 1011 | G14: 段邦彦 | H14: 27.15 | I14: 750 | K14: =I14+J14 -> 750 | L14: 160 | M14: 2210 | N14: 2260 | O14: =N14-M14 -> 50 | P14: =ROUND(H14*0,0) -> 0 | Q14: =O14+P14 -> 50 | R14: 0.8 | S14: =ROUND(Q14*0.7,0) -> 35 | T14: =ROUND(Q14*R14,0) -> 40 | U14: =ROUND(H14*0,0) -> 0 | V14: =ROUND(U14*1.5,0) -> 0 | W14: =ROUND(H14*0.2,0) -> 5 | X14: =ROUND(W14*8.5,0) -> 43 | Y14: =I14+J14+L14+S14+T14+V14+X14 -> 1028 | AD14: =AA14+AB14+AC14 -> 0 | AH14: =AE14+AF14-AG14 -> 0 | AI14: =Y14+Z14+AJ14-AD14-AG14 -> 1028 | AP14: =AL14+AN14+AM14+AO14 -> 0 | AU14: =SUM(AQ14:AT14) -> 0 | AV14: =AI14-AP14-AU14 -> 1028
A15: =SUBTOTAL(2,$Y$4:Y15) -> 12 | B15: NO:012 | C15: 一楼商铺 | D15: 1012 | E15: 27.5 | F15: 1012 | G15: 李文学 | H15: 27.5 | I15: 750 | J15: 0 | K15: =I15+J15 -> 750 | L15: 160 | M15: 2479 | N15: 2584 | O15: =N15-M15 -> 105 | P15: =ROUND(H15*0,0) -> 0 | Q15: =O15+P15 -> 105 | R15: 0.8 | S15: =ROUND(Q15*0.7,0) -> 74 | T15: =ROUND(Q15*R15,0) -> 84 | U15: =ROUND(H15*0,0) -> 0 | V15: =ROUND(U15*1.5,0) -> 0 | W15: =ROUND(H15*0.2,0) -> 6 | X15: =ROUND(W15*8.5,0) -> 51 | Y15: =I15+J15+L15+S15+T15+V15+X15 -> 1119 | AD15: =AA15+AB15+AC15 -> 0 | AH15: =AE15+AF15-AG15 -> 0 | AI15: =Y15+Z15+AJ15-AD15-AG15 -> 1119 | AP15: =AL15+AN15+AM15+AO15 -> 0 | AU15: =SUM(AQ15:AT15) -> 0 | AV15: =AI15-AP15-AU15 -> 1119
A16: =SUBTOTAL(2,$Y$4:Y16) -> 13 | B16: NO:013 | C16: 一楼商铺 | D16: 1013 | E16: 27.15 | F16: 1013 | G16: 揭英祥 | H16: =E16 -> 27.15 | I16: 1200 | K16: =I16+J16 -> 1200 | L16: 160 | M16: 4343 | N16: 4410 | O16: =N16-M16 -> 67 | P16: =ROUND(H16*0,0) -> 0 | Q16: =O16+P16 -> 67 | R16: 0.8 | S16: =ROUND(Q16*0.7,0) -> 47 | T16: =ROUND(Q16*R16,0) -> 54 | U16: =ROUND(H16*5.6,0) -> 152 | V16: =ROUND(U16*1.5,0) -> 228 | W16: =ROUND(H16*0.2,0) -> 5 | X16: =ROUND(W16*8.5,0) -> 43 | Y16: =I16+J16+L16+S16+T16+V16+X16 -> 1732 | AD16: =AA16+AB16+AC16 -> 0 | AH16: =AE16+AF16-AG16 -> 0 | AI16: =Y16+Z16+AJ16-AD16-AG16 -> 1732 | AP16: =AL16+AN16+AM16+AO16 -> 0 | AU16: =SUM(AQ16:AT16) -> 0 | AV16: =AI16-AP16-AU16 -> 1732
A17: =SUBTOTAL(2,$Y$4:Y17) -> 14 | B17: NO:014 | C17: 一楼商铺 | D17: 1014 | E17: 27.15 | F17: 1014 | G17: 陈文彬 | H17: 27.15 | I17: 1500 | J17: 0 | K17: =I17+J17 -> 1500 | L17: 160 | M17: 5894 | N17: 6102 | O17: =N17-M17 -> 208 | P17: =ROUND(H17*0,0) -> 0 | Q17: =O17+P17 -> 208 | R17: 0.8 | S17: =ROUND(Q17*0.7,0) -> 146 | T17: =ROUND(Q17*R17,0) -> 166 | U17: =ROUND(H17*5.6,0) -> 152 | V17: =ROUND(U17*1.5,0) -> 228 | W17: =ROUND(H17*0.2,0) -> 5 | X17: =ROUND(W17*8.5,0) -> 43 | Y17: =I17+J17+L17+S17+T17+V17+X17 -> 2243 | AD17: =AA17+AB17+AC17 -> 0 | AH17: =AE17+AF17-AG17 -> 0 | AI17: =Y17+Z17+AJ17-AD17-AG17 -> 2243 | AP17: =AL17+AN17+AM17+AO17 -> 0 | AU17: =SUM(AQ17:AT17) -> 0 | AV17: =AI17-AP17-AU17 -> 2243
A18: =SUBTOTAL(2,$Y$4:Y18) -> 15 | B18: NO:015 | C18: 一楼商铺 | D18: 1015 | E18: 27.15 | F18: 1015 | G18: 张平君 | H18: 27.15 | I18: 1200 | J18: 0 | K18: =I18+J18 -> 1200 | L18: 160 | M18: 5484 | N18: 5506 | O18: =N18-M18 -> 22 | P18: =ROUND(H18*0,0) -> 0 | Q18: =O18+P18 -> 22 | R18: 0.8 | S18: =ROUND(Q18*0.7,0) -> 15 | T18: =ROUND(Q18*R18,0) -> 18 | U18: =ROUND(H18*5.6,0) -> 152 | V18: =ROUND(U18*1.5,0) -> 228 | W18: =ROUND(H18*0.2,0) -> 5 | X18: =ROUND(W18*8.5,0) -> 43 | Y18: =I18+J18+L18+S18+T18+V18+X18 -> 1664 | AD18: =AA18+AB18+AC18 -> 0 | AH18: =AE18+AF18-AG18 -> 0 | AI18: =Y18+Z18+AJ18-AD18-AG18 -> 1664 | AP18: =AL18+AN18+AM18+AO18 -> 0 | AU18: =SUM(AQ18:AT18) -> 0 | AV18: =AI18-AP18-AU18 -> 1664
A19: =SUBTOTAL(2,$Y$4:Y19) -> 16 | B19: NO:016 | C19: 一楼商铺 | D19: 1016-1017 | E19: =27.15+27.5 -> 54.65 | F19: 1016/1017 | G19: 卢汉总 | H19: =E19 -> 54.65 | I19: 2800 | J19: 200 | K19: =I19+J19 -> 3000 | L19: 320 | M19: =5382+1645 -> 7027 | N19: =5413+1699 -> 7112 | O19: =N19-M19 -> 85 | P19: =ROUND(H19*0,0) -> 0 | Q19: =O19+P19 -> 85 | R19: 0.8 | S19: =ROUND(Q19*0.7,0) -> 60 | T19: =ROUND(Q19*R19,0) -> 68 | U19: =ROUND(H19*5.6,0) -> 306 | V19: =ROUND(U19*1.5,0) -> 459 | W19: =ROUND(H19*0.2,0) -> 11 | X19: =ROUND(W19*8.5,0) -> 94 | Y19: =I19+J19+L19+S19+T19+V19+X19 -> 4001 | AD19: =AA19+AB19+AC19 -> 0 | AH19: =AE19+AF19-AG19 -> 0 | AI19: =Y19+Z19+AJ19-AD19-AG19 -> 4001 | AP19: =AL19+AN19+AM19+AO19 -> 0 | AU19: =SUM(AQ19:AT19) -> 0 | AV19: =AI19-AP19-AU19 -> 4001
A20: =SUBTOTAL(2,$Y$4:Y20) -> 17 | B20: NO:017 | C20: 一楼商铺 | D20: 1018 | E20: 27.5 | F20: 1018 | G20: 白成滔 | H20: =E20 -> 27.5 | I20: 2000 | J20: 0 | K20: =I20+J20 -> 2000 | L20: 160 | M20: 4204 | N20: 4239 | O20: =N20-M20 -> 35 | P20: =ROUND(H20*0,0) -> 0 | Q20: =O20+P20 -> 35 | R20: 0.8 | S20: =ROUND(Q20*0.7,0) -> 25 | T20: =ROUND(Q20*R20,0) -> 28 | U20: =ROUND(H20*5.6,0) -> 154 | V20: =ROUND(U20*1.5,0) -> 231 | W20: =ROUND(H20*0.2,0) -> 6 | X20: =ROUND(W20*8.5,0) -> 51 | Y20: =I20+J20+L20+S20+T20+V20+X20 -> 2495 | AD20: =AA20+AB20+AC20 -> 0 | AH20: =AE20+AF20-AG20 -> 0 | AI20: =Y20+Z20+AJ20-AD20-AG20 -> 2495 | AP20: =AL20+AN20+AM20+AO20 -> 0 | AU20: =SUM(AQ20:AT20) -> 0 | AV20: =AI20-AP20-AU20 -> 2495
A21: =SUBTOTAL(2,$Y$4:Y21) -> 18 | B21: NO:018 | C21: 一楼商铺 | D21: 1019 | E21: 27.15 | F21: 1019 | G21: 王长梅 | H21: 27.15 | I21: 1200 | K21: =I21+J21 -> 1200 | L21: 160 | M21: 1623 | N21: 1634 | O21: =N21-M21 -> 11 | P21: =ROUND(H21*0,0) -> 0 | Q21: =O21+P21 -> 11 | R21: 0.8 | S21: =ROUND(Q21*0.7,0) -> 8 | T21: =ROUND(Q21*R21,0) -> 9 | U21: =ROUND(H21*5.6,0) -> 152 | V21: =ROUND(U21*1.5,0) -> 228 | W21: 5 | X21: =ROUND(W21*8.5,0) -> 43 | Y21: =I21+J21+L21+S21+T21+V21+X21 -> 1648 | AD21: =AA21+AB21+AC21 -> 0 | AH21: =AE21+AF21-AG21 -> 0 | AI21: =Y21+Z21+AJ21-AD21-AG21 -> 1648 | AP21: =AL21+AN21+AM21+AO21 -> 0 | AU21: =SUM(AQ21:AT21) -> 0 | AV21: =AI21-AP21-AU21 -> 1648
A22: =SUBTOTAL(2,$Y$4:Y22) -> 19 | B22: NO:019 | C22: 一楼商铺 | D22: 1020 | E22: 27.15 | F22: 1020 | G22: 张爱玲 | H22: =E22 -> 27.15 | I22: 1200 | J22: 0 | K22: =I22+J22 -> 1200 | L22: 160 | M22: 9421 | N22: 9455 | O22: =N22-M22 -> 34 | P22: =ROUND(H22*0,0) -> 0 | Q22: =O22+P22 -> 34 | R22: 0.8 | S22: =ROUND(Q22*0.7,0) -> 24 | T22: =ROUND(Q22*R22,0) -> 27 | U22: =ROUND(H22*5.6,0) -> 152 | V22: =ROUND(U22*1.5,0) -> 228 | W22: =ROUND(H22*0.2,0) -> 5 | X22: =ROUND(W22*8.5,0) -> 43 | Y22: =I22+J22+L22+S22+T22+V22+X22 -> 1682 | AD22: =AA22+AB22+AC22 -> 0 | AH22: =AE22+AF22-AG22 -> 0 | AI22: =Y22+Z22+AJ22-AD22-AG22 -> 1682 | AP22: =AL22+AN22+AM22+AO22 -> 0 | AU22: =SUM(AQ22:AT22) -> 0 | AV22: =AI22-AP22-AU22 -> 1682
A23: =SUBTOTAL(2,$Y$4:Y23) -> 20 | B23: NO:020 | C23: 一楼商铺 | D23: 1021 | E23: 27.15 | F23: 1021 | G23: 刘光全 | H23: =E23 -> 27.15 | I23: 1200 | J23: 200 | K23: =I23+J23 -> 1400 | L23: 160 | M23: 6380 | N23: 6424 | O23: =N23-M23 -> 44 | P23: =ROUND(H23*0,0) -> 0 | Q23: =O23+P23 -> 44 | R23: 0.8 | S23: =ROUND(Q23*0.7,0) -> 31 | T23: =ROUND(Q23*R23,0) -> 35 | U23: =ROUND(H23*5.6,0) -> 152 | V23: =ROUND(U23*1.5,0) -> 228 | W23: =ROUND(H23*0.2,0) -> 5 | X23: =ROUND(W23*8.5,0) -> 43 | Y23: =I23+J23+L23+S23+T23+V23+X23 -> 1897 | AD23: =AA23+AB23+AC23 -> 0 | AH23: =AE23+AF23-AG23 -> 0 | AI23: =Y23+Z23+AJ23-AD23-AG23 -> 1897 | AP23: =AL23+AN23+AM23+AO23 -> 0 | AU23: =SUM(AQ23:AT23) -> 0 | AV23: =AI23-AP23-AU23 -> 1897
A24: =SUBTOTAL(2,$Y$4:Y24) -> 21 | B24: NO:021 | C24: 一楼商铺 | D24: 1022 | E24: 56.26 | F24: 1022 | G24: 庄诗霖 | H24: =E24 -> 56.26 | I24: 2200 | K24: =I24+J24 -> 2200 | L24: 160 | M24: 3123 | N24: 3147 | O24: =N24-M24 -> 24 | P24: =ROUND(H24*0,0) -> 0 | Q24: =O24+P24 -> 24 | R24: 0.8 | S24: =ROUND(Q24*0.7,0) -> 17 | T24: =ROUND(Q24*R24,0) -> 19 | U24: =ROUND(H24*0,0) -> 0 | V24: =ROUND(U24*1.5,0) -> 0 | W24: =ROUND(H24*0.2,0) -> 11 | X24: =ROUND(W24*8.5,0) -> 94 | Y24: =I24+J24+L24+S24+T24+V24+X24 -> 2490 | AD24: =AA24+AB24+AC24 -> 0 | AH24: =AE24+AF24-AG24 -> 0 | AI24: =Y24+Z24+AJ24-AD24-AG24 -> 2490 | AP24: =AL24+AN24+AM24+AO24 -> 0 | AU24: =SUM(AQ24:AT24) -> 0 | AV24: =AI24-AP24-AU24 -> 2490
A25: =SUBTOTAL(2,$Y$4:Y25) -> 22 | B25: NO:022 | C25: 一楼商铺 | D25: 1023 | E25: 31.79 | F25: 1023 | G25: 黎培健 | H25: =E25 -> 31.79 | I25: 600 | J25: 0 | K25: =I25+J25 -> 600 | L25: 160 | M25: 2500 | N25: 2568 | O25: =N25-M25 -> 68 | P25: =ROUND(H25*0,0) -> 0 | Q25: =O25+P25 -> 68 | R25: 0.8 | S25: =ROUND(Q25*0.7,0) -> 48 | T25: =ROUND(Q25*R25,0) -> 54 | U25: =ROUND(H25*0,0) -> 0 | V25: =ROUND(U25*1.5,0) -> 0 | W25: =ROUND(H25*0.2,0) -> 6 | X25: =ROUND(W25*8.5,0) -> 51 | Y25: =I25+J25+L25+S25+T25+V25+X25 -> 913 | AD25: =AA25+AB25+AC25 -> 0 | AH25: =AE25+AF25-AG25 -> 0 | AI25: =Y25+Z25+AJ25-AD25-AG25 -> 913 | AP25: =AL25+AN25+AM25+AO25 -> 0 | AU25: =SUM(AQ25:AT25) -> 0 | AV25: =AI25-AP25-AU25 -> 913
A26: =SUBTOTAL(2,$Y$4:Y26) -> 23 | B26: NO:023 | C26: 一楼商铺 | D26: 1024 | E26: 43.89 | F26: 1024 | G26: 王小军 | H26: =E26 -> 43.89 | I26: 1448 | K26: =I26+J26 -> 1448 | L26: 160 | M26: 593 | N26: 628 | O26: =N26-M26 -> 35 | P26: =ROUND(H26*0,0) -> 0 | Q26: =O26+P26 -> 35 | R26: 0.8 | S26: =ROUND(Q26*0.7,0) -> 25 | T26: =ROUND(Q26*R26,0) -> 28 | U26: =ROUND(H26*0,0) -> 0 | V26: =ROUND(U26*1.5,0) -> 0 | W26: =ROUND(H26*0.2,0) -> 9 | X26: =ROUND(W26*8.5,0) -> 77 | Y26: =I26+J26+L26+S26+T26+V26+X26 -> 1738 | AD26: =AA26+AB26+AC26 -> 0 | AH26: =AE26+AF26-AG26 -> 0 | AI26: =Y26+Z26+AJ26-AD26-AG26 -> 1738 | AP26: =AL26+AN26+AM26+AO26 -> 0 | AU26: =SUM(AQ26:AT26) -> 0 | AV26: =AI26-AP26-AU26 -> 1738
A27: =SUBTOTAL(2,$Y$4:Y27) -> 24 | B27: NO:024 | C27: 一楼商铺 | D27: 1025 | E27: 27.15 | F27: 1025 | G27: 李雄辉 | H27: =E27 -> 27.15 | I27: 4200 | J27: 500 | K27: =I27+J27 -> 4700 | L27: 160 | M27: 1436 | N27: 1448 | O27: =N27-M27 -> 12 | P27: =ROUND(H27*0,0) -> 0 | Q27: =O27+P27 -> 12 | R27: 0.8 | S27: =ROUND(Q27*0.7,0) -> 8 | T27: =ROUND(Q27*R27,0) -> 10 | U27: =ROUND(H27*5.6,0) -> 152 | V27: =ROUND(U27*1.5,0) -> 228 | W27: =ROUND(H27*0.2,0) -> 5 | X27: =ROUND(W27*8.5,0) -> 43 | Y27: =I27+J27+L27+S27+T27+V27+X27 -> 5149 | AD27: =AA27+AB27+AC27 -> 0 | AH27: =AE27+AF27-AG27 -> 0 | AI27: =Y27+Z27+AJ27-AD27-AG27 -> 5149 | AP27: =AL27+AN27+AM27+AO27 -> 0 | AU27: =SUM(AQ27:AT27) -> 0 | AV27: =AI27-AP27-AU27 -> 5149
A28: =SUBTOTAL(2,$Y$4:Y28) -> 25 | B28: NO:025 | C28: 一楼商铺 | D28: 1025-A | E28: 26.45 | F28: 1025-A | G28: 苏建柳 | H28: =E28 -> 26.45 | I28: 2206 | J28: 250 | K28: =I28+J28 -> 2456 | L28: 160 | M28: 4759 | N28: 4859 | O28: =N28-M28 -> 100 | P28: =ROUND(H28*0,0) -> 0 | Q28: =O28+P28 -> 100 | R28: 0.8 | S28: =ROUND(Q28*0.7,0) -> 70 | T28: =ROUND(Q28*R28,0) -> 80 | U28: =ROUND(H28*5.6,0) -> 148 | V28: =ROUND(U28*1.5,0) -> 222 | W28: =ROUND(H28*0.2,0) -> 5 | X28: =ROUND(W28*8.5,0) -> 43 | Y28: =I28+J28+L28+S28+T28+V28+X28 -> 3031 | AD28: =AA28+AB28+AC28 -> 0 | AH28: =AE28+AF28-AG28 -> 0 | AI28: =Y28+Z28+AJ28-AD28-AG28 -> 3031 | AP28: =AL28+AN28+AM28+AO28 -> 0 | AU28: =SUM(AQ28:AT28) -> 0 | AV28: =AI28-AP28-AU28 -> 3031
A29: =SUBTOTAL(2,$Y$4:Y29) -> 26 | B29: NO:026 | C29: 一楼商铺 | D29: 1026 | E29: 27.15 | F29: 1026 | G29: 马旦 | H29: =E29 -> 27.15 | I29: 4202 | J29: 500 | K29: =I29+J29 -> 4702 | L29: 160 | M29: 4176 | N29: 4216 | O29: =N29-M29 -> 40 | P29: =ROUND(H29*0,0) -> 0 | Q29: =O29+P29 -> 40 | R29: 0.8 | S29: =ROUND(Q29*0.7,0) -> 28 | T29: =ROUND(Q29*R29,0) -> 32 | U29: =ROUND(H29*5.6,0) -> 152 | V29: =ROUND(U29*1.5,0) -> 228 | W29: =ROUND(H29*0.2,0) -> 5 | X29: =ROUND(W29*8.5,0) -> 43 | Y29: =I29+J29+L29+S29+T29+V29+X29 -> 5193 | AD29: =AA29+AB29+AC29 -> 0 | AH29: =AE29+AF29-AG29 -> 0 | AI29: =Y29+Z29+AJ29-AD29-AG29 -> 5193 | AP29: =AL29+AN29+AM29+AO29 -> 0 | AU29: =SUM(AQ29:AT29) -> 0 | AV29: =AI29-AP29-AU29 -> 5193
A30: =SUBTOTAL(2,$Y$4:Y30) -> 27 | B30: NO:027 | C30: 一楼商铺 | D30: 1027 | E30: 27.15 | F30: 1027 | G30: 范宏成 | H30: =E30 -> 27.15 | I30: 4200 | J30: 500 | K30: =I30+J30 -> 4700 | L30: 160 | M30: 3392 | N30: 3403 | O30: =N30-M30 -> 11 | P30: =ROUND(H30*0,0) -> 0 | Q30: =O30+P30 -> 11 | R30: 0.8 | S30: =ROUND(Q30*0.7,0) -> 8 | T30: =ROUND(Q30*R30,0) -> 9 | U30: =ROUND(H30*5.6,0) -> 152 | V30: =ROUND(U30*1.5,0) -> 228 | W30: =ROUND(H30*0.2,0) -> 5 | X30: =ROUND(W30*8.5,0) -> 43 | Y30: =I30+J30+L30+S30+T30+V30+X30 -> 5148 | AD30: =AA30+AB30+AC30 -> 0 | AH30: =AE30+AF30-AG30 -> 0 | AI30: =Y30+Z30+AJ30-AD30-AG30 -> 5148 | AP30: =AL30+AN30+AM30+AO30 -> 0 | AU30: =SUM(AQ30:AT30) -> 0 | AV30: =AI30-AP30-AU30 -> 5148
A31: =SUBTOTAL(2,$Y$4:Y31) -> 28 | B31: NO:028 | C31: 一楼商铺 | D31: 1028 | E31: 27.15 | F31: 1028 | G31: 阮文彬 | H31: 27.15 | I31: 4200 | J31: 500 | K31: =I31+J31 -> 4700 | L31: 160 | M31: 8257 | N31: 8298 | O31: =N31-M31 -> 41 | P31: =ROUND(H31*0,0) -> 0 | Q31: =O31+P31 -> 41 | R31: 0.8 | S31: =ROUND(Q31*0.7,0) -> 29 | T31: =ROUND(Q31*R31,0) -> 33 | U31: =ROUND(H31*5.6,0) -> 152 | V31: =ROUND(U31*1.5,0) -> 228 | W31: =ROUND(H31*0.2,0) -> 5 | X31: =ROUND(W31*8.5,0) -> 43 | Y31: =I31+J31+L31+S31+T31+V31+X31 -> 5193 | AD31: =AA31+AB31+AC31 -> 0 | AH31: =AE31+AF31-AG31 -> 0 | AI31: =Y31+Z31+AJ31-AD31-AG31 -> 5193 | AP31: =AL31+AN31+AM31+AO31 -> 0 | AU31: =SUM(AQ31:AT31) -> 0 | AV31: =AI31-AP31-AU31 -> 5193
A32: =SUBTOTAL(2,$Y$4:Y32) -> 29 | B32: NO:029 | C32: 一楼商铺 | D32: 1029 | E32: 27.15 | F32: 1029 | G32: 钟玲玲 | H32: =E32 -> 27.15 | I32: 4200 | J32: 500 | K32: =I32+J32 -> 4700 | L32: 160 | M32: 5452 | N32: 5489 | O32: =N32-M32 -> 37 | P32: =ROUND(H32*0,0) -> 0 | Q32: =O32+P32 -> 37 | R32: 0.8 | S32: =ROUND(Q32*0.7,0) -> 26 | T32: =ROUND(Q32*R32,0) -> 30 | U32: =ROUND(H32*5.6,0) -> 152 | V32: =ROUND(U32*1.5,0) -> 228 | W32: =ROUND(H32*0.2,0) -> 5 | X32: =ROUND(W32*8.5,0) -> 43 | Y32: =I32+J32+L32+S32+T32+V32+X32 -> 5187 | AD32: =AA32+AB32+AC32 -> 0 | AH32: =AE32+AF32-AG32 -> 0 | AI32: =Y32+Z32+AJ32-AD32-AG32 -> 5187 | AP32: =AL32+AN32+AM32+AO32 -> 0 | AU32: =SUM(AQ32:AT32) -> 0 | AV32: =AI32-AP32-AU32 -> 5187
A33: =SUBTOTAL(2,$Y$4:Y33) -> 30 | B33: NO:030 | C33: 一楼商铺 | D33: 1030 | E33: 27.15 | F33: 1030 | G33: 覃燕芬 | H33: =E33 -> 27.15 | I33: 4200 | J33: 500 | K33: =I33+J33 -> 4700 | L33: 160 | M33: 5699 | N33: 5761 | O33: =N33-M33 -> 62 | P33: =ROUND(H33*0,0) -> 0 | Q33: =O33+P33 -> 62 | R33: 0.8 | S33: =ROUND(Q33*0.7,0) -> 43 | T33: =ROUND(Q33*R33,0) -> 50 | U33: =ROUND(H33*5.6,0) -> 152 | V33: =ROUND(U33*1.5,0) -> 228 | W33: =ROUND(H33*0.2,0) -> 5 | X33: =ROUND(W33*8.5,0) -> 43 | Y33: =I33+J33+L33+S33+T33+V33+X33 -> 5224 | AD33: =AA33+AB33+AC33 -> 0 | AH33: =AE33+AF33-AG33 -> 0 | AI33: =Y33+Z33+AJ33-AD33-AG33 -> 5224 | AP33: =AL33+AN33+AM33+AO33 -> 0 | AU33: =SUM(AQ33:AT33) -> 0 | AV33: =AI33-AP33-AU33 -> 5224
A34: =SUBTOTAL(2,$Y$4:Y34) -> 31 | B34: NO:031 | C34: 一楼商铺 | D34: 1031 | E34: 23.77 | F34: 1031 | G34: 陈恳 | H34: 23.77 | I34: 4200 | J34: 500 | K34: =I34+J34 -> 4700 | L34: 160 | M34: 6328 | N34: 6375 | O34: =N34-M34 -> 47 | P34: =ROUND(H34*0,0) -> 0 | Q34: =O34+P34 -> 47 | R34: 0.8 | S34: =ROUND(Q34*0.7,0) -> 33 | T34: =ROUND(Q34*R34,0) -> 38 | U34: =ROUND(H34*5.6,0) -> 133 | V34: =ROUND(U34*1.5,0) -> 200 | W34: =ROUND(H34*0.2,0) -> 5 | X34: =ROUND(W34*8.5,0) -> 43 | Y34: =I34+J34+L34+S34+T34+V34+X34 -> 5174 | AD34: =AA34+AB34+AC34 -> 0 | AH34: =AE34+AF34-AG34 -> 0 | AI34: =Y34+Z34+AJ34-AD34-AG34 -> 5174 | AP34: =AL34+AN34+AM34+AO34 -> 0 | AU34: =SUM(AQ34:AT34) -> 0 | AV34: =AI34-AP34-AU34 -> 5174
A35: =SUBTOTAL(2,$Y$4:Y35) -> 32 | B35: NO:032 | C35: 一楼商铺 | D35: 1032 | E35: 27.15 | F35: 1032 | G35: 范琼静 | H35: =E35 -> 27.15 | I35: 4200 | J35: 500 | K35: =I35+J35 -> 4700 | L35: 160 | M35: 5983 | N35: 6025 | O35: =N35-M35 -> 42 | P35: =ROUND(H35*0,0) -> 0 | Q35: =O35+P35 -> 42 | R35: 0.8 | S35: =ROUND(Q35*0.7,0) -> 29 | T35: =ROUND(Q35*R35,0) -> 34 | U35: =ROUND(H35*5.6,0) -> 152 | V35: =ROUND(U35*1.5,0) -> 228 | W35: =ROUND(H35*0.2,0) -> 5 | X35: =ROUND(W35*8.5,0) -> 43 | Y35: =I35+J35+L35+S35+T35+V35+X35 -> 5194 | AD35: =AA35+AB35+AC35 -> 0 | AH35: =AE35+AF35-AG35 -> 0 | AI35: =Y35+Z35+AJ35-AD35-AG35 -> 5194 | AP35: =AL35+AN35+AM35+AO35 -> 0 | AU35: =SUM(AQ35:AT35) -> 0 | AV35: =AI35-AP35-AU35 -> 5194
A36: =SUBTOTAL(2,$Y$4:Y36) -> 33 | B36: NO:033 | C36: 一楼商铺 | D36: 1033 | E36: 27.15 | F36: 1033 | G36: 蔡安琦 | H36: =E36 -> 27.15 | I36: 4200 | J36: 500 | K36: =I36+J36 -> 4700 | L36: 160 | M36: 9222 | N36: 9253 | O36: =N36-M36 -> 31 | P36: =ROUND(H36*0,0) -> 0 | Q36: =O36+P36 -> 31 | R36: 0.8 | S36: =ROUND(Q36*0.7,0) -> 22 | T36: =ROUND(Q36*R36,0) -> 25 | U36: =ROUND(H36*5.6,0) -> 152 | V36: =ROUND(U36*1.5,0) -> 228 | W36: =ROUND(H36*0.2,0) -> 5 | X36: =ROUND(W36*8.5,0) -> 43 | Y36: =I36+J36+L36+S36+T36+V36+X36 -> 5178 | AD36: =AA36+AB36+AC36 -> 0 | AH36: =AE36+AF36-AG36 -> 0 | AI36: =Y36+Z36+AJ36-AD36-AG36 -> 5178 | AP36: =AL36+AN36+AM36+AO36 -> 0 | AU36: =SUM(AQ36:AT36) -> 0 | AV36: =AI36-AP36-AU36 -> 5178
A37: =SUBTOTAL(2,$Y$4:Y37) -> 34 | B37: NO:034 | C37: 一楼商铺 | D37: 1034 | E37: 27.15 | F37: 1034 | G37: 杨志鸿 | H37: =E37 -> 27.15 | I37: 4200 | J37: 500 | K37: =I37+J37 -> 4700 | L37: 160 | M37: 2989 | N37: 3002 | O37: =N37-M37 -> 13 | P37: =ROUND(H37*0,0) -> 0 | Q37: =O37+P37 -> 13 | R37: 0.8 | S37: =ROUND(Q37*0.7,0) -> 9 | T37: =ROUND(Q37*R37,0) -> 10 | U37: =ROUND(H37*5.6,0) -> 152 | V37: =ROUND(U37*1.5,0) -> 228 | W37: =ROUND(H37*0.2,0) -> 5 | X37: =ROUND(W37*8.5,0) -> 43 | Y37: =I37+J37+L37+S37+T37+V37+X37 -> 5150 | AD37: =AA37+AB37+AC37 -> 0 | AH37: =AE37+AF37-AG37 -> 0 | AI37: =Y37+Z37+AJ37-AD37-AG37 -> 5150 | AP37: =AL37+AN37+AM37+AO37 -> 0 | AU37: =SUM(AQ37:AT37) -> 0 | AV37: =AI37-AP37-AU37 -> 5150
A38: =SUBTOTAL(2,$Y$4:Y38) -> 35 | B38: NO:035 | C38: 一楼商铺 | D38: 1035 | E38: 27.15 | F38: 1035 | G38: 王正庚 | H38: =E38 -> 27.15 | I38: 4200 | J38: 500 | K38: =I38+J38 -> 4700 | L38: 160 | M38: 10414 | N38: =20900/2 -> 10450 | O38: =N38-M38 -> 36 | P38: =ROUND(H38*0,0) -> 0 | Q38: =O38+P38 -> 36 | R38: 0.8 | S38: =ROUND(Q38*0.7,0) -> 25 | T38: =ROUND(Q38*R38,0) -> 29 | U38: =ROUND(H38*5.6,0) -> 152 | V38: =ROUND(U38*1.5,0) -> 228 | W38: =ROUND(H38*0.2,0) -> 5 | X38: =ROUND(W38*8.5,0) -> 43 | Y38: =I38+J38+L38+S38+T38+V38+X38 -> 5185 | AD38: =AA38+AB38+AC38 -> 0 | AH38: =AE38+AF38-AG38 -> 0 | AI38: =Y38+Z38+AJ38-AD38-AG38 -> 5185 | AP38: =AL38+AN38+AM38+AO38 -> 0 | AU38: =SUM(AQ38:AT38) -> 0 | AV38: =AI38-AP38-AU38 -> 5185
A39: =SUBTOTAL(2,$Y$4:Y39) -> 36 | B39: NO:036 | C39: 一楼商铺 | D39: 1036 | E39: 27.15 | F39: 1036 | G39: 李耿坚 | H39: =E39 -> 27.15 | I39: 4200 | J39: 500 | K39: =I39+J39 -> 4700 | L39: 160 | M39: 10414 | N39: 10450 | O39: =N39-M39 -> 36 | P39: =ROUND(H39*0,0) -> 0 | Q39: =O39+P39 -> 36 | R39: 0.8 | S39: =ROUND(Q39*0.7,0) -> 25 | T39: =ROUND(Q39*R39,0) -> 29 | U39: =ROUND(H39*5.6,0) -> 152 | V39: =ROUND(U39*1.5,0) -> 228 | W39: =ROUND(H39*0.2,0) -> 5 | X39: =ROUND(W39*8.5,0) -> 43 | Y39: =I39+J39+L39+S39+T39+V39+X39 -> 5185 | AD39: =AA39+AB39+AC39 -> 0 | AH39: =AE39+AF39-AG39 -> 0 | AI39: =Y39+Z39+AJ39-AD39-AG39 -> 5185 | AP39: =AL39+AN39+AM39+AO39 -> 0 | AU39: =SUM(AQ39:AT39) -> 0 | AV39: =AI39-AP39-AU39 -> 5185
A40: =SUBTOTAL(2,$Y$4:Y40) -> 37 | B40: NO:037 | C40: 一楼商铺 | D40: 1037 | E40: 27.15 | F40: 1037 | G40: 范宏健 | H40: =E40 -> 27.15 | I40: 4200 | J40: 500 | K40: =I40+J40 -> 4700 | L40: 160 | M40: 3570 | N40: 3615 | O40: =N40-M40 -> 45 | P40: =ROUND(H40*0,0) -> 0 | Q40: =O40+P40 -> 45 | R40: 0.8 | S40: =ROUND(Q40*0.7,0) -> 32 | T40: =ROUND(Q40*R40,0) -> 36 | U40: =ROUND(H40*5.6,0) -> 152 | V40: =ROUND(U40*1.5,0) -> 228 | W40: =ROUND(H40*0.2,0) -> 5 | X40: =ROUND(W40*8.5,0) -> 43 | Y40: =I40+J40+L40+S40+T40+V40+X40 -> 5199 | AD40: =AA40+AB40+AC40 -> 0 | AH40: =AE40+AF40-AG40 -> 0 | AI40: =Y40+Z40+AJ40-AD40-AG40 -> 5199 | AP40: =AL40+AN40+AM40+AO40 -> 0 | AU40: =SUM(AQ40:AT40) -> 0 | AV40: =AI40-AP40-AU40 -> 5199
A41: =SUBTOTAL(2,$Y$4:Y41) -> 38 | B41: NO:038 | C41: 一楼商铺 | D41: 1038 | E41: 27.15 | F41: 1038 | G41: 杨义坤 | H41: =E41 -> 27.15 | I41: 4200 | J41: 500 | K41: =I41+J41 -> 4700 | L41: 160 | M41: 4088 | N41: 4143 | O41: =N41-M41 -> 55 | P41: =ROUND(H41*0,0) -> 0 | Q41: =O41+P41 -> 55 | R41: 0.8 | S41: =ROUND(Q41*0.7,0) -> 39 | T41: =ROUND(Q41*R41,0) -> 44 | U41: =ROUND(H41*5.6,0) -> 152 | V41: =ROUND(U41*1.5,0) -> 228 | W41: =ROUND(H41*0.2,0) -> 5 | X41: =ROUND(W41*8.5,0) -> 43 | Y41: =I41+J41+L41+S41+T41+V41+X41 -> 5214 | AD41: =AA41+AB41+AC41 -> 0 | AH41: =AE41+AF41-AG41 -> 0 | AI41: =Y41+Z41+AJ41-AD41-AG41 -> 5214 | AP41: =AL41+AN41+AM41+AO41 -> 0 | AU41: =SUM(AQ41:AT41) -> 0 | AV41: =AI41-AP41-AU41 -> 5214
A42: =SUBTOTAL(2,$Y$4:Y42) -> 39 | B42: NO:039 | C42: 一楼商铺 | D42: 1039 | E42: 27.15 | F42: 1039 | G42: 陈秋香 | H42: =E42 -> 27.15 | I42: 4200 | J42: 500 | K42: =I42+J42 -> 4700 | L42: 160 | M42: 6193 | N42: 6216 | O42: =N42-M42 -> 23 | P42: =ROUND(H42*0,0) -> 0 | Q42: =O42+P42 -> 23 | R42: 0.8 | S42: =ROUND(Q42*0.7,0) -> 16 | T42: =ROUND(Q42*R42,0) -> 18 | U42: =ROUND(H42*5.6,0) -> 152 | V42: =ROUND(U42*1.5,0) -> 228 | W42: =ROUND(H42*0.2,0) -> 5 | X42: =ROUND(W42*8.5,0) -> 43 | Y42: =I42+J42+L42+S42+T42+V42+X42 -> 5165 | AD42: =AA42+AB42+AC42 -> 0 | AH42: =AE42+AF42-AG42 -> 0 | AI42: =Y42+Z42+AJ42-AD42-AG42 -> 5165 | AP42: =AL42+AN42+AM42+AO42 -> 0 | AU42: =SUM(AQ42:AT42) -> 0 | AV42: =AI42-AP42-AU42 -> 5165
A43: =SUBTOTAL(2,$Y$4:Y43) -> 40 | B43: NO:040 | C43: 一楼商铺 | D43: 1040 | E43: 27.15 | F43: 1040 | G43: 陈少华 | H43: =E43 -> 27.15 | I43: 4202 | J43: 500 | K43: =I43+J43 -> 4702 | L43: 160 | M43: 6603 | N43: 6642 | O43: =N43-M43 -> 39 | P43: =ROUND(H43*0,0) -> 0 | Q43: =O43+P43 -> 39 | R43: 0.8 | S43: =ROUND(Q43*0.7,0) -> 27 | T43: =ROUND(Q43*R43,0) -> 31 | U43: =ROUND(H43*5.6,0) -> 152 | V43: =ROUND(U43*1.5,0) -> 228 | W43: =ROUND(H43*0.2,0) -> 5 | X43: =ROUND(W43*8.5,0) -> 43 | Y43: =I43+J43+L43+S43+T43+V43+X43 -> 5191 | AD43: =AA43+AB43+AC43 -> 0 | AH43: =AE43+AF43-AG43 -> 0 | AI43: =Y43+Z43+AJ43-AD43-AG43 -> 5191 | AP43: =AL43+AN43+AM43+AO43 -> 0 | AU43: =SUM(AQ43:AT43) -> 0 | AV43: =AI43-AP43-AU43 -> 5191
A44: =SUBTOTAL(2,$Y$4:Y44) -> 41 | B44: NO:041 | C44: 一楼商铺 | D44: 1041 | E44: 27.15 | F44: 1041 | G44: 林文浩 | H44: =E44 -> 27.15 | I44: 4200 | J44: 0 | K44: =I44+J44 -> 4200 | L44: 160 | M44: 5037 | N44: 5191 | O44: =N44-M44 -> 154 | P44: =ROUND(H44*0,0) -> 0 | Q44: =O44+P44 -> 154 | R44: 0.8 | S44: =ROUND(Q44*0.7,0) -> 108 | T44: =ROUND(Q44*R44,0) -> 123 | U44: =ROUND(H44*5.6,0) -> 152 | V44: =ROUND(U44*1.5,0) -> 228 | W44: =ROUND(H44*0.2,0) -> 5 | X44: =ROUND(W44*8.5,0) -> 43 | Y44: =I44+J44+L44+S44+T44+V44+X44 -> 4862 | AD44: =AA44+AB44+AC44 -> 0 | AH44: =AE44+AF44-AG44 -> 0 | AI44: =Y44+Z44+AJ44-AD44-AG44 -> 4862 | AP44: =AL44+AN44+AM44+AO44 -> 0 | AU44: =SUM(AQ44:AT44) -> 0 | AV44: =AI44-AP44-AU44 -> 4862
A45: =SUBTOTAL(2,$Y$4:Y45) -> 42 | B45: NO:042 | C45: 一楼商铺 | D45: 1042 | E45: 27.15 | F45: 1042 | G45: 陈俊炳 | H45: =E45 -> 27.15 | I45: 4200 | J45: 500 | K45: =I45+J45 -> 4700 | L45: 160 | M45: 7525 | N45: 7613 | O45: =N45-M45 -> 88 | P45: =ROUND(H45*0,0) -> 0 | Q45: =O45+P45 -> 88 | R45: 0.8 | S45: =ROUND(Q45*0.7,0) -> 62 | T45: =ROUND(Q45*R45,0) -> 70 | U45: =ROUND(H45*5.6,0) -> 152 | V45: =ROUND(U45*1.5,0) -> 228 | W45: =ROUND(H45*0.2,0) -> 5 | X45: =ROUND(W45*8.5,0) -> 43 | Y45: =I45+J45+L45+S45+T45+V45+X45 -> 5263 | AD45: =AA45+AB45+AC45 -> 0 | AH45: =AE45+AF45-AG45 -> 0 | AI45: =Y45+Z45+AJ45-AD45-AG45 -> 5263 | AP45: =AL45+AN45+AM45+AO45 -> 0 | AU45: =SUM(AQ45:AT45) -> 0 | AV45: =AI45-AP45-AU45 -> 5263
A46: =SUBTOTAL(2,$Y$4:Y46) -> 43 | B46: NO:043 | C46: 一楼商铺 | D46: 1043 | E46: 27.15 | F46: 1043 | G46: 曾丽 | H46: 27.15 | I46: 3500 | J46: 0 | K46: =I46+J46 -> 3500 | L46: 160 | M46: 7132 | N46: 7184 | O46: =N46-M46 -> 52 | P46: =ROUND(H46*0,0) -> 0 | Q46: =O46+P46 -> 52 | R46: 0.8 | S46: =ROUND(Q46*0.7,0) -> 36 | T46: =ROUND(Q46*R46,0) -> 42 | U46: =ROUND(H46*5.6,0) -> 152 | V46: =ROUND(U46*1.5,0) -> 228 | W46: =ROUND(H46*0.2,0) -> 5 | X46: =ROUND(W46*8.5,0) -> 43 | Y46: =I46+J46+L46+S46+T46+V46+X46 -> 4009 | AD46: =AA46+AB46+AC46 -> 0 | AH46: =AE46+AF46-AG46 -> 0 | AI46: =Y46+Z46+AJ46-AD46-AG46 -> 4009 | AP46: =AL46+AN46+AM46+AO46 -> 0 | AU46: =SUM(AQ46:AT46) -> 0 | AV46: =AI46-AP46-AU46 -> 4009
A47: =SUBTOTAL(2,$Y$4:Y47) -> 44 | B47: NO:044 | C47: 一楼商铺 | D47: 1044 | E47: 27.15 | F47: 1044 | G47: 杨要 | H47: =E47 -> 27.15 | I47: =4202 -> 4202 | J47: 200 | K47: =I47+J47 -> 4402 | L47: 160 | M47: 4157 | N47: 4219 | O47: =N47-M47 -> 62 | P47: =ROUND(H47*0,0) -> 0 | Q47: =O47+P47 -> 62 | R47: 0.8 | S47: =ROUND(Q47*0.7,0) -> 43 | T47: =ROUND(Q47*R47,0) -> 50 | U47: =ROUND(H47*5.6,0) -> 152 | V47: =ROUND(U47*1.5,0) -> 228 | W47: =ROUND(H47*0.2,0) -> 5 | X47: =ROUND(W47*8.5,0) -> 43 | Y47: =I47+J47+L47+S47+T47+V47+X47 -> 4926 | AD47: =AA47+AB47+AC47 -> 0 | AH47: =AE47+AF47-AG47 -> 0 | AI47: =Y47+Z47+AJ47-AD47-AG47 -> 4926 | AP47: =AL47+AN47+AM47+AO47 -> 0 | AU47: =SUM(AQ47:AT47) -> 0 | AV47: =AI47-AP47-AU47 -> 4926
A48: =SUBTOTAL(2,$Y$4:Y48) -> 45 | B48: NO:045 | C48: 一楼商铺 | D48: 1045 | E48: 26.49 | F48: 1045 | G48: 陈柳旋 | H48: =E48 -> 26.49 | I48: 4200 | J48: 500 | K48: =I48+J48 -> 4700 | L48: 160 | M48: 5823 | N48: 5885 | O48: =N48-M48 -> 62 | P48: =ROUND(H48*0,0) -> 0 | Q48: =O48+P48 -> 62 | R48: 0.8 | S48: =ROUND(Q48*0.7,0) -> 43 | T48: =ROUND(Q48*R48,0) -> 50 | U48: =ROUND(H48*5.6,0) -> 148 | V48: =ROUND(U48*1.5,0) -> 222 | W48: =ROUND(H48*0.2,0) -> 5 | X48: =ROUND(W48*8.5,0) -> 43 | Y48: =I48+J48+L48+S48+T48+V48+X48 -> 5218 | AD48: =AA48+AB48+AC48 -> 0 | AH48: =AE48+AF48-AG48 -> 0 | AI48: =Y48+Z48+AJ48-AD48-AG48 -> 5218 | AP48: =AL48+AN48+AM48+AO48 -> 0 | AU48: =SUM(AQ48:AT48) -> 0 | AV48: =AI48-AP48-AU48 -> 5218
A49: =SUBTOTAL(2,$Y$4:Y49) -> 46 | B49: NO:046 | C49: 一楼商铺 | D49: 1046 | E49: 26.49 | F49: 1046 | G49: 胡命礼 | H49: =E49 -> 26.49 | I49: 4200 | J49: 500 | K49: =I49+J49 -> 4700 | L49: 160 | M49: 5655 | N49: 5746 | O49: =N49-M49 -> 91 | P49: =ROUND(H49*0,0) -> 0 | Q49: =O49+P49 -> 91 | R49: 0.8 | S49: =ROUND(Q49*0.7,0) -> 64 | T49: =ROUND(Q49*R49,0) -> 73 | U49: =ROUND(H49*5.6,0) -> 148 | V49: =ROUND(U49*1.5,0) -> 222 | W49: =ROUND(H49*0.2,0) -> 5 | X49: =ROUND(W49*8.5,0) -> 43 | Y49: =I49+J49+L49+S49+T49+V49+X49 -> 5262 | AD49: =AA49+AB49+AC49 -> 0 | AH49: =AE49+AF49-AG49 -> 0 | AI49: =Y49+Z49+AJ49-AD49-AG49 -> 5262 | AP49: =AL49+AN49+AM49+AO49 -> 0 | AU49: =SUM(AQ49:AT49) -> 0 | AV49: =AI49-AP49-AU49 -> 5262
A50: =SUBTOTAL(2,$Y$4:Y50) -> 47 | B50: NO:047 | C50: 一楼商铺 | D50: 1047 | E50: 26.49 | F50: 1047 | G50: 黄廉颖 | H50: =E50 -> 26.49 | I50: 4200 | J50: 500 | K50: =I50+J50 -> 4700 | L50: 160 | M50: 7795 | N50: 7887 | O50: =N50-M50 -> 92 | P50: =ROUND(H50*0,0) -> 0 | Q50: =O50+P50 -> 92 | R50: 0.8 | S50: =ROUND(Q50*0.7,0) -> 64 | T50: =ROUND(Q50*R50,0) -> 74 | U50: =ROUND(H50*5.6,0) -> 148 | V50: =ROUND(U50*1.5,0) -> 222 | W50: =ROUND(H50*0.2,0) -> 5 | X50: =ROUND(W50*8.5,0) -> 43 | Y50: =I50+J50+L50+S50+T50+V50+X50 -> 5263 | AD50: =AA50+AB50+AC50 -> 0 | AH50: =AE50+AF50-AG50 -> 0 | AI50: =Y50+Z50+AJ50-AD50-AG50 -> 5263 | AP50: =AL50+AN50+AM50+AO50 -> 0 | AU50: =SUM(AQ50:AT50) -> 0 | AV50: =AI50-AP50-AU50 -> 5263
A51: =SUBTOTAL(2,$Y$4:Y51) -> 48 | B51: NO:048 | C51: 一楼商铺 | D51: 1048 | E51: 26.49 | F51: 1048 | G51: 李嘉格 | H51: =E51 -> 26.49 | I51: 4202 | J51: 500 | K51: =I51+J51 -> 4702 | L51: 160 | M51: 5509 | N51: 5529 | O51: =N51-M51 -> 20 | P51: =ROUND(H51*0,0) -> 0 | Q51: =O51+P51 -> 20 | R51: 0.8 | S51: =ROUND(Q51*0.7,0) -> 14 | T51: =ROUND(Q51*R51,0) -> 16 | U51: =ROUND(H51*5.6,0) -> 148 | V51: =ROUND(U51*1.5,0) -> 222 | W51: =ROUND(H51*0.2,0) -> 5 | X51: =ROUND(W51*8.5,0) -> 43 | Y51: =I51+J51+L51+S51+T51+V51+X51 -> 5157 | AD51: =AA51+AB51+AC51 -> 0 | AH51: =AE51+AF51-AG51 -> 0 | AI51: =Y51+Z51+AJ51-AD51-AG51 -> 5157 | AP51: =AL51+AN51+AM51+AO51 -> 0 | AU51: =SUM(AQ51:AT51) -> 0 | AV51: =AI51-AP51-AU51 -> 5157
A52: =SUBTOTAL(2,$Y$4:Y52) -> 49 | B52: NO:049 | C52: 一楼商铺 | D52: 1049 | E52: 26.49 | F52: 1049 | G52: 何飞 | H52: =E52 -> 26.49 | I52: 4200 | J52: 500 | K52: =I52+J52 -> 4700 | L52: 160 | M52: 2001 | N52: 2001 | O52: =N52-M52 -> 0 | P52: =ROUND(H52*0,0) -> 0 | Q52: =O52+P52 -> 0 | R52: 0.8 | S52: =ROUND(Q52*0.7,0) -> 0 | T52: =ROUND(Q52*R52,0) -> 0 | U52: =ROUND(H52*5.6,0) -> 148 | V52: =ROUND(U52*1.5,0) -> 222 | W52: =ROUND(H52*0.2,0) -> 5 | X52: =ROUND(W52*8.5,0) -> 43 | Y52: =I52+J52+L52+S52+T52+V52+X52 -> 5125 | AD52: =AA52+AB52+AC52 -> 0 | AH52: =AE52+AF52-AG52 -> 0 | AI52: =Y52+Z52+AJ52-AD52-AG52 -> 5125 | AP52: =AL52+AN52+AM52+AO52 -> 0 | AU52: =SUM(AQ52:AT52) -> 0 | AV52: =AI52-AP52-AU52 -> 5125
A53: =SUBTOTAL(2,$Y$4:Y53) -> 50 | B53: NO:050 | C53: 一楼商铺 | D53: 1050 | E53: 26.49 | F53: 1050 | G53: 刘玲 | H53: =E53 -> 26.49 | I53: 4200 | J53: 500 | K53: =I53+J53 -> 4700 | L53: 160 | M53: 8017 | N53: 8075 | O53: =N53-M53 -> 58 | P53: =ROUND(H53*0,0) -> 0 | Q53: =O53+P53 -> 58 | R53: 0.8 | S53: =ROUND(Q53*0.7,0) -> 41 | T53: =ROUND(Q53*R53,0) -> 46 | U53: =ROUND(H53*5.6,0) -> 148 | V53: =ROUND(U53*1.5,0) -> 222 | W53: =ROUND(H53*0.2,0) -> 5 | X53: =ROUND(W53*8.5,0) -> 43 | Y53: =I53+J53+L53+S53+T53+V53+X53 -> 5212 | AD53: =AA53+AB53+AC53 -> 0 | AH53: =AE53+AF53-AG53 -> 0 | AI53: =Y53+Z53+AJ53-AD53-AG53 -> 5212 | AP53: =AL53+AN53+AM53+AO53 -> 0 | AU53: =SUM(AQ53:AT53) -> 0 | AV53: =AI53-AP53-AU53 -> 5212
A54: =SUBTOTAL(2,$Y$4:Y54) -> 51 | B54: NO:051 | C54: 一楼商铺 | D54: 1051 | E54: 26.49 | F54: 1051 | G54: 陈慧芳 | H54: =E54 -> 26.49 | I54: 4200 | J54: 500 | K54: =I54+J54 -> 4700 | L54: 160 | M54: 480 | N54: 512 | O54: =N54-M54 -> 32 | P54: =ROUND(H54*0,0) -> 0 | Q54: =O54+P54 -> 32 | R54: 0.8 | S54: =ROUND(Q54*0.7,0) -> 22 | T54: =ROUND(Q54*R54,0) -> 26 | U54: =ROUND(H54*5.6,0) -> 148 | V54: =ROUND(U54*1.5,0) -> 222 | W54: =ROUND(H54*0.2,0) -> 5 | X54: =ROUND(W54*8.5,0) -> 43 | Y54: =I54+J54+L54+S54+T54+V54+X54 -> 5173 | AD54: =AA54+AB54+AC54 -> 0 | AH54: =AE54+AF54-AG54 -> 0 | AI54: =Y54+Z54+AJ54-AD54-AG54 -> 5173 | AP54: =AL54+AN54+AM54+AO54 -> 0 | AU54: =SUM(AQ54:AT54) -> 0 | AV54: =AI54-AP54-AU54 -> 5173
A55: =SUBTOTAL(2,$Y$4:Y55) -> 52 | B55: NO:052 | C55: 一楼商铺 | D55: 1052 | E55: 26.49 | F55: 1052 | G55: 李硕果 | H55: =E55 -> 26.49 | I55: 4202 | J55: 500 | K55: =I55+J55 -> 4702 | L55: 160 | M55: 4458 | N55: 4532 | O55: =N55-M55 -> 74 | P55: =ROUND(H55*0,0) -> 0 | Q55: =O55+P55 -> 74 | R55: 0.8 | S55: =ROUND(Q55*0.7,0) -> 52 | T55: =ROUND(Q55*R55,0) -> 59 | U55: =ROUND(H55*5.6,0) -> 148 | V55: =ROUND(U55*1.5,0) -> 222 | W55: =ROUND(H55*0.2,0) -> 5 | X55: =ROUND(W55*8.5,0) -> 43 | Y55: =I55+J55+L55+S55+T55+V55+X55 -> 5238 | AD55: =AA55+AB55+AC55 -> 0 | AH55: =AE55+AF55-AG55 -> 0 | AI55: =Y55+Z55+AJ55-AD55-AG55 -> 5238 | AP55: =AL55+AN55+AM55+AO55 -> 0 | AU55: =SUM(AQ55:AT55) -> 0 | AV55: =AI55-AP55-AU55 -> 5238
A56: =SUBTOTAL(2,$Y$4:Y56) -> 53 | B56: NO:053 | C56: 一楼商铺 | D56: 1053 | E56: 26.15 | F56: 1053 | G56: 黄文波 | H56: =E56 -> 26.15 | I56: 4202 | J56: 500 | K56: =I56+J56 -> 4702 | L56: 160 | M56: 6032 | N56: 6061 | O56: =N56-M56 -> 29 | P56: =ROUND(H56*0,0) -> 0 | Q56: =O56+P56 -> 29 | R56: 0.8 | S56: =ROUND(Q56*0.7,0) -> 20 | T56: =ROUND(Q56*R56,0) -> 23 | U56: =ROUND(H56*5.6,0) -> 146 | V56: =ROUND(U56*1.5,0) -> 219 | W56: =ROUND(H56*0.2,0) -> 5 | X56: =ROUND(W56*8.5,0) -> 43 | Y56: =I56+J56+L56+S56+T56+V56+X56 -> 5167 | AD56: =AA56+AB56+AC56 -> 0 | AH56: =AE56+AF56-AG56 -> 0 | AI56: =Y56+Z56+AJ56-AD56-AG56 -> 5167 | AP56: =AL56+AN56+AM56+AO56 -> 0 | AU56: =SUM(AQ56:AT56) -> 0 | AV56: =AI56-AP56-AU56 -> 5167
A57: =SUBTOTAL(2,$Y$4:Y57) -> 54 | B57: NO:054 | C57: 一楼商铺 | D57: 1054 | E57: 27.15 | F57: 1054 | G57: 沈飞艳 | H57: =E57 -> 27.15 | I57: 4200 | J57: 500 | K57: =I57+J57 -> 4700 | L57: 160 | M57: 6355 | N57: 6411 | O57: =N57-M57 -> 56 | P57: =ROUND(H57*0,0) -> 0 | Q57: =O57+P57 -> 56 | R57: 0.8 | S57: =ROUND(Q57*0.7,0) -> 39 | T57: =ROUND(Q57*R57,0) -> 45 | U57: =ROUND(H57*5.6,0) -> 152 | V57: =ROUND(U57*1.5,0) -> 228 | W57: =ROUND(H57*0.2,0) -> 5 | X57: =ROUND(W57*8.5,0) -> 43 | Y57: =I57+J57+L57+S57+T57+V57+X57 -> 5215 | AD57: =AA57+AB57+AC57 -> 0 | AH57: =AE57+AF57-AG57 -> 0 | AI57: =Y57+Z57+AJ57-AD57-AG57 -> 5215 | AP57: =AL57+AN57+AM57+AO57 -> 0 | AU57: =SUM(AQ57:AT57) -> 0 | AV57: =AI57-AP57-AU57 -> 5215
A58: =SUBTOTAL(2,$Y$4:Y58) -> 55 | B58: NO:055 | C58: 一楼商铺 | D58: 1055 | E58: 26.49 | F58: 1055 | G58: 梁中梅 | H58: =E58 -> 26.49 | I58: 4200 | J58: 500 | K58: =I58+J58 -> 4700 | L58: 160 | M58: 8887 | N58: 8962 | O58: =N58-M58 -> 75 | P58: =ROUND(H58*0,0) -> 0 | Q58: =O58+P58 -> 75 | R58: 0.8 | S58: =ROUND(Q58*0.7,0) -> 53 | T58: =ROUND(Q58*R58,0) -> 60 | U58: =ROUND(H58*5.6,0) -> 148 | V58: =ROUND(U58*1.5,0) -> 222 | W58: =ROUND(H58*0.2,0) -> 5 | X58: =ROUND(W58*8.5,0) -> 43 | Y58: =I58+J58+L58+S58+T58+V58+X58 -> 5238 | AD58: =AA58+AB58+AC58 -> 0 | AH58: =AE58+AF58-AG58 -> 0 | AI58: =Y58+Z58+AJ58-AD58-AG58 -> 5238 | AP58: =AL58+AN58+AM58+AO58 -> 0 | AU58: =SUM(AQ58:AT58) -> 0 | AV58: =AI58-AP58-AU58 -> 5238
A59: =SUBTOTAL(2,$Y$4:Y59) -> 56 | B59: NO:056 | C59: 一楼商铺 | D59: 1056 | E59: 26.49 | F59: 1056 | G59: 吴玉荡 | H59: =E59 -> 26.49 | I59: 4200 | J59: 500 | K59: =I59+J59 -> 4700 | L59: 160 | M59: 5536 | N59: 5591 | O59: =N59-M59 -> 55 | P59: =ROUND(H59*0,0) -> 0 | Q59: =O59+P59 -> 55 | R59: 0.8 | S59: =ROUND(Q59*0.7,0) -> 39 | T59: =ROUND(Q59*R59,0) -> 44 | U59: =ROUND(H59*5.6,0) -> 148 | V59: =ROUND(U59*1.5,0) -> 222 | W59: =ROUND(H59*0.2,0) -> 5 | X59: =ROUND(W59*8.5,0) -> 43 | Y59: =I59+J59+L59+S59+T59+V59+X59 -> 5208 | AD59: =AA59+AB59+AC59 -> 0 | AH59: =AE59+AF59-AG59 -> 0 | AI59: =Y59+Z59+AJ59-AD59-AG59 -> 5208 | AP59: =AL59+AN59+AM59+AO59 -> 0 | AU59: =SUM(AQ59:AT59) -> 0 | AV59: =AI59-AP59-AU59 -> 5208
A60: =SUBTOTAL(2,$Y$4:Y60) -> 57 | B60: NO:057 | C60: 一楼商铺 | D60: 1057 | E60: 26.49 | F60: 1057 | G60: 肖梓尧 | H60: =E60 -> 26.49 | I60: 4200 | J60: 500 | K60: =I60+J60 -> 4700 | L60: 160 | M60: 1970 | N60: 2048 | O60: =N60-M60 -> 78 | P60: =ROUND(H60*0,0) -> 0 | Q60: =O60+P60 -> 78 | R60: 0.8 | S60: =ROUND(Q60*0.7,0) -> 55 | T60: =ROUND(Q60*R60,0) -> 62 | U60: =ROUND(H60*5.6,0) -> 148 | V60: =ROUND(U60*1.5,0) -> 222 | W60: =ROUND(H60*0.2,0) -> 5 | X60: =ROUND(W60*8.5,0) -> 43 | Y60: =I60+J60+L60+S60+T60+V60+X60 -> 5242 | AD60: =AA60+AB60+AC60 -> 0 | AH60: =AE60+AF60-AG60 -> 0 | AI60: =Y60+Z60+AJ60-AD60-AG60 -> 5242 | AP60: =AL60+AN60+AM60+AO60 -> 0 | AU60: =SUM(AQ60:AT60) -> 0 | AV60: =AI60-AP60-AU60 -> 5242
A61: =SUBTOTAL(2,$Y$4:Y61) -> 58 | B61: NO:058 | C61: 一楼商铺 | D61: 1058 | E61: 26.49 | F61: 1058 | G61: 江朝 | H61: 26.49 | I61: 4200 | J61: 500 | K61: =I61+J61 -> 4700 | L61: 160 | M61: 8423 | N61: 8527 | O61: =N61-M61 -> 104 | P61: =ROUND(H61*0,0) -> 0 | Q61: =O61+P61 -> 104 | R61: 0.8 | S61: =ROUND(Q61*0.7,0) -> 73 | T61: =ROUND(Q61*R61,0) -> 83 | U61: =ROUND(H61*5.6,0) -> 148 | V61: =ROUND(U61*1.5,0) -> 222 | W61: =ROUND(H61*0.2,0) -> 5 | X61: =ROUND(W61*8.5,0) -> 43 | Y61: =I61+J61+L61+S61+T61+V61+X61 -> 5281 | AD61: =AA61+AB61+AC61 -> 0 | AH61: =AE61+AF61-AG61 -> 0 | AI61: =Y61+Z61+AJ61-AD61-AG61 -> 5281 | AP61: =AL61+AN61+AM61+AO61 -> 0 | AU61: =SUM(AQ61:AT61) -> 0 | AV61: =AI61-AP61-AU61 -> 5281
A62: =SUBTOTAL(2,$Y$4:Y62) -> 59 | B62: NO:059 | C62: 一楼商铺 | D62: 1059 | E62: 26.49 | F62: 1059 | G62: 温平 | H62: =E62 -> 26.49 | I62: 4200 | J62: 500 | K62: =I62+J62 -> 4700 | L62: 160 | M62: 7981 | N62: 8081 | O62: =N62-M62 -> 100 | P62: =ROUND(H62*0,0) -> 0 | Q62: =O62+P62 -> 100 | R62: 0.8 | S62: =ROUND(Q62*0.7,0) -> 70 | T62: =ROUND(Q62*R62,0) -> 80 | U62: =ROUND(H62*5.6,0) -> 148 | V62: =ROUND(U62*1.5,0) -> 222 | W62: =ROUND(H62*0.2,0) -> 5 | X62: =ROUND(W62*8.5,0) -> 43 | Y62: =I62+J62+L62+S62+T62+V62+X62 -> 5275 | AD62: =AA62+AB62+AC62 -> 0 | AH62: =AE62+AF62-AG62 -> 0 | AI62: =Y62+Z62+AJ62-AD62-AG62 -> 5275 | AP62: =AL62+AN62+AM62+AO62 -> 0 | AU62: =SUM(AQ62:AT62) -> 0 | AV62: =AI62-AP62-AU62 -> 5275
A63: =SUBTOTAL(2,$Y$4:Y63) -> 60 | B63: NO:060 | C63: 一楼商铺 | D63: 1060 | E63: 26.49 | F63: 1060 | G63: 戴晓怡 | H63: =E63 -> 26.49 | I63: 4200 | J63: 500 | K63: =I63+J63 -> 4700 | L63: 160 | M63: 6219 | N63: 6257 | O63: =N63-M63 -> 38 | P63: =ROUND(H63*0,0) -> 0 | Q63: =O63+P63 -> 38 | R63: 0.8 | S63: =ROUND(Q63*0.7,0) -> 27 | T63: =ROUND(Q63*R63,0) -> 30 | U63: =ROUND(H63*5.6,0) -> 148 | V63: =ROUND(U63*1.5,0) -> 222 | W63: =ROUND(H63*0.2,0) -> 5 | X63: =ROUND(W63*8.5,0) -> 43 | Y63: =I63+J63+L63+S63+T63+V63+X63 -> 5182 | AD63: =AA63+AB63+AC63 -> 0 | AH63: =AE63+AF63-AG63 -> 0 | AI63: =Y63+Z63+AJ63-AD63-AG63 -> 5182 | AP63: =AL63+AN63+AM63+AO63 -> 0 | AU63: =SUM(AQ63:AT63) -> 0 | AV63: =AI63-AP63-AU63 -> 5182
A64: =SUBTOTAL(2,$Y$4:Y64) -> 61 | B64: NO:061 | C64: 一楼商铺 | D64: 1061 | E64: 26.49 | F64: 1061 | G64: 李丽 | H64: =E64 -> 26.49 | I64: 3500 | J64: 200 | K64: =I64+J64 -> 3700 | L64: 160 | M64: 6585 | N64: 6833 | O64: =N64-M64 -> 248 | P64: =ROUND(H64*0,0) -> 0 | Q64: =O64+P64 -> 248 | R64: 0.8 | S64: =ROUND(Q64*0.7,0) -> 174 | T64: =ROUND(Q64*R64,0) -> 198 | U64: =ROUND(H64*5.6,0) -> 148 | V64: =ROUND(U64*1.5,0) -> 222 | W64: =ROUND(H64*0.2,0) -> 5 | X64: =ROUND(W64*8.5,0) -> 43 | Y64: =I64+J64+L64+S64+T64+V64+X64 -> 4497 | AD64: =AA64+AB64+AC64 -> 0 | AH64: =AE64+AF64-AG64 -> 0 | AI64: =Y64+Z64+AJ64-AD64-AG64 -> 4497 | AP64: =AL64+AN64+AM64+AO64 -> 0 | AU64: =SUM(AQ64:AT64) -> 0 | AV64: =AI64-AP64-AU64 -> 4497
A65: =SUBTOTAL(2,$Y$4:Y65) -> 62 | B65: NO:062 | C65: 一楼商铺 | D65: 1062 | E65: 27.15 | F65: 1062 | G65: 章芳琴 | H65: =E65 -> 27.15 | I65: 3000 | J65: 0 | K65: =I65+J65 -> 3000 | L65: 160 | M65: 590 | N65: 728 | O65: =N65-M65 -> 138 | P65: =ROUND(H65*0,0) -> 0 | Q65: =O65+P65 -> 138 | R65: 0.8 | S65: =ROUND(Q65*0.7,0) -> 97 | T65: =ROUND(Q65*R65,0) -> 110 | U65: =ROUND(H65*5.6,0) -> 152 | V65: =ROUND(U65*1.5,0) -> 228 | W65: =ROUND(H65*0.2,0) -> 5 | X65: =ROUND(W65*8.5,0) -> 43 | Y65: =I65+J65+L65+S65+T65+V65+X65 -> 3638 | AD65: =AA65+AB65+AC65 -> 0 | AH65: =AE65+AF65-AG65 -> 0 | AI65: =Y65+Z65+AJ65-AD65-AG65 -> 3638 | AP65: =AL65+AN65+AM65+AO65 -> 0 | AU65: =SUM(AQ65:AT65) -> 0 | AV65: =AI65-AP65-AU65 -> 3638
A66: =SUBTOTAL(2,$Y$4:Y66) -> 63 | B66: NO:063 | C66: 一楼商铺 | D66: 1063 | E66: 6.21 | F66: 1063 | G66: 余迎龙 | H66: =E66 -> 6.21 | I66: =2240-640 -> 1600 | J66: 0 | K66: =I66+J66 -> 1600 | L66: 160 | M66: 6067 | N66: 6093 | O66: =N66-M66 -> 26 | P66: =ROUND(H66*0,0) -> 0 | Q66: =O66+P66 -> 26 | R66: 0.8 | S66: =ROUND(Q66*0.7,0) -> 18 | T66: =ROUND(Q66*R66,0) -> 21 | U66: =ROUND(H66*5.6,0) -> 35 | V66: =ROUND(U66*1.5,0) -> 53 | W66: =ROUND(H66*0.2,0) -> 1 | X66: =ROUND(W66*8.5,0) -> 9 | Y66: =I66+J66+L66+S66+T66+V66+X66 -> 1861 | AD66: =AA66+AB66+AC66 -> 0 | AH66: =AE66+AF66-AG66 -> 0 | AI66: =Y66+Z66+AJ66-AD66-AG66 -> 1861 | AP66: =AL66+AN66+AM66+AO66 -> 0 | AU66: =SUM(AQ66:AT66) -> 0 | AV66: =AI66-AP66-AU66 -> 1861
A67: =SUBTOTAL(2,$Y$4:Y67) -> 64 | B67: NO:064 | C67: 一楼商铺 | D67: 1065 | E67: 6.21 | F67: 1065 | G67: 万军银 | H67: =E67 -> 6.21 | I67: 1200 | J67: 0 | K67: =I67+J67 -> 1200 | L67: 160 | M67: 6909 | N67: 6910 | O67: =N67-M67 -> 1 | P67: =ROUND(H67*0,0) -> 0 | Q67: =O67+P67 -> 1 | R67: 0.8 | S67: =ROUND(Q67*0.7,0) -> 1 | T67: =ROUND(Q67*R67,0) -> 1 | U67: =ROUND(H67*5.6,0) -> 35 | V67: =ROUND(U67*1.5,0) -> 53 | W67: =ROUND(H67*0.2,0) -> 1 | X67: =ROUND(W67*8.5,0) -> 9 | Y67: =I67+J67+L67+S67+T67+V67+X67 -> 1424 | AD67: =AA67+AB67+AC67 -> 0 | AH67: =AE67+AF67-AG67 -> 0 | AI67: =Y67+Z67+AJ67-AD67-AG67 -> 1424 | AP67: =AL67+AN67+AM67+AO67 -> 0 | AU67: =SUM(AQ67:AT67) -> 0 | AV67: =AI67-AP67-AU67 -> 1424
A68: =SUBTOTAL(2,$Y$4:Y68) -> 65 | B68: NO:065 | C68: 一楼商铺 | D68: 1066 | E68: 27.15 | F68: 1066 | G68: 卢永润 | H68: =E68 -> 27.15 | I68: 4200 | J68: 500 | K68: =I68+J68 -> 4700 | L68: 160 | M68: 9256 | N68: 9306 | O68: =N68-M68 -> 50 | P68: =ROUND(H68*0,0) -> 0 | Q68: =O68+P68 -> 50 | R68: 0.8 | S68: =ROUND(Q68*0.7,0) -> 35 | T68: =ROUND(Q68*R68,0) -> 40 | U68: =ROUND(H68*5.6,0) -> 152 | V68: =ROUND(U68*1.5,0) -> 228 | W68: =ROUND(H68*0.2,0) -> 5 | X68: =ROUND(W68*8.5,0) -> 43 | Y68: =I68+J68+L68+S68+T68+V68+X68 -> 5206 | AD68: =AA68+AB68+AC68 -> 0 | AH68: =AE68+AF68-AG68 -> 0 | AI68: =Y68+Z68+AJ68-AD68-AG68 -> 5206 | AP68: =AL68+AN68+AM68+AO68 -> 0 | AU68: =SUM(AQ68:AT68) -> 0 | AV68: =AI68-AP68-AU68 -> 5206
A69: =SUBTOTAL(2,$Y$4:Y69) -> 66 | B69: NO:066 | C69: 一楼展柜 | F69: 1067展柜(全包） | G69: 章芳琴 | I69: 1500 | K69: =I69+J69 -> 1500 | L69: 0 | S69: =ROUND(Q69*0.7,0) -> 0 | X69: =ROUND(W69*8.5,0) -> 0 | Y69: =I69+J69+L69+S69+T69+V69+X69 -> 1500 | AD69: =AA69+AB69+AC69 -> 0 | AH69: =AE69+AF69-AG69 -> 0 | AI69: =Y69+Z69+AJ69-AD69-AG69 -> 1500 | AP69: =AL69+AN69+AM69+AO69 -> 0 | AU69: =SUM(AQ69:AT69) -> 0 | AV69: =AI69-AP69-AU69 -> 1500
A70: =SUBTOTAL(2,$Y$4:Y70) -> 67 | B70: NO:067 | C70: 一楼展柜 | F70: 1068展柜/1069展柜 | G70: 黄伟慧 | I70: 1200 | K70: =I70+J70 -> 1200 | L70: 0 | S70: =ROUND(Q70*0.7,0) -> 0 | X70: =ROUND(W70*8.5,0) -> 0 | Y70: =I70+J70+L70+S70+T70+V70+X70 -> 1200 | AD70: =AA70+AB70+AC70 -> 0 | AH70: =AE70+AF70-AG70 -> 0 | AI70: =Y70+Z70+AJ70-AD70-AG70 -> 1200 | AP70: =AL70+AN70+AM70+AO70 -> 0 | AU70: =SUM(AQ70:AT70) -> 0 | AV70: =AI70-AP70-AU70 -> 1200
A71: =SUBTOTAL(2,$Y$4:Y71) -> 68 | B71: NO:068 | C71: 一楼展柜 | F71: 大厅01 | G71: 张文英 | I71: 2000 | K71: =I71+J71 -> 2000 | L71: 0 | S71: =ROUND(Q71*0.7,0) -> 0 | Y71: =I71+J71+L71+S71+T71+V71+X71 -> 2000 | AD71: =AA71+AB71+AC71 -> 0 | AH71: =AE71+AF71-AG71 -> 0 | AI71: =Y71+Z71+AJ71-AD71-AG71 -> 2000 | AP71: =AL71+AN71+AM71+AO71 -> 0 | AU71: =SUM(AQ71:AT71) -> 0 | AV71: =AI71-AP71-AU71 -> 2000 | AW71: 电费300
A72: =SUBTOTAL(2,$Y$4:Y72) -> 69 | B72: NO:069 | C72: 一楼展柜 | F72: 大厅02 | G72: 黎鹏其 | I72: 1500 | K72: =I72+J72 -> 1500 | L72: 0 | V72: 200 | Y72: =I72+J72+L72+S72+T72+V72+X72 -> 1700 | AD72: =AA72+AB72+AC72 -> 0 | AH72: =AE72+AF72-AG72 -> 0 | AI72: =Y72+Z72+AJ72-AD72-AG72 -> 1700 | AP72: =AL72+AN72+AM72+AO72 -> 0 | AU72: =SUM(AQ72:AT72) -> 0 | AV72: =AI72-AP72-AU72 -> 1700
A73: =SUBTOTAL(2,$Y$4:Y73) -> 70 | B73: NO:070 | C73: 二楼档口 | D73: 2001 | E73: 27.42 | F73: 2001 | G73: 黄廉廷（临租） | H73: =E73 -> 27.42 | I73: 2500 | J73: 200 | K73: =I73+J73 -> 2700 | L73: 160 | M73: 9072 | N73: 9184 | O73: =N73-M73 -> 112 | P73: =ROUND(H73*0,0) -> 0 | Q73: =O73+P73 -> 112 | R73: 0.8 | S73: =ROUND(Q73*0.7,0) -> 78 | T73: =ROUND(Q73*R73,0) -> 90 | U73: =ROUND(H73*5.6,0) -> 154 | V73: =ROUND(U73*1.5,0) -> 231 | W73: =ROUND(H73*0.2,0) -> 5 | X73: =ROUND(W73*8.5,0) -> 43 | Y73: =I73+J73+L73+S73+T73+V73+X73 -> 3302 | AD73: =AA73+AB73+AC73 -> 0 | AH73: =AE73+AF73-AG73 -> 0 | AI73: =Y73+Z73+AJ73-AD73-AG73 -> 3302 | AP73: =AL73+AN73+AM73+AO73 -> 0 | AU73: =SUM(AQ73:AT73) -> 0 | AV73: =AI73-AP73-AU73 -> 3302
A74: =SUBTOTAL(2,$Y$4:Y74) -> 71 | B74: NO:071 | C74: 二楼档口 | D74: 2002 | E74: 19.54 | F74: 2002 | G74: 孙标然 | H74: =E74 -> 19.54 | I74: 2500 | J74: 200 | K74: =I74+J74 -> 2700 | L74: 160 | M74: 7806 | N74: 7840 | O74: =N74-M74 -> 34 | P74: =ROUND(H74*0,0) -> 0 | Q74: =O74+P74 -> 34 | R74: 0.8 | S74: =ROUND(Q74*0.7,0) -> 24 | T74: =ROUND(Q74*R74,0) -> 27 | U74: =ROUND(H74*5.6,0) -> 109 | V74: =ROUND(U74*1.5,0) -> 164 | W74: =ROUND(H74*0.2,0) -> 4 | X74: =ROUND(W74*8.5,0) -> 34 | Y74: =I74+J74+L74+S74+T74+V74+X74 -> 3109 | AD74: =AA74+AB74+AC74 -> 0 | AH74: =AE74+AF74-AG74 -> 0 | AI74: =Y74+Z74+AJ74-AD74-AG74 -> 3109 | AP74: =AL74+AN74+AM74+AO74 -> 0 | AU74: =SUM(AQ74:AT74) -> 0 | AV74: =AI74-AP74-AU74 -> 3109
A75: =SUBTOTAL(2,$Y$4:Y75) -> 72 | B75: NO:072 | C75: 二楼档口 | D75: 2003 | E75: 19.54 | F75: 2003 | G75: 陆兆亮 | H75: =E75 -> 19.54 | I75: 2500 | J75: 200 | K75: =I75+J75 -> 2700 | L75: 160 | M75: 8606 | N75: 8638 | O75: =N75-M75 -> 32 | P75: =ROUND(H75*0,0) -> 0 | Q75: =O75+P75 -> 32 | R75: 0.8 | S75: =ROUND(Q75*0.7,0) -> 22 | T75: =ROUND(Q75*R75,0) -> 26 | U75: =ROUND(H75*5.6,0) -> 109 | V75: =ROUND(U75*1.5,0) -> 164 | W75: =ROUND(H75*0.2,0) -> 4 | X75: =ROUND(W75*8.5,0) -> 34 | Y75: =I75+J75+L75+S75+T75+V75+X75 -> 3106 | AD75: =AA75+AB75+AC75 -> 0 | AH75: =AE75+AF75-AG75 -> 0 | AI75: =Y75+Z75+AJ75-AD75-AG75 -> 3106 | AP75: =AL75+AN75+AM75+AO75 -> 0 | AU75: =SUM(AQ75:AT75) -> 0 | AV75: =AI75-AP75-AU75 -> 3106
A76: =SUBTOTAL(2,$Y$4:Y76) -> 73 | B76: NO:073 | C76: 二楼档口 | D76: 2004 | E76: 19.54 | F76: 2004 | G76: 林翠侠 | H76: =E76 -> 19.54 | I76: 2500 | J76: 200 | K76: =I76+J76 -> 2700 | L76: 160 | M76: 8878 | N76: 8900 | O76: =N76-M76 -> 22 | P76: =ROUND(H76*0,0) -> 0 | Q76: =O76+P76 -> 22 | R76: 0.8 | S76: =ROUND(Q76*0.7,0) -> 15 | T76: =ROUND(Q76*R76,0) -> 18 | U76: =ROUND(H76*5.6,0) -> 109 | V76: =ROUND(U76*1.5,0) -> 164 | W76: =ROUND(H76*0.2,0) -> 4 | X76: =ROUND(W76*8.5,0) -> 34 | Y76: =I76+J76+L76+S76+T76+V76+X76 -> 3091 | AD76: =AA76+AB76+AC76 -> 0 | AH76: =AE76+AF76-AG76 -> 0 | AI76: =Y76+Z76+AJ76-AD76-AG76 -> 3091 | AP76: =AL76+AN76+AM76+AO76 -> 0 | AU76: =SUM(AQ76:AT76) -> 0 | AV76: =AI76-AP76-AU76 -> 3091
A77: =SUBTOTAL(2,$Y$4:Y77) -> 74 | B77: NO:074 | C77: 二楼档口 | D77: 2005 | E77: 19.54 | F77: 2005 | G77: 徐忠琴 | H77: =E77 -> 19.54 | I77: 2500 | J77: 200 | K77: =I77+J77 -> 2700 | L77: 160 | M77: 8650 | N77: 8692 | O77: =N77-M77 -> 42 | P77: =ROUND(H77*0,0) -> 0 | Q77: =O77+P77 -> 42 | R77: 0.8 | S77: =ROUND(Q77*0.7,0) -> 29 | T77: =ROUND(Q77*R77,0) -> 34 | U77: =ROUND(H77*5.6,0) -> 109 | V77: =ROUND(U77*1.5,0) -> 164 | W77: =ROUND(H77*0.2,0) -> 4 | X77: =ROUND(W77*8.5,0) -> 34 | Y77: =I77+J77+L77+S77+T77+V77+X77 -> 3121 | AD77: =AA77+AB77+AC77 -> 0 | AH77: =AE77+AF77-AG77 -> 0 | AI77: =Y77+Z77+AJ77-AD77-AG77 -> 3121 | AP77: =AL77+AN77+AM77+AO77 -> 0 | AU77: =SUM(AQ77:AT77) -> 0 | AV77: =AI77-AP77-AU77 -> 3121
A78: =SUBTOTAL(2,$Y$4:Y78) -> 75 | B78: NO:075 | C78: 二楼档口 | D78: 2006 | E78: 19.54 | F78: 2006 | G78: 周丽红 | H78: =E78 -> 19.54 | I78: 2500 | J78: 200 | K78: =I78+J78 -> 2700 | L78: 160 | M78: 795 | N78: 816 | O78: =N78-M78 -> 21 | P78: =ROUND(H78*0,0) -> 0 | Q78: =O78+P78 -> 21 | R78: 0.8 | S78: =ROUND(Q78*0.7,0) -> 15 | T78: =ROUND(Q78*R78,0) -> 17 | U78: =ROUND(H78*5.6,0) -> 109 | V78: =ROUND(U78*1.5,0) -> 164 | W78: =ROUND(H78*0.2,0) -> 4 | X78: =ROUND(W78*8.5,0) -> 34 | Y78: =I78+J78+L78+S78+T78+V78+X78 -> 3090 | AD78: =AA78+AB78+AC78 -> 0 | AH78: =AE78+AF78-AG78 -> 0 | AI78: =Y78+Z78+AJ78-AD78-AG78 -> 3090 | AP78: =AL78+AN78+AM78+AO78 -> 0 | AU78: =SUM(AQ78:AT78) -> 0 | AV78: =AI78-AP78-AU78 -> 3090
A79: =SUBTOTAL(2,$Y$4:Y79) -> 76 | B79: NO:076 | C79: 二楼档口 | D79: 2007 | E79: 19.54 | F79: 2007/2008 | G79: 黄伟军 | H79: =E79*2 -> 39.08 | I79: 5000 | J79: 400 | K79: =I79+J79 -> 5400 | L79: 320 | M79: 7374 | N79: 7391 | O79: =N79-M79 -> 17 | P79: =ROUND(H79*0,0) -> 0 | Q79: =O79+P79 -> 17 | R79: 0.8 | S79: =ROUND(Q79*0.7,0) -> 12 | T79: =ROUND(Q79*R79,0) -> 14 | U79: =ROUND(H79*5.6,0) -> 219 | V79: =ROUND(U79*1.5,0) -> 329 | W79: =ROUND(H79*0.2,0) -> 8 | X79: =ROUND(W79*8.5,0) -> 68 | Y79: =I79+J79+L79+S79+T79+V79+X79 -> 6143 | AD79: =AA79+AB79+AC79 -> 0 | AH79: =AE79+AF79-AG79 -> 0 | AI79: =Y79+Z79+AJ79-AD79-AG79 -> 6143 | AP79: =AL79+AN79+AM79+AO79 -> 0 | AU79: =SUM(AQ79:AT79) -> 0 | AV79: =AI79-AP79-AU79 -> 6143
A80: =SUBTOTAL(2,$Y$4:Y80) -> 77 | B80: NO:077 | C80: 二楼档口 | D80: 2008 | E80: 19.54 | F80: 2008 | G80: 黄伟军 | K80: =I80+J80 -> 0 | L80: 0 | M80: 12 | N80: 52 | O80: =N80-M80 -> 40 | P80: =ROUND(H80*0,0) -> 0 | Q80: =O80+P80 -> 40 | R80: 0.8 | S80: =ROUND(Q80*0.7,0) -> 28 | T80: =ROUND(Q80*R80,0) -> 32 | U80: =ROUND(H80*5.6,0) -> 0 | V80: =ROUND(U80*1.5,0) -> 0 | W80: =ROUND(H80*0.2,0) -> 0 | X80: =ROUND(W80*8.5,0) -> 0 | Y80: =I80+J80+L80+S80+T80+V80+X80 -> 60 | AD80: =AA80+AB80+AC80 -> 0 | AH80: =AE80+AF80-AG80 -> 0 | AI80: =Y80+Z80+AJ80-AD80-AG80 -> 60 | AP80: =AL80+AN80+AM80+AO80 -> 0 | AU80: =SUM(AQ80:AT80) -> 0 | AV80: =AI80-AP80-AU80 -> 60
A81: =SUBTOTAL(2,$Y$4:Y81) -> 78 | B81: NO:078 | C81: 二楼档口 | D81: 2009 | E81: 19.54 | F81: 2009 | G81: 冯世豪 | H81: =E81 -> 19.54 | I81: 2500 | J81: 200 | K81: =I81+J81 -> 2700 | L81: 160 | M81: 4634 | N81: 4660 | O81: =N81-M81 -> 26 | P81: =ROUND(H81*0,0) -> 0 | Q81: =O81+P81 -> 26 | R81: 0.8 | S81: =ROUND(Q81*0.7,0) -> 18 | T81: =ROUND(Q81*R81,0) -> 21 | U81: =ROUND(H81*5.6,0) -> 109 | V81: =ROUND(U81*1.5,0) -> 164 | W81: =ROUND(H81*0.2,0) -> 4 | X81: =ROUND(W81*8.5,0) -> 34 | Y81: =I81+J81+L81+S81+T81+V81+X81 -> 3097 | AD81: =AA81+AB81+AC81 -> 0 | AH81: =AE81+AF81-AG81 -> 0 | AI81: =Y81+Z81+AJ81-AD81-AG81 -> 3097 | AP81: =AL81+AN81+AM81+AO81 -> 0 | AU81: =SUM(AQ81:AT81) -> 0 | AV81: =AI81-AP81-AU81 -> 3097
A82: =SUBTOTAL(2,$Y$4:Y82) -> 79 | B82: NO:079 | C82: 二楼档口 | D82: 2010 | E82: 19.54 | F82: 2010 | G82: 王既异 | H82: =E82 -> 19.54 | I82: 2500 | J82: 200 | K82: =I82+J82 -> 2700 | L82: 160 | M82: 1267 | N82: 1301 | O82: =N82-M82 -> 34 | P82: =ROUND(H82*0,0) -> 0 | Q82: =O82+P82 -> 34 | R82: 0.8 | S82: =ROUND(Q82*0.7,0) -> 24 | T82: =ROUND(Q82*R82,0) -> 27 | U82: =ROUND(H82*5.6,0) -> 109 | V82: =ROUND(U82*1.5,0) -> 164 | W82: =ROUND(H82*0.2,0) -> 4 | X82: =ROUND(W82*8.5,0) -> 34 | Y82: =I82+J82+L82+S82+T82+V82+X82 -> 3109 | AD82: =AA82+AB82+AC82 -> 0 | AH82: =AE82+AF82-AG82 -> 0 | AI82: =Y82+Z82+AJ82-AD82-AG82 -> 3109 | AP82: =AL82+AN82+AM82+AO82 -> 0 | AU82: =SUM(AQ82:AT82) -> 0 | AV82: =AI82-AP82-AU82 -> 3109
A83: =SUBTOTAL(2,$Y$4:Y83) -> 80 | B83: NO:080 | C83: 二楼档口 | D83: 2011 | E83: 19.54 | F83: 2011 | G83: 颜艳军 | H83: =E83 -> 19.54 | I83: 2500 | J83: 200 | K83: =I83+J83 -> 2700 | L83: 160 | M83: 8680 | N83: 8743 | O83: =N83-M83 -> 63 | P83: =ROUND(H83*0,0) -> 0 | Q83: =O83+P83 -> 63 | R83: 0.8 | S83: =ROUND(Q83*0.7,0) -> 44 | T83: =ROUND(Q83*R83,0) -> 50 | U83: =ROUND(H83*5.6,0) -> 109 | V83: =ROUND(U83*1.5,0) -> 164 | W83: =ROUND(H83*0.2,0) -> 4 | X83: =ROUND(W83*8.5,0) -> 34 | Y83: =I83+J83+L83+S83+T83+V83+X83 -> 3152 | AD83: =AA83+AB83+AC83 -> 0 | AH83: =AE83+AF83-AG83 -> 0 | AI83: =Y83+Z83+AJ83-AD83-AG83 -> 3152 | AP83: =AL83+AN83+AM83+AO83 -> 0 | AU83: =SUM(AQ83:AT83) -> 0 | AV83: =AI83-AP83-AU83 -> 3152
A84: =SUBTOTAL(2,$Y$4:Y84) -> 81 | B84: NO:081 | C84: 二楼档口 | D84: 2012 | E84: 19.54 | F84: 2012 | G84: 卢永永 | H84: =E84 -> 19.54 | I84: 2500 | J84: 200 | K84: =I84+J84 -> 2700 | L84: 160 | M84: 554 | N84: 592 | O84: =N84-M84 -> 38 | P84: =ROUND(H84*0,0) -> 0 | Q84: =O84+P84 -> 38 | R84: 0.8 | S84: =ROUND(Q84*0.7,0) -> 27 | T84: =ROUND(Q84*R84,0) -> 30 | U84: =ROUND(H84*5.6,0) -> 109 | V84: =ROUND(U84*1.5,0) -> 164 | W84: =ROUND(H84*0.2,0) -> 4 | X84: =ROUND(W84*8.5,0) -> 34 | Y84: =I84+J84+L84+S84+T84+V84+X84 -> 3115 | AD84: =AA84+AB84+AC84 -> 0 | AH84: =AE84+AF84-AG84 -> 0 | AI84: =Y84+Z84+AJ84-AD84-AG84 -> 3115 | AP84: =AL84+AN84+AM84+AO84 -> 0 | AU84: =SUM(AQ84:AT84) -> 0 | AV84: =AI84-AP84-AU84 -> 3115
A85: =SUBTOTAL(2,$Y$4:Y85) -> 82 | B85: NO:082 | C85: 二楼档口 | D85: 2013 | E85: 19.54 | F85: 2013 | G85: 陈高俊 | H85: =E85 -> 19.54 | I85: 2500 | J85: 200 | K85: =I85+J85 -> 2700 | L85: 160 | M85: 2047 | N85: 2056 | O85: =N85-M85 -> 9 | P85: =ROUND(H85*0,0) -> 0 | Q85: =O85+P85 -> 9 | R85: 0.8 | S85: =ROUND(Q85*0.7,0) -> 6 | T85: =ROUND(Q85*R85,0) -> 7 | U85: =ROUND(H85*5.6,0) -> 109 | V85: =ROUND(U85*1.5,0) -> 164 | W85: =ROUND(H85*0.2,0) -> 4 | X85: =ROUND(W85*8.5,0) -> 34 | Y85: =I85+J85+L85+S85+T85+V85+X85 -> 3071 | AD85: =AA85+AB85+AC85 -> 0 | AH85: =AE85+AF85-AG85 -> 0 | AI85: =Y85+Z85+AJ85-AD85-AG85 -> 3071 | AP85: =AL85+AN85+AM85+AO85 -> 0 | AU85: =SUM(AQ85:AT85) -> 0 | AV85: =AI85-AP85-AU85 -> 3071
A86: =SUBTOTAL(2,$Y$4:Y86) -> 83 | B86: NO:083 | C86: 二楼档口 | D86: 2014 | E86: 19.54 | F86: 2014 | G86: 张顶 | H86: =E86 -> 19.54 | I86: 2500 | J86: 200 | K86: =I86+J86 -> 2700 | L86: 160 | M86: 2403 | N86: 2405 | O86: =N86-M86 -> 2 | P86: =ROUND(H86*0,0) -> 0 | Q86: =O86+P86 -> 2 | R86: 0.8 | S86: =ROUND(Q86*0.7,0) -> 1 | T86: =ROUND(Q86*R86,0) -> 2 | U86: =ROUND(H86*5.6,0) -> 109 | V86: =ROUND(U86*1.5,0) -> 164 | W86: =ROUND(H86*0.2,0) -> 4 | X86: =ROUND(W86*8.5,0) -> 34 | Y86: =I86+J86+L86+S86+T86+V86+X86 -> 3061 | AD86: =AA86+AB86+AC86 -> 0 | AH86: =AE86+AF86-AG86 -> 0 | AI86: =Y86+Z86+AJ86-AD86-AG86 -> 3061 | AP86: =AL86+AN86+AM86+AO86 -> 0 | AU86: =SUM(AQ86:AT86) -> 0 | AV86: =AI86-AP86-AU86 -> 3061
A87: =SUBTOTAL(2,$Y$4:Y87) -> 84 | B87: NO:084 | C87: 二楼档口 | D87: 2015 | E87: 19.54 | F87: 2015 | G87: 冯章权 | H87: =E87 -> 19.54 | I87: 2500 | J87: 200 | K87: =I87+J87 -> 2700 | L87: 160 | M87: 9589 | N87: 9615 | O87: =N87-M87 -> 26 | P87: =ROUND(H87*0,0) -> 0 | Q87: =O87+P87 -> 26 | R87: 0.8 | S87: =ROUND(Q87*0.7,0) -> 18 | T87: =ROUND(Q87*R87,0) -> 21 | U87: =ROUND(H87*5.6,0) -> 109 | V87: =ROUND(U87*1.5,0) -> 164 | W87: =ROUND(H87*0.2,0) -> 4 | X87: =ROUND(W87*8.5,0) -> 34 | Y87: =I87+J87+L87+S87+T87+V87+X87 -> 3097 | AD87: =AA87+AB87+AC87 -> 0 | AH87: =AE87+AF87-AG87 -> 0 | AI87: =Y87+Z87+AJ87-AD87-AG87 -> 3097 | AP87: =AL87+AN87+AM87+AO87 -> 0 | AU87: =SUM(AQ87:AT87) -> 0 | AV87: =AI87-AP87-AU87 -> 3097
A88: =SUBTOTAL(2,$Y$4:Y88) -> 85 | B88: NO:085 | C88: 二楼档口 | D88: 2016 | E88: 19.54 | F88: 2016 | G88: 黎慧敏 | H88: =E88 -> 19.54 | I88: 2500 | J88: 200 | K88: =I88+J88 -> 2700 | L88: 160 | M88: 9080 | N88: 9131 | O88: =N88-M88 -> 51 | P88: =ROUND(H88*0,0) -> 0 | Q88: =O88+P88 -> 51 | R88: 0.8 | S88: =ROUND(Q88*0.7,0) -> 36 | T88: =ROUND(Q88*R88,0) -> 41 | U88: =ROUND(H88*5.6,0) -> 109 | V88: =ROUND(U88*1.5,0) -> 164 | W88: =ROUND(H88*0.2,0) -> 4 | X88: =ROUND(W88*8.5,0) -> 34 | Y88: =I88+J88+L88+S88+T88+V88+X88 -> 3135 | AD88: =AA88+AB88+AC88 -> 0 | AH88: =AE88+AF88-AG88 -> 0 | AI88: =Y88+Z88+AJ88-AD88-AG88 -> 3135 | AP88: =AL88+AN88+AM88+AO88 -> 0 | AU88: =SUM(AQ88:AT88) -> 0 | AV88: =AI88-AP88-AU88 -> 3135
A89: =SUBTOTAL(2,$Y$4:Y89) -> 86 | B89: NO:086 | C89: 二楼档口 | D89: 2017 | E89: 19.54 | F89: 2017 | G89: 黎慧敏 | H89: =E89 -> 19.54 | I89: 2500 | J89: 200 | K89: =I89+J89 -> 2700 | L89: 160 | M89: 9485 | N89: 9532 | O89: =N89-M89 -> 47 | P89: =ROUND(H89*0,0) -> 0 | Q89: =O89+P89 -> 47 | R89: 0.8 | S89: =ROUND(Q89*0.7,0) -> 33 | T89: =ROUND(Q89*R89,0) -> 38 | U89: =ROUND(H89*5.6,0) -> 109 | V89: =ROUND(U89*1.5,0) -> 164 | W89: =ROUND(H89*0.2,0) -> 4 | X89: =ROUND(W89*8.5,0) -> 34 | Y89: =I89+J89+L89+S89+T89+V89+X89 -> 3129 | AD89: =AA89+AB89+AC89 -> 0 | AH89: =AE89+AF89-AG89 -> 0 | AI89: =Y89+Z89+AJ89-AD89-AG89 -> 3129 | AP89: =AL89+AN89+AM89+AO89 -> 0 | AU89: =SUM(AQ89:AT89) -> 0 | AV89: =AI89-AP89-AU89 -> 3129
A90: =SUBTOTAL(2,$Y$4:Y90) -> 87 | B90: NO:087 | C90: 二楼档口 | D90: 2018 | E90: 19.54 | F90: 2018 | G90: 钟丽梅 | H90: =E90 -> 19.54 | I90: 2500 | J90: 200 | K90: =I90+J90 -> 2700 | L90: 160 | M90: 2004 | N90: 2099 | O90: =N90-M90 -> 95 | P90: =ROUND(H90*0,0) -> 0 | Q90: =O90+P90 -> 95 | R90: 0.8 | S90: =ROUND(Q90*0.7,0) -> 67 | T90: =ROUND(Q90*R90,0) -> 76 | U90: =ROUND(H90*5.6,0) -> 109 | V90: =ROUND(U90*1.5,0) -> 164 | W90: =ROUND(H90*0.2,0) -> 4 | X90: =ROUND(W90*8.5,0) -> 34 | Y90: =I90+J90+L90+S90+T90+V90+X90 -> 3201 | AD90: =AA90+AB90+AC90 -> 0 | AH90: =AE90+AF90-AG90 -> 0 | AI90: =Y90+Z90+AJ90-AD90-AG90 -> 3201 | AP90: =AL90+AN90+AM90+AO90 -> 0 | AU90: =SUM(AQ90:AT90) -> 0 | AV90: =AI90-AP90-AU90 -> 3201
A91: =SUBTOTAL(2,$Y$4:Y91) -> 88 | B91: NO:088 | C91: 二楼档口 | D91: 2019 | E91: 19.54 | F91: 2019 | G91: 周欣雨 | H91: =E91 -> 19.54 | I91: 2500 | J91: 200 | K91: =I91+J91 -> 2700 | L91: 160 | M91: 1295 | N91: 1359 | O91: =N91-M91 -> 64 | P91: =ROUND(H91*0,0) -> 0 | Q91: =O91+P91 -> 64 | R91: 0.8 | S91: =ROUND(Q91*0.7,0) -> 45 | T91: =ROUND(Q91*R91,0) -> 51 | U91: =ROUND(H91*5.6,0) -> 109 | V91: =ROUND(U91*1.5,0) -> 164 | W91: =ROUND(H91*0.2,0) -> 4 | X91: =ROUND(W91*8.5,0) -> 34 | Y91: =I91+J91+L91+S91+T91+V91+X91 -> 3154 | AD91: =AA91+AB91+AC91 -> 0 | AH91: =AE91+AF91-AG91 -> 0 | AI91: =Y91+Z91+AJ91-AD91-AG91 -> 3154 | AP91: =AL91+AN91+AM91+AO91 -> 0 | AU91: =SUM(AQ91:AT91) -> 0 | AV91: =AI91-AP91-AU91 -> 3154
A92: =SUBTOTAL(2,$Y$4:Y92) -> 89 | B92: NO:089 | C92: 二楼档口 | D92: 2020 | E92: 19.54 | F92: 2020 | G92: 朱楚帆 | H92: =E92 -> 19.54 | I92: 2500 | J92: 200 | K92: =I92+J92 -> 2700 | L92: 160 | M92: 8770 | N92: 8808 | O92: =N92-M92 -> 38 | P92: =ROUND(H92*0,0) -> 0 | Q92: =O92+P92 -> 38 | R92: 0.8 | S92: =ROUND(Q92*0.7,0) -> 27 | T92: =ROUND(Q92*R92,0) -> 30 | U92: =ROUND(H92*5.6,0) -> 109 | V92: =ROUND(U92*1.5,0) -> 164 | W92: =ROUND(H92*0.2,0) -> 4 | X92: =ROUND(W92*8.5,0) -> 34 | Y92: =I92+J92+L92+S92+T92+V92+X92 -> 3115 | AD92: =AA92+AB92+AC92 -> 0 | AH92: =AE92+AF92-AG92 -> 0 | AI92: =Y92+Z92+AJ92-AD92-AG92 -> 3115 | AP92: =AL92+AN92+AM92+AO92 -> 0 | AU92: =SUM(AQ92:AT92) -> 0 | AV92: =AI92-AP92-AU92 -> 3115
... A97: =SUBTOTAL(2,$Y$4:Y97) -> 94 | B97: NO:094 | C97: 二楼档口 | D97: 2025 | E97: 23.84 | F97: 2025 | G97: 焦小峰 | H97: =E97 -> 23.84 | I97: 2500 | J97: 200 | K97: =I97+J97 -> 2700 | L97: 160 | M97: 853 | N97: 870 | O97: =N97-M97 -> 17 | P97: =ROUND(H97*0,0) -> 0 | Q97: =O97+P97 -> 17 | R97: 0.8 | S97: =ROUND(Q97*0.7,0) -> 12 | T97: =ROUND(Q97*R97,0) -> 14 | U97: =ROUND(H97*5.6,0) -> 134 | V97: =ROUND(U97*1.5,0) -> 201 | W97: =ROUND(H97*0.2,0) -> 5 | X97: =ROUND(W97*8.5,0) -> 43 | Y97: =I97+J97+L97+S97+T97+V97+X97 -> 3130 | AD97: =AA97+AB97+AC97 -> 0 | AH97: =AE97+AF97-AG97 -> 0 | AI97: =Y97+Z97+AJ97-AD97-AG97 -> 3130 | AP97: =AL97+AN97+AM97+AO97 -> 0 | AU97: =SUM(AQ97:AT97) -> 0 | AV97: =AI97-AP97-AU97 -> 3130
A98: =SUBTOTAL(2,$Y$4:Y98) -> 95 | B98: NO:095 | C98: 二楼档口 | D98: 2026 | E98: 38.03 | F98: 2026 | G98: 办公室 | K98: =I98+J98 -> 0 | M98: 5755 | N98: 5755 | O98: =N98-M98 -> 0 | P98: =ROUND(H97*0,0) -> 0 | Q98: =O98+P98 -> 0 | R98: 0.8 | S98: =ROUND(Q98*0.7,0) -> 0 | T98: =ROUND(Q98*R98,0) -> 0 | U98: =ROUND(H98*0,0) -> 0 | V98: =ROUND(U98*1.5,0) -> 0 | W98: =ROUND(H98*0.2,0) -> 0 | Y98: =I98+J98+L98+S98+T98+V98+X98 -> 0 | AD98: =AA98+AB98+AC98 -> 0 | AH98: =AE98+AF98-AG98 -> 0 | AI98: =Y98+Z98+AJ98-AD98-AG98 -> 0 | AP98: =AL98+AN98+AM98+AO98 -> 0 | AU98: =SUM(AQ98:AT98) -> 0 | AV98: =AI98-AP98-AU98 -> 0
A99: =SUBTOTAL(2,$Y$4:Y99) -> 96 | B99: NO:096 | C99: 二楼档口 | D99: 2027 | E99: 39.33 | F99: 2027 | G99: 办公室 | K99: =I99+J99 -> 0 | M99: 5816 | N99: 5816 | O99: =N99-M99 -> 0 | P99: =ROUND(H98*0,0) -> 0 | Q99: =O99+P99 -> 0 | R99: 0.8 | S99: =ROUND(Q99*0.7,0) -> 0 | T99: =ROUND(Q99*R99,0) -> 0 | U99: =ROUND(H99*0,0) -> 0 | V99: =ROUND(U99*1.5,0) -> 0 | W99: =ROUND(H99*0.2,0) -> 0 | Y99: =I99+J99+L99+S99+T99+V99+X99 -> 0 | AD99: =AA99+AB99+AC99 -> 0 | AH99: =AE99+AF99-AG99 -> 0 | AI99: =Y99+Z99+AJ99-AD99-AG99 -> 0 | AP99: =AL99+AN99+AM99+AO99 -> 0 | AU99: =SUM(AQ99:AT99) -> 0 | AV99: =AI99-AP99-AU99 -> 0
A100: =SUBTOTAL(2,$Y$4:Y100) -> 97 | B100: NO:097 | C100: 二楼档口 | D100: 2029 | E100: 18.32 | F100: 2029 | G100: 郭林红 | H100: =E100 -> 18.32 | I100: 2500 | J100: 200 | K100: =I100+J100 -> 2700 | L100: 160 | M100: 2976 | N100: 3072 | O100: =N100-M100 -> 96 | P100: =ROUND(H100*0,0) -> 0 | Q100: =O100+P100 -> 96 | R100: 0.8 | S100: =ROUND(Q100*0.7,0) -> 67 | T100: =ROUND(Q100*R100,0) -> 77 | U100: =ROUND(H100*5.6,0) -> 103 | V100: =ROUND(U100*1.5,0) -> 155 | W100: =ROUND(H100*0.2,0) -> 4 | X100: =ROUND(W100*8.5,0) -> 34 | Y100: =I100+J100+L100+S100+T100+V100+X100 -> 3193 | AD100: =AA100+AB100+AC100 -> 0 | AH100: =AE100+AF100-AG100 -> 0 | AI100: =Y100+Z100+AJ100-AD100-AG100 -> 3193 | AP100: =AL100+AN100+AM100+AO100 -> 0 | AU100: =SUM(AQ100:AT100) -> 0 | AV100: =AI100-AP100-AU100 -> 3193
A101: =SUBTOTAL(2,$Y$4:Y101) -> 98 | B101: NO:098 | C101: 二楼档口 | D101: 2030 | E101: 16.54 | F101: 2030 | G101: 郭林红 | H101: =E101 -> 16.54 | I101: 2500 | J101: 200 | K101: =I101+J101 -> 2700 | L101: 160 | M101: 9094 | N101: 9140 | O101: =N101-M101 -> 46 | P101: =ROUND(H101*0,0) -> 0 | Q101: =O101+P101 -> 46 | R101: 0.8 | S101: =ROUND(Q101*0.7,0) -> 32 | T101: =ROUND(Q101*R101,0) -> 37 | U101: =ROUND(H101*5.6,0) -> 93 | V101: =ROUND(U101*1.5,0) -> 140 | W101: =ROUND(H101*0.2,0) -> 3 | X101: =ROUND(W101*8.5,0) -> 26 | Y101: =I101+J101+L101+S101+T101+V101+X101 -> 3095 | AD101: =AA101+AB101+AC101 -> 0 | AH101: =AE101+AF101-AG101 -> 0 | AI101: =Y101+Z101+AJ101-AD101-AG101 -> 3095 | AP101: =AL101+AN101+AM101+AO101 -> 0 | AU101: =SUM(AQ101:AT101) -> 0 | AV101: =AI101-AP101-AU101 -> 3095
A102: =SUBTOTAL(2,$Y$4:Y102) -> 99 | B102: NO:099 | C102: 二楼档口 | D102: 2031 | E102: 16.54 | F102: 2031 | G102: 习国斌 | H102: =E102 -> 16.54 | I102: 2500 | J102: 200 | K102: =I102+J102 -> 2700 | L102: 160 | M102: 9551 | N102: 9581 | O102: =N102-M102 -> 30 | P102: =ROUND(H102*0,0) -> 0 | Q102: =O102+P102 -> 30 | R102: 0.8 | S102: =ROUND(Q102*0.7,0) -> 21 | T102: =ROUND(Q102*R102,0) -> 24 | U102: =ROUND(H102*5.6,0) -> 93 | V102: =ROUND(U102*1.5,0) -> 140 | W102: =ROUND(H102*0.2,0) -> 3 | X102: =ROUND(W102*8.5,0) -> 26 | Y102: =I102+J102+L102+S102+T102+V102+X102 -> 3071 | AD102: =AA102+AB102+AC102 -> 0 | AH102: =AE102+AF102-AG102 -> 0 | AI102: =Y102+Z102+AJ102-AD102-AG102 -> 3071 | AP102: =AL102+AN102+AM102+AO102 -> 0 | AU102: =SUM(AQ102:AT102) -> 0 | AV102: =AI102-AP102-AU102 -> 3071
A103: =SUBTOTAL(2,$Y$4:Y103) -> 100 | B103: NO:100 | C103: 二楼档口 | D103: 2032 | E103: 16.54 | F103: 2032 | G103: 张明亮 | H103: =E103 -> 16.54 | I103: 2500 | J103: 200 | K103: =I103+J103 -> 2700 | L103: 160 | M103: 8940 | N103: 8973 | O103: =N103-M103 -> 33 | P103: =ROUND(H103*0,0) -> 0 | Q103: =O103+P103 -> 33 | R103: 0.8 | S103: =ROUND(Q103*0.7,0) -> 23 | T103: =ROUND(Q103*R103,0) -> 26 | U103: =ROUND(H103*5.6,0) -> 93 | V103: =ROUND(U103*1.5,0) -> 140 | W103: =ROUND(H103*0.2,0) -> 3 | X103: =ROUND(W103*8.5,0) -> 26 | Y103: =I103+J103+L103+S103+T103+V103+X103 -> 3075 | AD103: =AA103+AB103+AC103 -> 0 | AH103: =AE103+AF103-AG103 -> 0 | AI103: =Y103+Z103+AJ103-AD103-AG103 -> 3075 | AP103: =AL103+AN103+AM103+AO103 -> 0 | AU103: =SUM(AQ103:AT103) -> 0 | AV103: =AI103-AP103-AU103 -> 3075
A104: =SUBTOTAL(2,$Y$4:Y104) -> 101 | B104: NO:101 | C104: 二楼档口 | D104: 2033 | E104: 16.54 | F104: 2033 | G104: 余芝玲 | H104: =E104 -> 16.54 | I104: 2500 | J104: 200 | K104: =I104+J104 -> 2700 | L104: 160 | M104: 9622 | N104: 9641 | O104: =N104-M104 -> 19 | P104: =ROUND(H104*0,0) -> 0 | Q104: =O104+P104 -> 19 | R104: 0.8 | S104: =ROUND(Q104*0.7,0) -> 13 | T104: =ROUND(Q104*R104,0) -> 15 | U104: =ROUND(H104*5.6,0) -> 93 | V104: =ROUND(U104*1.5,0) -> 140 | W104: =ROUND(H104*0.2,0) -> 3 | X104: =ROUND(W104*8.5,0) -> 26 | Y104: =I104+J104+L104+S104+T104+V104+X104 -> 3054 | AD104: =AA104+AB104+AC104 -> 0 | AH104: =AE104+AF104-AG104 -> 0 | AI104: =Y104+Z104+AJ104-AD104-AG104 -> 3054 | AP104: =AL104+AN104+AM104+AO104 -> 0 | AU104: =SUM(AQ104:AT104) -> 0 | AV104: =AI104-AP104-AU104 -> 3054 | AW104: 创意园
...

Sheet Sheet6
A1: 合同
A2: 档号 | B2: 档主名 | H2: 档口号 | I2: 商户名 | J2: 租金 | K2: 管理费
C3: 月租 | D3: 管理费
A4: 1001-01（临一） | B4: 何具达 | C4: 3052 | D4: 210 | H4: 1001-01（临一） | I4: 何具达 | J4: 3052 | K4: 210 | L4: =C4-J4 -> 0 | M4: =D4-K4 -> 0
A5: 1001 | B5: 邓凤强 | C5: 4200 | D5: 500 | H5: 1001 | I5: 邓凤强 | J5: 4200 | K5: 500
A6: 1002 | B6: 苏建柳 | C6: 1500 | H6: 1002 | I6: 苏建柳 | J6: 1500
A7: 1003 | B7: 李鹏飞 | C7: 3000 | D7: 0 | H7: 1003/1004 | I7: 李鹏飞 | J7: 3000
A8: 1005 | B8: 黄腾凌 | C8: 1200 | D8: 200 | H8: 1005 | I8: 黄腾凌 | J8: 1200 | K8: 200
A9: 1006 | B9: 刘展 | C9: 1200 | D9: 200 | H9: 1006 | I9: 刘展 | J9: 1200 | K9: 200
A10: 1007 | B10: 王正庚 | C10: 1200 | D10: 0 | H10: 1007 | I10: 王正庚 | J10: 1200
A11: 1008 | B11: 潭日标 | C11: 2500 | D11: 0 | H11: 1008/1009 | I11: 潭日标 | J11: 2500
A12: 1009 | B12: 潭日标 | H12: 1009 | I12: 潭日标
A13: 1010 | B13: 王长梅 | C13: 1500 | H13: 1010 | I13: 王长梅 | J13: 1500
A14: 1011 | B14: 段邦彦 | C14: 750 | H14: 1011 | I14: 段邦彦 | J14: 750
A15: 1012 | B15: 李文学 | C15: 750 | H15: 1012 | I15: 李文学 | J15: 750 | K15: 0
A16: 1013 | B16: 揭英祥 | C16: 1200 | H16: 1013 | I16: 揭英祥 | J16: 1200
A17: 1014 | B17: 陈文彬 | C17: 1500 | H17: 1014 | I17: 陈文彬 | J17: 1500 | K17: 0
A18: 1015 | B18: 张平君 | C18: 1200 | H18: 1015 | I18: 张平君 | J18: 1200 | K18: 0
A19: 1016 | B19: 卢汉总 | C19: 2800 | D19: 200 | H19: 1016/1017 | I19: 卢汉总 | J19: 2800 | K19: 200
A20: 1018 | B20: 白成滔 | C20: 2000 | H20: 1018 | I20: 白成滔 | J20: 2000 | K20: 0
A21: 1019 | B21: 王长梅 | C21: 1200 | H21: 1019 | I21: 王长梅 | J21: 1200
A22: 1020 | B22: 张爱玲 | C22: 1200 | H22: 1020 | I22: 张爱玲 | J22: 1200 | K22: 0
A23: 1021 | B23: 刘光全 | C23: 1200 | D23: 200 | H23: 1021 | I23: 刘光全 | J23: 1200 | K23: 200
A24: 1022 | B24: 庄诗霖 | C24: 2200 | H24: 1022 | I24: 庄诗霖 | J24: 2200
A25: 1023 | B25: 黎培健 | C25: 600 | D25: 0 | H25: 1023 | I25: 黎培健 | J25: 600 | K25: 0
A26: 1024 | B26: 王小军 | C26: 1448 | H26: 1024 | I26: 王小军 | J26: 1448
A27: 1025 | B27: 李雄辉 | C27: 4200 | D27: 500 | H27: 1025 | I27: 林小武 | J27: 4200 | K27: 500
A28: 1025-A | B28: 苏建柳 | C28: 2206 | D28: 250 | H28: 1025-A | I28: 苏建柳 | J28: 2206 | K28: 250
A29: 1026 | B29: 马旦 | C29: 4202 | D29: 500 | H29: 1026 | I29: 马旦 | J29: 4202 | K29: 500
A30: 1027 | B30: 范宏成 | C30: 4200 | D30: 500 | H30: 1027 | I30: 范宏成 | J30: 4200 | K30: 500
A31: 1028 | B31: 阮文彬 | C31: 4200 | D31: 500 | H31: 1028 | I31: 阮文彬 | J31: 4200 | K31: 500
A32: 1029 | B32: 钟玲玲 | C32: 4200 | D32: 500 | H32: 1029 | I32: 钟玲玲 | J32: 4200 | K32: 500
A33: 1030 | B33: 覃燕芬 | C33: 4200 | D33: 500 | H33: 1030 | I33: 覃燕芬 | J33: 4200 | K33: 500
A34: 1031 | B34: 陈恳 | C34: 4200 | D34: 500 | H34: 1031 | I34: 陈恳 | J34: 4200 | K34: 500
A35: 1032 | B35: 范琼静 | C35: 4200 | D35: 500 | H35: 1032 | I35: 范琼静 | J35: 4200 | K35: 500
A36: 1033 | B36: 蔡安琦 | C36: 4200 | D36: 500 | H36: 1033 | I36: 蔡安琦 | J36: 4200 | K36: 500
A37: 1034 | B37: 杨志鸿 | C37: 4200 | D37: 500 | H37: 1034 | I37: 杨志鸿 | J37: 4200 | K37: 500
A38: 1035 | B38: 王正庚 | C38: 4200 | D38: 500 | H38: 1035 | I38: 廖文怀 | J38: 4200 | K38: 500
A39: 1036 | B39: 李耿坚 | C39: 4200 | D39: 500 | H39: 1036 | I39: 李耿坚 | J39: 4200 | K39: 500
A40: 1037 | B40: 范宏健 | C40: 4200 | D40: 500 | H40: 1037 | I40: 范宏健 | J40: 4200 | K40: 500
A41: 1038 | B41: 杨义坤 | C41: 4200 | D41: 500 | H41: 1038
A42: 1039 | B42: 陈秋香 | C42: 4200 | D42: 500 | H42: 1039 | I42: 陈秋香 | J42: 4200 | K42: 500
A43: 1040 | B43: 陈少华 | C43: 4202 | D43: 500 | H43: 1040 | I43: 陈少华 | J43: 4202 | K43: 500
A44: 1041 | B44: 林文浩 | C44: 4200 | H44: 1041 | I44: 林文浩 | J44: 4200 | K44: 0
A45: 1042 | B45: 陈俊炳 | C45: 4200 | D45: 500 | H45: 1042 | I45: 陈俊炳 | J45: 4200 | K45: 500
A46: 1043 | B46: 曾丽 | C46: 3500 | D46: 0 | H46: 1043 | I46: 曾丽 | J46: 3500 | K46: 0
A47: 1044 | B47: 杨要 | C47: 4202 | D47: 200 | H47: 1044 | I47: 杨要 | J47: 4202 | K47: 200
A48: 1045 | B48: 陈柳旋 | C48: 4200 | D48: 500 | H48: 1045 | I48: 陈柳旋 | J48: 4200 | K48: 500
A49: 1046 | B49: 胡命礼 | C49: 4200 | D49: 500 | H49: 1046 | I49: 胡命礼 | J49: 4200 | K49: 500
A50: 1047 | B50: 黄廉颖 | C50: 4200 | D50: 500 | H50: 1047 | I50: 黄廉颖 | J50: 4200 | K50: 500
A51: 1048 | B51: 李嘉格 | C51: 4202 | D51: 500 | H51: 1048 | I51: 李嘉格 | J51: 4202 | K51: 500
A52: 1049 | B52: 何飞 | C52: 4200 | D52: 500 | H52: 1049 | I52: 何飞 | J52: 4200 | K52: 500
A53: 1050 | B53: 刘玲 | C53: 4200 | D53: 500 | H53: 1050 | I53: 易金启 | J53: 4200 | K53: 500
A54: 1051 | B54: 陈慧芳 | C54: 4200 | D54: 500 | H54: 1051 | I54: 余华生 | J54: 4200 | K54: 500
A55: 1052 | B55: 李硕果 | C55: 4202 | D55: 500 | H55: 1052 | I55: 李硕果 | J55: 4202 | K55: 500
A56: 1053 | B56: 黄文波 | C56: 4202 | D56: 500 | H56: 1053 | I56: 黄文波 | J56: 4202 | K56: 500
... A64: 1061 | B64: 李丽 | C64: 3500 | D64: 200 | H64: 1061 | I64: 李丽 | J64: 3500 | K64: 200
A65: 1062 | B65: 章芳琴 | C65: 3000 | H65: 1062 | I65: 章芳琴 | J65: 3000 | K65: 0
A66: 1063 | B66: 余迎龙 | C66: 1600 | D66: 0 | H66: 1063 | I66: 余迎龙 | J66: 1600 | K66: 0
A67: 1065 | B67: 万军银 | C67: 1200 | D67: 0 | H67: 1065 | I67: 万军银 | J67: 1200 | K67: 0
A68: 1066 | B68: 卢永润 | C68: 4200 | D68: 500 | H68: 1066 | I68: 卢永润 | J68: 4200 | K68: 500
A69: 1067展柜 | B69: 章芳琴 | C69: 1500 | H69: 1067展柜(全包） | I69: 章芳琴 | J69: 1500
A70: 1068展柜 | B70: 黄伟慧 | C70: 1200 | H70: 1068展柜/1069展柜 | I70: 黄伟慧 | J70: 1200
A71: 大厅01 | B71: 张文英 | C71: 2000 | H71: 大厅01 | I71: 张文英 | J71: 2000
A72: 大厅02 | B72: 黎鹏其 | C72: 1500 | H72: 大厅02 | I72: 黎鹏其 | J72: 1500
A73: 2001 | B73: 黄廉廷 | C73: 1500 | H73: 2001 | I73: 黄廉廷（临租） | J73: 2500 | K73: 200
A74: 2002 | B74: 孙标然 | C74: 2500 | D74: 200 | H74: 2002 | I74: 孙标然 | J74: 2500 | K74: 200
A75: 2003 | B75: 陆兆亮 | C75: 2500 | D75: 200 | H75: 2003 | I75: 陆兆亮 | J75: 2500 | K75: 200
A76: 2004 | B76: 林翠侠 | C76: 2500 | D76: 200 | H76: 2004 | I76: 林翠侠 | J76: 2500 | K76: 200
A77: 2005 | B77: 徐忠琴 | C77: 2500 | D77: 200 | H77: 2005 | I77: 徐忠琴 | J77: 2500 | K77: 200
A78: 2006 | B78: 周丽红 | C78: 2500 | D78: 200 | H78: 2006 | I78: 周丽红 | J78: 2500 | K78: 200
A79: 2007 | B79: 黄伟军 | C79: 5000 | D79: 400 | H79: 2007/2008 | I79: 黄伟军 | J79: 5000 | K79: 400
A80: 2008 | B80: 黄伟军 | H80: 2008 | I80: 黄伟军
A81: 2009 | B81: 冯世豪 | C81: 2500 | D81: 200 | H81: 2009 | I81: 冯世豪 | J81: 2500 | K81: 200
A82: 2010 | B82: 王既异 | C82: 2500 | D82: 200 | H82: 2010 | I82: 王既异 | J82: 2500 | K82: 200
A83: 2011 | B83: 颜艳军 | C83: 2500 | D83: 200 | H83: 2011 | I83: 颜艳军 | J83: 2500 | K83: 200
A84: 2012 | B84: 卢永永 | C84: 2500 | D84: 200 | H84: 2012 | I84: 卢永永 | J84: 2500 | K84: 200
A85: 2013 | B85: 陈高俊 | C85: 2500 | D85: 200 | H85: 2013 | I85: 陈高俊 | J85: 2500 | K85: 200
A86: 2014 | B86: 张顶 | C86: 2500 | D86: 200 | H86: 2014 | I86: 张顶 | J86: 2500 | K86: 200
A87: 2015 | B87: 冯章权 | C87: 2500 | D87: 200 | H87: 2015 | I87: 冯章权 | J87: 2500 | K87: 200
A88: 2016 | B88: 黎慧敏 | C88: 2500 | D88: 200 | H88: 2016 | I88: 黎慧敏 | J88: 2500 | K88: 200
A89: 2017 | B89: 黎慧敏 | C89: 2500 | D89: 200 | H89: 2017 | I89: 黎慧敏 | J89: 2500 | K89: 200
A90: 2018 | B90: 钟丽梅 | C90: 2500 | D90: 200 | H90: 2018 | I90: 钟丽梅 | J90: 2500 | K90: 200
A91: 2019 | B91: 周欣雨 | C91: 2500 | D91: 200 | H91: 2019 | I91: 周欣雨 | J91: 2500 | K91: 200
A92: 2020 | B92: 朱楚帆 | C92: 2500 | D92: 200 | H92: 2020 | I92: 朱楚帆 | J92: 2500 | K92: 200
... A97: 2025 | B97: 焦小峰 | C97: 2500 | D97: 200 | H97: 2025 | I97: 焦小峰 | J97: 2500 | K97: 200
A98: 2026 | B98: 林樊杰 | C98: 1800 | H98: 2026 | I98: 办公室
A99: 2027 | B99: 焦红楼 | C99: 1180 | H99: 2027 | I99: 办公室
A100: 2029 | B100: 郭林红 | C100: 2500 | D100: 200 | H100: 2029 | I100: 郭林红 | J100: 2500 | K100: 200
A101: 2030 | B101: 郭林红 | C101: 2500 | D101: 200 | H101: 2030 | I101: 郭林红 | J101: 2500 | K101: 200
A102: 2031 | B102: 习国斌 | C102: 2500 | D102: 200 | H102: 2031 | I102: 习国斌 | J102: 2500 | K102: 200
A103: 2032 | B103: 张明亮 | C103: 2500 | D103: 200 | H103: 2032 | I103: 张明亮 | J103: 2500 | K103: 200
A104: 2033 | B104: 余芝玲 | C104: 2500 | D104: 200 | H104: 2033 | I104: 余芝玲 | J104: 2500 | K104: 200
A105: 2034 | B105: 余芝玲 | C105: 2500 | D105: 200 | H105: 2034 | I105: 余芝玲 | J105: 2500 | K105: 200
A106: 2035 | B106: 欧阳辉 | C106: 2500 | D106: 200 | H106: 2035 | I106: 欧阳辉 | J106: 2500 | K106: 200
A107: 2035A | B107: 邬水芬 | C107: 2500 | D107: 200 | H107: 2035A | I107: 邬水芬 | J107: 2500 | K107: 200
A108: 2036 | B108: 陈蓉 | C108: 2500 | D108: 200 | H108: 2036 | I108: 陈蓉 | J108: 2500 | K108: 200
A109: 2037 | B109: 徐介全 | C109: 2500 | D109: 200 | H109: 2037 | I109: 徐介全 | J109: 2500 | K109: 200
A110: 2038 | B110: 徐介全 | C110: 2500 | D110: 200 | H110: 2038 | I110: 徐介全 | J110: 2500 | K110: 200
A111: 2039 | B111: 蔡玉琴 | C111: 2500 | D111: 200 | H111: 2039 | I111: 蔡玉琴 | J111: 2500 | K111: 200
...

Sheet Sheet7
A2: 档口号 | B2: 商户名
A4: 1001-01（临一） | B4: 何具达
A5: 1001 | B5: 邓凤强
A6: 1002 | B6: 苏建柳
A7: 1003/1004 | B7: 李鹏飞
A8: 1005 | B8: 黄腾凌
A9: 1006 | B9: 刘展
A10: 1007 | B10: 王正庚
A11: 1008/1009 | B11: 潭日标
A12: 1009 | B12: 潭日标
A13: 1010 | B13: 王长梅
A14: 1011 | B14: 段邦彦
A15: 1012 | B15: 李文学
A16: 1013 | B16: 揭英祥
A17: 1014 | B17: 陈文彬
A18: 1015 | B18: 张平君
A19: 1016/1017 | B19: 卢汉总
A20: 1018 | B20: 白成滔
A21: 1019 | B21: 王长梅
A22: 1020 | B22: 张爱玲
A23: 1021 | B23: 刘光全
A24: 1022 | B24: 庄诗霖
A25: 1023 | B25: 黎培健
A26: 1024 | B26: 王小军
A27: 1025 | B27: 李雄辉
A28: 1025-A | B28: 苏建柳
A29: 1026 | B29: 马旦
A30: 1027 | B30: 范宏成
A31: 1028 | B31: 阮文彬
A32: 1029 | B32: 钟玲玲
A33: 1030 | B33: 覃燕芬
A34: 1031 | B34: 陈恳
A35: 1032 | B35: 范琼静
A36: 1033 | B36: 蔡安琦
A37: 1034 | B37: 杨志鸿
A38: 1035 | B38: 王正庚
A39: 1036 | B39: 李耿坚
A40: 1037 | B40: 范宏健
... A68: 1066 | B68: 卢永润
A69: 1067展柜(全包） | B69: 章芳琴
A70: 1068展柜/1069展柜 | B70: 黄伟慧
A71: 大厅01 | B71: 张文英
A72: 大厅02 | B72: 黎鹏其
A73: 2001 | B73: 黄廉廷（临租）
A74: 2002 | B74: 孙标然
A75: 2003 | B75: 陆兆亮
A76: 2004 | B76: 林翠侠
A77: 2005 | B77: 徐忠琴
A78: 2006 | B78: 周丽红
A79: 2007/2008 | B79: 黄伟军
A80: 2008 | B80: 黄伟军
A81: 2009 | B81: 冯世豪
A82: 2010 | B82: 王既异
A83: 2011 | B83: 颜艳军
A84: 2012 | B84: 卢永永
A85: 2013 | B85: 陈高俊
A86: 2014 | B86: 张顶
A87: 2015 | B87: 冯章权
A88: 2016 | B88: 黎慧敏
A89: 2017 | B89: 黎慧敏
A90: 2018 | B90: 钟丽梅
A91: 2019 | B91: 周欣雨
... A106: 2035 | B106: 欧阳辉
A107: 2035A | B107: 邬水芬
A108: 2036 | B108: 陈蓉
A109: 2036 | B109: 陈蓉
A110: 2037 | B110: 徐介全
A111: 2038 | B111: 徐介全
A112: 2039 | B112: 蔡玉琴
A113: 2040 | B113: 吕穗生
A114: 2041 | B114: 吕穗生
A115: 2042 | B115: 吴礼娴
A116: 2043/2044 | B116: 林晓玲
A117: 2044 | B117: 林晓玲
A118: 2045 | B118: 柏云涛
A119: 2046 | B119: 文林海
A120: 2047 | B120: 郭红林
A121: 2048 | B121: 赵野
A122: 2049 | B122: 黄腾坡
A123: 2050 | B123: 徐俊明
A124: 2051 | B124: 黄廉勃
A125: 2052 | B125: 阚显巍
A126: 2053 | B126: 詹爱彩
A127: 2054 | B127: 孙瑜
A128: 2055 | B128: 孙瑜
... A135: 2062 | B135: 黄桂涛
A136: 2063/2064 | B136: 吴彬辉
A137: 2064 | B137: 吴彬辉
A138: 2066 | B138: 王小军
A139: 2067 | B139: 王海亮
A140: 2068 | B140: 郑美卿
A141: 2069 | B141: 陈亚丽
A142: 2070 | B142: 王名冲
A143: 2071 | B143: 陈寿锋
A144: 2072 | B144: 王琴
A145: 2073 | B145: 林晓君
A146: 2074 | B146: 刘丽秀
A147: 2075 | B147: 王楚红
A148: 2076 | B148: 孙瑜
A149: 2077 | B149: 刘真辉
...

Sheet 电表
A2: 档口号 | B2: 商铺号 | C2: 11月份 | D2: 12月份 | E2: 1月份 | F2: 2月份 | G2: 3月份 | H2: 4月份 | I2: 5月份 | J2: 6月份 | K2: 7月份 | L2: 8月份 | M2: 9月份
A4: 1001-01（临一） | B4: 1001-01（临一） | C4: 19518 | D4: 19645
A5: 1001 | B5: 1001 | C5: 3340 | D5: 3491
A6: 1002 | B6: 1002 | C6: 8431 | D6: 8436
A7: 1003/1004 | B7: 1003/1004 | C7: =5652+9610 -> 15262 | D7: =9610+5974 -> 15584
A8: 1005 | B8: 1005 | C8: 2696 | D8: 2746
A9: 1006 | B9: 1006 | C9: 4133 | D9: 4186
A10: 1007 | B10: 1007 | C10: 370 | D10: 450
A11: 1008/1009 | B11: 1008/1009 | C11: 1417 | D11: 1565
A12: 1009 | B12: 1009 | C12: 2986 | D12: 3050
A13: 1010 | B13: 1010 | C13: 7204 | D13: 7317
A14: 1011 | B14: 1011 | C14: 1903 | D14: 1913
A15: 1012 | B15: 1012 | C15: 778 | D15: 841
A16: 1013 | B16: 1013 | C16: 2705 | D16: 2775
A17: 1014 | B17: 1014 | C17: 2040 | D17: 2226
A18: 1015 | B18: 1015 | C18: 5248 | D18: 5267
A19: 1016/1017 | B19: 1016/1017 | C19: =4907+728 -> 5635 | D19: =4966+860 -> 5826
A20: 1018 | B20: 1018 | C20: 3664 | D20: 3710
A21: 1019 | B21: 1019 | C21: 1395 | D21: 1411
A22: 1020 | B22: 1020 | C22: 9151 | D22: 9247
A23: 1021 | B23: 1021 | C23: 5429 | D23: 5573
A24: 1022 | B24: 1022 | C24: 2613 | D24: 2647
A25: 1023 | B25: 1023 | C25: 1839 | D25: 1851
A26: 1024 | B26: 1024 | C26: 186 | D26: 225
A27: 1025 | B27: 1025 | C27: 1219 | D27: 1233
A28: 1025-A | B28: 1025-A | C28: 2817 | D28: 2877
A29: 1026 | B29: 1026 | C29: 3230 | D29: 3345
A30: 1027 | B30: 1027 | C30: 3120 | D30: 3151
A31: 1028 | B31: 1028 | C31: 7768 | D31: 7816
A32: 1029 | B32: 1029 | C32: 4820 | D32: 4912
A33: 1030 | B33: 1030 | C33: 4863 | D33: 4948
A34: 1031 | B34: 1031 | C34: 5641 | D34: 5728
A35: 1032 | B35: 1032 | C35: 5380 | D35: 5477
A36: 1033 | B36: 1033 | C36: 8359 | D36: 8452
A37: 1034 | B37: 1034 | C37: 2652 | D37: 2692
A38: 1035 | B38: 1035 | C38: 9842 | D38: 9894
A39: 1036 | B39: 1036 | C39: 9842 | D39: 9894
A40: 1037 | B40: 1037 | C40: 3158 | D40: 3207
... A68: 1066 | B68: 1066 | C68: 7977 | D68: 8185
A69: 1067展柜(全包） | B69: 1067展柜(全包）
A70: 1068展柜/1069展柜 | B70: 1068展柜/1069展柜
A71: 一楼前电梯展柜1069 | B71: 一楼前电梯展柜1069
A72: 2001 | B72: 2001 | C72: 7602 | D72: 7711
A73: 2002 | B73: 2002 | C73: 7063 | D73: 7129
A74: 2003 | B74: 2003 | C74: 8243 | D74: 8294
A75: 2004 | B75: 2004 | C75: 8594 | D75: 8618
A76: 2005 | B76: 2005 | C76: 7929 | D76: 8012
A77: 2006 | B77: 2006 | C77: 199 | D77: 263
A78: 2007/2008 | B78: 2007/2008 | C78: 6991 | D78: 7028
A79: 2008 | B79: 2008 | C79: 9039 | D79: 9089
A80: 2009 | B80: 2009 | C80: 4327 | D80: 4361
A81: 2010 | B81: 2010 | C81: 329 | D81: 424
A82: 2011 | B82: 2011 | C82: 7850 | D82: 7911
A83: 2012 | B83: 2012 | C83: 10033 | D83: 100
A84: 2013 | B84: 2013 | C84: 1759 | D84: 1830
A85: 2014 | B85: 2014 | C85: 2299 | D85: 2317
A86: 2015 | B86: 2015 | C86: 9213 | D86: 9253
A87: 2016 | B87: 2016 | C87: 8454 | D87: 8527
A88: 2017 | B88: 2017 | C88: 8822 | D88: 8933
A89: 2018 | B89: 2018 | C89: 321 | D89: 507
A90: 2019 | B90: 2019 | C90: 9911 | D90: 10037
... A105: 2035 | B105: 2035 | C105: 9826 | D105: 9865
A106: 2035A | B106: 2035A | C106: 1129 | D106: 1197
A107: 2036 | B107: 2036 | C107: 7432 | D107: 7432
A108: 2036 | B108: 2036 | C108: 8423 | D108: 8470
A109: 2037 | B109: 2037 | C109: 1621 | D109: 1766
A110: 2038 | B110: 2038 | C110: 7876 | D110: 7876
A111: 2039 | B111: 2039 | C111: 5498 | D111: 5582
A112: 2040 | B112: 2040 | C112: 5225 | D112: 5249
A113: 2041 | B113: 2041 | C113: 7653 | D113: 7709
A114: 2042 | B114: 2042 | C114: 6035 | D114: 6096
A115: 2043/2044 | B115: 2043/2044 | C115: 749 | D115: 862
A116: 2044 | B116: 2044 | C116: 9241 | D116: 9358
A117: 2045 | B117: 2045 | C117: 6884 | D117: 6942
A118: 2046 | B118: 2046 | C118: 5126 | D118: 5168
A119: 2047 | B119: 2047 | C119: 696 | D119: 756
A120: 2048 | B120: 2048 | C120: 6660 | D120: 6750
A121: 2049 | B121: 2049 | C121: 7693 | D121: 7751
A122: 2050 | B122: 2050 | C122: 6887 | D122: 6922
A123: 2051 | B123: 2051 | C123: 576 | D123: 652
A124: 2052 | B124: 2052 | C124: 7162 | D124: 7204
A125: 2053 | B125: 2053 | C125: 7853 | D125: 7893
A126: 2054 | B126: 2054 | C126: 326 | D126: 478
A127: 2055 | B127: 2055 | C127: 6494 | D127: 6494
... A134: 2062 | B134: 2062 | C134: 7762 | D134: 7795
A135: 2063/2064 | B135: 2063/2064 | C135: 0 | D135: 0
A136: 2064 | B136: 2064 | C136: 940 | D136: 1085
A137: 2066 | B137: 2066 | C137: 9865 | D137: 9995
A138: 2067 | B138: 2067 | C138: 5251 | D138: 5251
A139: 2068 | B139: 2068 | C139: 266 | D139: 336
A140: 2069 | B140: 2069 | C140: 7913 | D140: 7953
A141: 2070 | B141: 2070 | C141: 7313 | D141: 7378
A142: 2071 | B142: 2071 | C142: 7864 | D142: 7913
A143: 2072 | B143: 2072 | C143: 3486 | D143: 3608
A144: 2073 | B144: 2073 | C144: 6070 | D144: 6162
A145: 2074 | B145: 2074 | C145: 6533 | D145: 6571
A146: 2075 | B146: 2075 | C146: 8189 | D146: 8262
A147: 2076 | B147: 2076 | C147: 914 | D147: 1016
A148: 2077 | B148: 2077 | C148: 9260 | D148: 9298
A149: 2078/2079 | B149: 2078/2079 | C149: 132 | D149: 233
...

Sheet Sheet5
A2: 档口号 | B2: 商户名 | C2: 租金 | F2: 档号 | G2: 档主名
H3: 月租
A4: 1002 | B4: 苏建柳 | C4: 1500 | F4: 1002 | G4: 苏建柳 | H4: 1500 | I4: =C4-H4 -> 0
A5: 1025-A | B5: 苏建柳 | C5: 2206 | F5: 1025-A | G5: 苏建柳 | H5: 4202 | I5: =C5-H5 -> -1996
A6: 1037 | B6: 范宏健 | C6: 4200 | F6: 1037 | G6: 范宏健 | H6: 4200 | I6: =C6-H6 -> 0
A7: 1040 | B7: 陈少华 | C7: 4202 | F7: 1040 | G7: 陈少华 | H7: 4202 | I7: =C7-H7 -> 0
A8: 1055 | B8: 梁中梅 | C8: 4200 | F8: 1055 | G8: 梁中梅 | H8: 4200 | I8: =C8-H8 -> 0
A9: 2002 | B9: 孙标然 | C9: 2300 | F9: 2002 | G9: 孙标然 | H9: 2300 | I9: =C9-H9 -> 0
A10: 2006 | B10: 周丽红 | C10: 2300 | F10: 2006 | G10: 周丽红 | H10: 2300 | I10: =C10-H10 -> 0
A11: 2009 | B11: 冯世豪 | C11: 2300 | F11: 2009 | G11: 冯世豪 | H11: 2300 | I11: =C11-H11 -> 0
A12: 2014 | B12: 张顶 | C12: 2300 | F12: 2014 | G12: 张顶 | H12: 2300 | I12: =C12-H12 -> 0
A13: 2016 | B13: 黎慧敏 | C13: 2300 | F13: 2016 | G13: 黎慧敏 | H13: 2300 | I13: =C13-H13 -> 0
A14: 2017 | B14: 黎慧敏 | C14: 2300 | F14: 2017 | G14: 黎慧敏 | H14: 2300 | I14: =C14-H14 -> 0
A15: 2021 | B15: 吴桂华 | C15: 2300 | F15: 2021 | G15: 吴桂华 | H15: 2300 | I15: =C15-H15 -> 0
A16: 2029 | B16: 郭林红 | C16: 2300 | F16: 2029 | G16: 郭林红 | H16: 2300 | I16: =C16-H16 -> 0
A17: 2039 | B17: 蔡玉琴 | C17: 2300 | F17: 2039 | G17: 蔡玉琴 | H17: 2300 | I17: =C17-H17 -> 0
A18: 2043/2044 | B18: 林晓玲 | C18: 4600 | F18: 2043 | G18: 林晓玲 | H18: 4600 | I18: =C18-H18 -> 0
A19: 2044 | B19: 林晓玲 | F19: 2044 | G19: 林晓玲 | I19: =C19-H19 -> 0
A20: 2047 | B20: 郭红林 | C20: 2000 | F20: 2047 | G20: 郭红林 | H20: 2000 | I20: =C20-H20 -> 0
A21: 2054 | B21: 孙瑜 | C21: 2300 | F21: 2054（2053A) | G21: 孙瑜 | H21: 4600 | I21: =C21-H21 -> -2300
A22: 2055 | B22: 孙瑜 | C22: 2300 | F22: 2055 | G22: 孙瑜 | I22: =C22-H22 -> 2300
A23: 2057 | B23: 牟军 | C23: 2300 | F23: 2057 | G23: 牟军 | H23: 2300 | I23: =C23-H23 -> 0
A24: 2063/2064 | B24: 吴彬辉 | C24: 4600 | F24: 2063 | G24: 吴彬辉 | H24: 4600 | I24: =C24-H24 -> 0
A25: 2064 | B25: 吴彬辉 | F25: 2064 | G25: 吴彬辉 | I25: =C25-H25 -> 0
A26: 2074 | B26: 刘丽秀 | C26: 2300 | F26: 2075A(2074) | G26: 刘丽秀 | H26: 2300 | I26: =C26-H26 -> 0
A27: 2082 | B27: 叶雪梅 | C27: 2300 | F27: 2082 | G27: 叶雪梅 | H27: 2300 | I27: =C27-H27 -> 0
A28: 2084 | B28: 梁彬 | C28: 2300 | F28: 2084 | G28: 梁彬 | H28: 2300 | I28: =C28-H28 -> 0
A29: 2086 | B29: 张维原 | C29: 2300 | F29: 2086 | G29: 张维原 | H29: 2300 | I29: =C29-H29 -> 0
A30: 2088 | B30: 林香超 | C30: 2300 | F30: 2088 | G30: 林香超 | H30: 2300 | I30: =C30-H30 -> 0
A31: 3011 | B31: 王海亮 | C31: 5000 | F31: 3011 | G31: 王海亮 | H31: 5000 | I31: =C31-H31 -> 0
A32: 3017 | B32: 张顶 | C32: 5000 | F32: 3017 | G32: 张顶 | H32: 5000 | I32: =C32-H32 -> 0
A33: 3022 | B33: 陈娇丽 | C33: 5000 | F33: 3022 | G33: 陈娇丽 | H33: 5000 | I33: =C33-H33 -> 0
A34: 3048 | B34: 刘德政 | C34: 5000 | F34: 3028/3053/3054 | G34: 张智森 | H34: 6000 | I34: =C34-H34 -> -1000
A35: 3049 | B35: 林香科 | C35: 5000 | F35: 3048 | G35: 刘德政 | H35: 5000 | I35: =C35-H35 -> 0
A36: 3028/3053/3054 | B36: 张智森 | C36: 6000 | F36: 3049 | G36: 林香科 | H36: 5000 | I36: =C36-H36 -> 1000
A37: 4006 | B37: 刘德政 | C37: 4500 | F37: 4006 | G37: 刘德政 | H37: 4500 | I37: =C37-H37 -> 0
A38: 4025 | B38: 黄保军 | C38: 4500 | F38: 4025 | G38: 黄保军 | H38: 4500 | I38: =C38-H38 -> 0
A39: 4043 | B39: 黄杰清 | C39: 4500 | F39: 4043 | G39: 黄杰清 | H39: 4500 | I39: =C39-H39 -> 0
A40: 5001 | B40: 沈阳俊 | C40: 4000 | F40: 5001 | G40: 沈阳俊 | H40: 4000 | I40: =C40-H40 -> 0
A41: 5006 | B41: 陈淡吟 | C41: 4000 | F41: 5006 | G41: 陈淡吟 | H41: 4000 | I41: =C41-H41 -> 0
A42: 5008 | B42: 江瑞芝 | C42: 4000 | F42: 5008 | G42: 江瑞芝 | H42: 4000 | I42: =C42-H42 -> 0
A43: 5023 | B43: 王贵云 | C43: 4000 | F43: 5023 | G43: 王贵云 | H43: 4000 | I43: =C43-H43 -> 0
A44: 5024 | B44: 王贵云 | C44: 4000 | F44: 5024 | G44: 王贵云 | H44: 4000 | I44: =C44-H44 -> 0
A45: 5038 | B45: 陈汉真 | C45: 4000 | F45: 5038 | G45: 陈汉真 | H45: 4000 | I45: =C45-H45 -> 0
A46: 5040 | B46: 张璐 | C46: 4000 | F46: 5040 | G46: 张璐 | H46: 4000 | I46: =C46-H46 -> 0
A47: 5045 | B47: 冯彬彬 | C47: 4000 | F47: 5045 | G47: 冯彬彬 | H47: 4000 | I47: =C47-H47 -> 0
A48: 5046-5047 | B48: 邓杰 | C48: 4500 | F48: 5046 | G48: 邓杰 | H48: 7000
C51: =SUM(C4:C50) -> 147608 | H51: =SUM(H4:H50) -> 152104 | I51: =C51-H51 -> -4496

Sheet Sheet2
B3: 商铺号 | C3: 商户名 | D3: 面积 | E3: 租金 | F3: 管理费
B5: 2001 | C5: 黄廉廷（临租） | E5: 1500 | H5: 2001 | I5: 黄廉廷 | J5: 1500 | L5: =E5-J5 -> 0
B6: 2022 | C6: 白成涛 | E6: 2000 | H6: 2022 | I6: 白成涛 | J6: 2000 | L6: =E6-J6 -> 0
B7: 2044 | C7: 钟日生 | D7: 16.54 | E7: 2000 | H7: 2044 | I7: 钟日生 | J7: 2000 | L7: =E7-J7 -> 0
B8: 3009半档 | C8: 罗春兰 | D8: 32.425 | E8: 2540 | F8: 200 | H8: 3009 | I8: 罗春兰 | J8: 2540 | K8: 200 | L8: =E8-J8 -> 0
B9: 3040半档 | C9: 庄智杨 | D9: 32.425 | E9: 2788 | F9: 200 | H9: 3040 | I9: 庄智杨 | J9: 2788 | K9: 200 | L9: =E9-J9 -> 0
B10: 3045半档 | C10: 张朝花 | D10: 32.425 | E10: 2662 | F10: 200 | H10: 3045 | I10: 张朝花 | J10: 2662 | K10: 200 | L10: =E10-J10 -> 0
B11: 4006半档 | C11: 刘德政 | D11: 32.425 | E11: 2800 | F11: 200 | H11: 4006 | I11: 刘德政 | J11: 2800 | K11: 200 | L11: =E11-J11 -> 0
B12: 4011半档 | C12: 赖文杰 | D12: 32.425 | E12: 2800 | F12: 200 | H12: 4011 | I12: 赖文杰 | J12: 2800 | K12: 200 | L12: =E12-J12 -> 0
B13: 4016半档 | C13: 蔡祖莹 | D13: 32.425 | E13: 2697 | F13: 200 | H13: 4016 | I13: 蔡祖莹 | J13: 2697 | K13: 200 | L13: =E13-J13 -> 0
B14: 4018半档 | C14: 张朝帅 | D14: 32.425 | L14: =E14-J14 -> 0
B15: 4021半档 | C15: 张丽风 | D15: 32.425 | E15: 2800 | F15: 200 | H15: 4021 | I15: 张丽风 | J15: 2800 | K15: 200 | L15: =E15-J15 -> 0
B16: 4026半档 | C16: 张朝凯 | D16: 32.425 | E16: 2691 | F16: 200 | H16: 4026 | I16: 张朝凯 | J16: 2691 | K16: 200 | L16: =E16-J16 -> 0
B17: 4030半档 | C17: 王丽枝 | D17: 32.425 | E17: 3500 | F17: 250 | H17: 4030 | I17: 王丽枝 | J17: 3500 | K17: 250 | L17: =E17-J17 -> 0
B18: 4035半档 | C18: 黄廉兴 | D18: 32.425 | E18: 2800 | F18: 200 | H18: 4035 | I18: 黄廉兴 | J18: 2800 | K18: 200 | L18: =E18-J18 -> 0
B19: 4038半档 | C19: 陈超 | D19: 32.425 | E19: 2800 | F19: 200 | H19: 4038 | I19: 陈超 | J19: 2800 | K19: 200 | L19: =E19-J19 -> 0
B20: 4040半档 | C20: 刘航 | D20: 32.425 | E20: 2800 | F20: 200 | H20: 4040 | I20: 刘航 | J20: 2800 | K20: 200 | L20: =E20-J20 -> 0
B21: 4043半档 | C21: 卢永润 | D21: 32.425 | E21: 3500 | F21: 200 | H21: 4043 | I21: 卢永润 | J21: 3500 | K21: 200 | L21: =E21-J21 -> 0
B22: 4044半档 | C22: 张虎 | D22: 32.425 | E22: 2800 | F22: 200 | H22: 4044 | I22: 张虎 | J22: 2800 | K22: 200 | L22: =E22-J22 -> 0
B23: 4046半档 | C23: 李义中 | D23: 32.425 | E23: 3250 | F23: 200 | H23: 4046 | I23: 李义中 | J23: 3250 | K23: 200 | L23: =E23-J23 -> 0
B24: 4046A半档 | C24: 李太焕 | D24: 32.425 | E24: 2758 | F24: 200 | H24: 4046A | I24: 李太焕 | J24: 2758 | K24: 200 | L24: =E24-J24 -> 0

Sheet Sheet3
A1: 商铺号 | B1: 商户名 | C1: 面积 | D1: 租金 | E1: 管理费 | H1: 档号 | I1: 档主名 | L1: 递增日（2021） | M1: 递增金额
J2: 月租 | K2: 管理费
A3: 1001-01（临一） | B3: 陈良伟 | C3: 19.5 | D3: 3052 | E3: 210 | H3: 1001-01（临一） | I3: 陈良伟 | J3: 3052 | K3: 210 | L3: 44256 | M3: 2906 | N3: =D3-J3 -> 0
A4: 1001 | B4: 邓凤强 | C4: 21.87 | D4: 4202 | E4: 500 | H4: 1001 | I4: 邓凤强 | J4: 4202 | K4: 500 | N4: =D4-J4 -> 0
A5: 1002 | B5: 苏建柳 | C5: 27.87 | D5: 3000 | H5: 1002 | I5: 苏建柳 | J5: 3000 | N5: =D5-J5 -> 0
A6: 1003/1004 | B6: 陈汉真 | C6: 49.02 | D6: 2851 | E6: 400 | H6: 1003 | I6: 陈汉真 | J6: 2851 | K6: 400 | N6: =D6-J6 -> 0
A7: 1005 | B7: 林翠侠 | C7: 27.15 | D7: 2000 | H7: 1005 | I7: 林翠侠 | J7: 2000 | N7: =D7-J7 -> 0
A8: 1006 | H8: 1006 | N8: =D8-J8 -> 0
A9: 1007 | H9: 1007 | N9: =D9-J9 -> 0
A10: 1008 | B10: 陈汉真（临租） | C10: 27.15 | D10: 1600 | H10: 1008 | I10: 陈汉真 | J10: 1600 | K10: 0 | N10: =D10-J10 -> 0
A11: 1009 | B11: 林丽情 | C11: 27.15 | D11: 4202 | E11: 500 | H11: 1009 | I11: 林丽情 | J11: 4202 | K11: 500 | N11: =D11-J11 -> 0
A12: 1010 | B12: 包君威 | C12: 23.77 | D12: 4202 | E12: 500 | H12: 1010 | I12: 包君威 | J12: 4202 | K12: 500 | N12: =D12-J12 -> 0
A13: 1011 | B13: 赵德花 | C13: 27.15 | D13: 2500 | H13: 1011 | I13: 赵德花 | J13: 2500 | N13: =D13-J13 -> 0
A14: 1012 | B14: 薛扬 | C14: 27.5 | D14: 2500 | H14: 1012 | I14: 薛扬 | J14: 2500 | N14: =D14-J14 -> 0
A15: 1013 | B15: 陈金俊 | C15: 27.15 | D15: 2500 | H15: 1013 | I15: 陈金俊 | J15: 2500 | N15: =D15-J15 -> 0
A16: 1014/1015 | B16: 王奎（临租） | C16: 54.3 | D16: 3000 | H16: 1014 | I16: 王奎 | J16: 3000 | N16: =D16-J16 -> 0
A17: 1016/1017 | B17: 王燕华 | C17: 54.3 | D17: 3800 | E17: 400 | H17: 1016 | I17: 王燕华 | J17: 3800 | K17: 400 | N17: =D17-J17 -> 0
A18: 1018 | B18: 白成滔 | C18: 27.5 | D18: 2000 | H18: 1018 | I18: 白成滔 | J18: 2700 | N18: =D18-J18 -> -700
A19: 1019 | B19: 杨桂芹（临） | C19: 27.15 | D19: 1600 | E19: 200 | H19: 1019 | I19: 杨桂芹 | J19: 1600 | K19: 200 | N19: =D19-J19 -> 0
A20: 1020 | H20: 1020 | N20: =D20-J20 -> 0
A21: 1021 | B21: 林春铸 | C21: 27.15 | D21: 4226 | E21: 500 | H21: 1021 | I21: 林春铸 | J21: =M24 -> 4226 | K21: 500 | N21: =D21-J21 -> 0
A22: 1022 | B22: 庄诗霖（临租） | C22: 56.26 | D22: 2531 | H22: 1022 | I22: 庄诗霖 | J22: 2531 | N22: =D22-J22 -> 0
A23: 1023 | B23: 赵德花（临仓） | C23: 31.79 | D23: 1000 | H23: 1023 | I23: 赵德花 | J23: 1000 | N23: =D23-J23 -> 0
A24: 1024 | B24: 王小军（临仓） | C24: 43.89 | D24: 1448 | H24: 1024 | I24: 王小军 | J24: 1448 | L24: 44413 | M24: 4226 | N24: =D24-J24 -> 0
A25: 1025 | B25: 林小武 | C25: 27.15 | D25: 4202 | E25: 500 | H25: 1025 | I25: 林小武 | J25: 4202 | K25: 500 | N25: =D25-J25 -> 0
A26: 1025-A | B26: 苏建柳 | C26: 26.45 | D26: 4202 | E26: 500 | H26: 1025-A | I26: 苏建柳 | J26: 4202 | K26: 500 | N26: =D26-J26 -> 0
A27: 1026 | B27: 林百光 | C27: 27.15 | D27: 4202 | E27: 500 | H27: 1026 | I27: 林百光 | J27: 4202 | K27: 500 | N27: =D27-J27 -> 0
A28: 1027 | H28: 1027 | N28: =D28-J28 -> 0
A29: 1028 | B29: 阮文宾 | C29: 27.15 | D29: 4202 | E29: 500 | H29: 1028 | I29: 阮文彬 | J29: 4202 | K29: 500 | N29: =D29-J29 -> 0
A30: 1029 | B30: 陈文超 | C30: 27.15 | D30: 4202 | E30: 500 | H30: 1029 | I30: 陈文超 | J30: 4202 | K30: 500 | N30: =D30-J30 -> 0
A31: 1030 | B31: 覃燕芬 | C31: 27.15 | D31: 4202 | E31: 500 | H31: 1030 | I31: 覃燕芬 | J31: =M34 -> 4202 | K31: 500 | N31: =D31-J31 -> 0
A32: 1031 | B32: 方海潮 | C32: 23.77 | D32: 4202 | E32: 500 | H32: 1031 | I32: 方海潮 | J32: 4202 | K32: 500 | N32: =D32-J32 -> 0
A33: 1032 | B33: 范琼静 | C33: 27.15 | D33: 4202 | E33: 500 | H33: 1032 | I33: 范琼静 | J33: 4202 | K33: 500 | N33: =D33-J33 -> 0
A34: 1033 | H34: 1033 | L34: 44470 | M34: 4202 | N34: =D34-J34 -> 0
A35: 1034 | H35: 1034 | N35: =D35-J35 -> 0
A36: 1035 | B36: 廖文怀 | C36: 27.15 | D36: 4202 | E36: 500 | H36: 1035 | I36: 廖文怀 | J36: 4202 | K36: 500 | N36: =D36-J36 -> 0
A37: 1036 | B37: 谢玲华 | C37: 27.15 | D37: 4202 | E37: 500 | H37: 1036 | I37: 谢玲华 | J37: 4202 | K37: 500 | N37: =D37-J37 -> 0
A38: 1037 | B38: 杨志鸿 | C38: 27.15 | D38: 4202 | E38: 500 | H38: 1037 | I38: 杨志鸿 | J38: 4202 | K38: 500 | N38: =D38-J38 -> 0
A39: 1038 | B39: 黄夏琼 | C39: 27.15 | D39: 4202 | E39: 500 | H39: 1038 | I39: 黄夏琼 | J39: 4202 | K39: 500 | N39: =D39-J39 -> 0
A40: 1039 | B40: 吴玉荡 | C40: 27.15 | D40: 4624 | E40: 500 | H40: 1039 | I40: 吴玉荡 | J40: 4624 | K40: 500 | N40: =D40-J40 -> 0
A41: 1040 | B41: 陈少华 | C41: 27.15 | D41: =5076-600 -> 4476 | E41: 500 | H41: 1040 | I41: 陈少华 | J41: =2538*2 -> 5076 | K41: 500 | N41: =D41-J41 -> -600
A42: 1041 | B42: 李耿坚 | C42: 27.15 | D42: 4202 | E42: 500 | H42: 1041 | I42: 李耿坚 | J42: 4202 | K42: 500 | N42: =D42-J42 -> 0
A43: 1042 | B43: 陈俊炳 | C43: 27.15 | D43: 4202 | E43: 500 | H43: 1042 | I43: 陈俊炳 | J43: =2101+2101 -> 4202 | K43: 500 | N43: =D43-J43 -> 0
A44: 1043 | B44: 刘怡 | C44: 27.15 | D44: 4202 | E44: 500 | H44: 1043 | I44: 刘怡 | J44: 4202 | K44: 500 | N44: =D44-J44 -> 0
A45: 1044 | B45: 陈秋香 | C45: 27.15 | D45: 4202 | E45: 500 | H45: 1044 | I45: 陈秋香 | J45: 4202 | K45: 500 | N45: =D45-J45 -> 0
A46: 1045 | B46: 黄金龙 | C46: 26.49 | D46: 4474 | E46: 500 | H46: 1045 | I46: 黄金龙 | J46: =M49 -> 4474 | K46: 500 | N46: =D46-J46 -> 0
A47: 1046 | B47: 胡命礼 | C47: 26.49 | D47: 4202 | E47: 500 | H47: 1046 | I47: 胡命礼 | J47: 4202 | K47: 500 | N47: =D47-J47 -> 0
A48: 1047 | B48: 庄展锐 | C48: 26.49 | D48: 4202 | E48: 500 | H48: 1047 | I48: 庄展锐 | J48: =M51 -> 4202 | K48: 500 | N48: =D48-J48 -> 0
A49: 1048 | B49: 刘云娇 | C49: 26.49 | D49: 4202 | E49: 500 | H49: 1048 | I49: 刘云娇 | J49: =M52 -> 4202 | K49: 500 | L49: 44287 | M49: 4474 | N49: =D49-J49 -> 0
A50: 1049 | B50: 何飞 | C50: 26.49 | D50: 4202 | E50: 500 | H50: 1049 | I50: 何飞 | J50: 4202 | K50: 500 | N50: =D50-J50 -> 0
A51: 1050 | B51: 易金启 | C51: 26.49 | D51: 4202 | E51: 500 | H51: 1050 | I51: 易金启 | J51: 4202 | K51: 500 | L51: 44470 | M51: 4202 | N51: =D51-J51 -> 0
A52: 1051 | B52: 余华生 | C52: 26.49 | D52: 4202 | E52: 500 | H52: 1051 | I52: 余华生 | J52: 4202 | K52: 500 | L52: 44470 | M52: 4202 | N52: =D52-J52 -> 0
A53: 1052 | B53: 范琼妹 | C53: 26.49 | D53: 4410 | E53: 500 | H53: 1052 | I53: 范琼妹 | J53: 4410 | K53: 500 | N53: =D53-J53 -> 0
A54: 1053 | B54: 肖勇 | C54: 26.15 | D54: 4202 | E54: 500 | H54: 1053 | I54: 肖勇 | J54: 4202 | K54: 500 | N54: =D54-J54 -> 0
A55: 1054 | B55: 沈飞艳 | C55: 27.15 | D55: 4202 | E55: 500 | H55: 1054 | I55: 沈飞艳 | J55: 4202 | K55: 500 | N55: =D55-J55 -> 0
A56: 1055 | B56: 林健辉 | C56: 26.49 | D56: 4624 | E56: 500 | H56: 1055 | I56: 林健辉 | J56: =2312+2312 -> 4624 | K56: 500 | L56: 44287 | M56: 4200 | N56: =D56-J56 -> 0
A57: 1056 | B57: 赵东芳 | C57: 26.49 | D57: 4202 | E57: 500 | H57: 1056 | I57: 赵东芳 | J57: 4202 | K57: 500 | N57: =D57-J57 -> 0
A58: 1057 | B58: 肖梓尧 | C58: 26.49 | D58: 4202 | E58: 500 | H58: 1057 | I58: 肖梓尧 | J58: 4202 | K58: 500 | N58: =D58-J58 -> 0
A59: 1058 | B59: 诸美华 | C59: 26.49 | D59: 4202 | E59: 500 | H59: 1058 | I59: 褚美华 | J59: 4202 | K59: 500 | N59: =D59-J59 -> 0
A60: 1059 | B60: 林思萍 | C60: 26.49 | D60: 4202 | E60: 500 | H60: 1059 | I60: 林思萍 | J60: 4202 | K60: 500 | N60: =D60-J60 -> 0
A61: 1060 | B61: 戴晓怡 | C61: 26.49 | D61: 4202 | E61: 500 | H61: 1060 | I61: 陈爱媛 | J61: =2101+2101 -> 4202 | K61: 500 | N61: =D61-J61 -> 0
A62: 1061 | H62: 1061 | N62: =D62-J62 -> 0
A63: 1062 | B63: 李嘉格 | C63: 27.15 | D63: 4202 | E63: 500 | H63: 1062 | I63: 李嘉格 | J63: 4202 | K63: 500 | N63: =D63-J63 -> 0
A64: 1063 | B64: 余迎龙 | C64: 6.21 | D64: 2240 | E64: 200 | H64: 1063 | I64: 余迎龙 | J64: 2240 | K64: 200 | N64: =D64-J64 -> 0
A65: 1065 | B65: 章芳琴 | C65: 6.21 | D65: 2240 | E65: 200 | H65: 1065 | I65: 章芳琴 | J65: 2240 | K65: 200 | N65: =D65-J65 -> 0
A66: 1066 | B66: 郭飞 | C66: 27.15 | D66: 5370 | E66: 500 | H66: 1066 | I66: 郭飞 | J66: =M69 -> 5370 | K66: 500 | N66: =D66-J66 -> 0
A67: 1067展柜(全包） | B67: 张小芳 | D67: 1600 | H67: 1067展柜 | I67: 张小芳 | J67: 1600 | N67: =D67-J67 -> 0
A68: 1068展柜(全包） | H68: 1068展柜 | N68: =D68-J68 -> 0
A69: 1069展柜(全包） | H69: 1069展柜 | L69: 44470 | M69: 5370 | N69: =D69-J69 -> 0
A70: 2001 | B70: 黄廉廷（临租） | D70: 1500 | H70: 2001 | I70: 黄廉廷 | J70: 1500 | N70: =D70-J70 -> 0
A71: 2002 | B71: 孙标然(临) | C71: 19.54 | D71: 4000 | H71: 2002 | I71: 孙标然 | J71: 4000 | N71: =D71-J71 -> 0
A72: 2003 | B72: 胡文英（临） | C72: 19.54 | D72: 4000 | H72: 2003 | I72: 胡文英 | J72: 4000 | N72: =D72-J72 -> 0
A73: 2004 | B73: 张谷香 | C73: 19.54 | D73: 4000 | H73: 2004 | I73: 张谷香 | J73: 4000 | K73: 0 | N73: =D73-J73 -> 0
A74: 2005 | B74: 卢永果 | C74: 19.54 | D74: 4000 | H74: 2005 | I74: 卢永果 | J74: 4000 | K74: 500 | N74: =D74-J74 -> 0
A75: 2006 | B75: 周丽红 | C75: 19.54 | D75: 4000 | H75: 2006 | I75: 周丽红 | J75: 4000 | K75: 0 | N75: =D75-J75 -> 0
A76: 2007 | B76: 杨斌 | C76: 19.54 | D76: 4000 | H76: 2007 | I76: 杨斌 | J76: 4100 | K76: 500 | N76: =D76-J76 -> -100
A77: 2008 | B77: 白保倩 | C77: 19.54 | D77: =4000 -> 4000 | H77: 2008 | I77: 白保倩 | J77: 4000 | N77: =D77-J77 -> 0
A78: 2009 | B78: 卢世雍 | C78: 16.54 | D78: 4000 | H78: 2009 | I78: 卢世雍 | J78: 4000 | K78: 0 | N78: =D78-J78 -> 0
A79: 2010 | B79: 王既异 | C79: 19.54 | D79: 4000 | H79: 2010 | I79: 王既异 | J79: 4000 | N79: =D79-J79 -> 0
A80: 2011 | B80: 颜艳军 | C80: 19.54 | D80: 4000 | H80: 2011 | I80: 颜艳军 | J80: 4000 | N80: =D80-J80 -> 0
A81: 2012 | B81: 孙建峰 | C81: 19.54 | D81: 4000 | H81: 2012 | I81: 孙建峰 | J81: 4000 | N81: =D81-J81 -> 0
A82: 2013 | B82: 阎新萍（临租） | C82: 19.54 | D82: 4000 | H82: 2013 | I82: 阎新萍 | J82: 4000 | N82: =D82-J82 -> 0
A83: 2014 | B83: 张明富（临租） | C83: 19.54 | D83: 4000 | H83: 2014 | I83: 张明富 | J83: 4000 | N83: =D83-J83 -> 0
A84: 2015 | B84: 张顶（临） | C84: 19.54 | D84: 4000 | H84: 2015 | I84: 张顶 | J84: 4000 | N84: =D84-J84 -> 0
A85: 2016 | B85: 黎慧敏 | C85: 19.54 | D85: 4000 | H85: 2016 | I85: 黎慧敏 | J85: 4000 | N85: =D85-J85 -> 0
A86: 2017 | B86: 黎慧敏 | C86: 19.54 | D86: 4000 | H86: 2017 | I86: 黎慧敏 | J86: 4000 | N86: =D86-J86 -> 0
A87: 2018 | B87: 林建婵（临） | C87: 19.54 | D87: 4000 | H87: 2018 | I87: 林建婵 | J87: 4000 | N87: =D87-J87 -> 0
A88: 2019 | H88: 2019 | N88: =D88-J88 -> 0
A89: 2020 | B89: 张晓璇 | C89: 19.54 | D89: 4000 | H89: 2020 | I89: 张晓璇 | J89: 4000 | K89: 0 | N89: =D89-J89 -> 0
A90: 2021 | B90: 卢世聪 | C90: 19.54 | D90: 4000 | H90: 2021 | I90: 卢世聪 | J90: 4000 | N90: =D90-J90 -> 0
A91: 2022 | B91: 白成涛 | D91: 2000 | H91: 2022 | I91: 白成涛 | J91: 2000 | N91: =D91-J91 -> 0
A92: 2023 | H92: 2023 | N92: =D92-J92 -> 0
A93: 2024 | B93: 余小帆 | C93: 19.54 | D93: 4000 | H93: 2024 | I93: 余小帆 | J93: 4000 | N93: =D93-J93 -> 0
A94: 2025 | B94: 高韦铃 | C94: 23.84 | D94: 4000 | H94: 2025 | I94: 高韦铃 | J94: 4000 | N94: =D94-J94 -> 0
A95: 2026 | B95: 林樊杰（临仓） | C95: 38.03 | D95: 1800 | H95: 2026 | I95: 林樊杰 | J95: 1800 | N95: =D95-J95 -> 0
A96: 2027 | B96: 焦红楼（临仓全包） | C96: 39.33 | D96: 1180 | H96: 2027 | I96: 焦红楼 | J96: 1180 | N96: =D96-J96 -> 0
A97: 2029 | B97: 郭林红 | C97: 19.54 | D97: 1500 | H97: 2029 | I97: 郭林红 | J97: 1500 | N97: =D97-J97 -> 0
A98: 2030 | B98: 陈顺生 | C98: 16.54 | D98: 4000 | H98: 2030 | I98: 陈顺生 | J98: 4000 | N98: =D98-J98 -> 0
A99: 2031 | B99: 习国斌 | C99: 16.54 | D99: 4000 | H99: 2031 | I99: 习国斌 | J99: 4000 | N99: =D99-J99 -> 0
A100: 2032 | B100: 陈华彬（临） | C100: 16.54 | D100: 4000 | H100: 2032 | I100: 陈华彬 | J100: 4000 | N100: =D100-J100 -> 0
...

Sheet Sheet4
K9: 4月 | L9: 5月 | M9: 6月 | N9: 7月
J10: 实际折扣 | K10: 6折 | L10: 5折 | M10: 5折 | N10: 5折
F12: 1021 | G12: 林春铸 | H12: 27.15 | I12: 4226 | K12: =ROUND(I12*0.4,0) -> 1690 | L12: =ROUND(I12*0.5,0) -> 2113 | M12: =ROUND(I12*0.5,0) -> 2113 | N12: =I12*0.5 -> 2113
F13: 1044 | G13: 陈秋香 | H13: 27.15 | I13: 4202 | K13: =ROUND(I13*0.4,0) -> 1681 | L13: =ROUND(I13*0.5,0) -> 2101 | M13: =ROUND(I13*0.5,0) -> 2101 | N13: =I13*0.5 -> 2101
F14: 1065 | G14: 章芳琴 | H14: 6.21 | I14: 2240 | K14: =ROUND(I14*0.4,0) -> 896 | L14: =ROUND(I14*0.5,0) -> 1120 | M14: =ROUND(I14*0.5,0) -> 1120 | N14: =I14*0.5 -> 1120
K16: 4月 | L16: 5月 | M16: 6月 | N16: 7月
J17: 市场折扣 | K17: 8折 | L17: 6折 | M17: 7折 | N17: 8折
K18: =ROUND(4226*0.2,0) -> 845 | L18: =ROUND(4226*0.4,0) -> 1690 | M18: =ROUND(4226*0.3,0) -> 1268 | N18: =ROUND(4226*0.2,0) -> 845
K19: =ROUND(4202*0.2,0) -> 840 | L19: =ROUND(4202*0.4,0) -> 1681 | M19: =ROUND(4202*0.3,0) -> 1261 | N19: =ROUND(4202*0.2,0) -> 840
K20: =ROUND(2240*0.2,0) -> 448 | L20: =ROUND(2240*0.4,0) -> 896 | M20: =ROUND(2240*0.3,0) -> 672 | N20: =ROUND(2240*0.2,0) -> 448
J22: 差额 | K22: =K12-K18 -> 845 | L22: =L12-L18 -> 423 | M22: =M12-M18 -> 845 | N22: =N12-N18 -> 1268 | P22: =SUM(K22:N22) -> 3381
K23: =K13-K19 -> 841 | L23: =L13-L19 -> 420 | M23: =M13-M19 -> 840 | N23: =N13-N19 -> 1261 | P23: =SUM(K23:N23) -> 3362
K24: =K14-K20 -> 448 | L24: =L14-L20 -> 224 | M24: =M14-M20 -> 448 | N24: =N14-N20 -> 672 | P24: =SUM(K24:N24) -> 1792

Sheet 电表数

Sheet 空档数
C2: 截止空档数3.30
C3: 一楼商铺 | D3: 1034
C4: 一楼商铺 | D4: 1061
C5: 一楼展柜 | D5: 1068展柜(全包）
C6: 一楼展柜 | D6: 1069展柜(全包）
C7: 二楼档口 | D7: 2001 | E7: 被占用 | G7: 3.31号到期未续签 | I7: 2019
C8: 二楼档口 | D8: 2044 | G8: 1028 | I8: 2040
C9: 二楼档口 | D9: 2045 | G9: 1033 | I9: 2052
C10: 二楼档口 | D10: 2061 | G10: 1037 | I10: 4010
C11: 二楼档口 | D11: 2062 | G11: 1041 | I11: 4019 | M11: -
C12: 二楼档口 | D12: 2064 | G12: 1058 | M12: 2019 | N12: 林建婵（临） | O12: 19.54 | P12: 4000 | R12: 2019 | S12: 林建婵（临）
C13: 二楼档口 | D13: 2066 | G13: 2078 | M13: 2040 | N13: 钟士梅 | O13: 16.54 | P13: 4000 | R13: 2040 | S13: 钟士梅
C14: 二楼档口 | D14: 2067 | G14: 2081 | M14: 2052 | N14: 赖鑫（临） | O14: 16.54 | P14: 4000 | R14: 2052 | S14: 赖鑫（临）
C15: 二楼档口 | D15: 2070 | G15: 2088 | M15: 2063 | N15: 王金保 | O15: 16.54 | P15: 4000 | R15: 2063 | S15: 李恒耀
C16: 二楼档口 | D16: 2084 | G16: 3011 | M16: 3009 | N16: 陈强 | O16: 32.425 | P16: 5080 | R16: 3009 | S16: 陈强
C17: 二楼档口 | D17: 2086 | G17: 4040 | H17: 待定先不出 | M17: 4007 | N17: 刘艳霞 | O17: 32.425 | P17: 6378 | R17: 4007 | S17: 刘艳霞
C18: 二楼档口 | D18: 2087 | M18: 4010 | N18: 李声亮 | O18: 32.425 | P18: 5650 | R18: 4010 | S18: 李声亮
C19: 二楼展柜 | D19: 2093展柜 | M19: 4011 | N19: 申俊强 | O19: 32.425 | P19: 6560 | R19: 4011 | S19: 申俊强
C20: 二楼展柜 | D20: 2095展柜 | M20: 4015 | N20: 罗银送 | O20: 32.425 | P20: 5792 | R20: 4015 | S20: 罗银送
C21: 二楼展柜 | D21: 2096展柜 | M21: 4018 | N21: 唐雄英 | O21: 32.425 | P21: 6560 | R21: 4018 | S21: 唐雄英
C22: 三楼档口 | D22: 3023 | M22: 4019 | N22: 黄叶乐 | O22: 32.425 | P22: 5650 | R22: 4019 | S22: 黄叶乐
C23: 三楼档口 | D23: 3030 | M23: 4030 | N23: 余海城 | O23: 32.425 | P23: 6558 | R23: 4030 | S23: 余海城
C24: 三楼档口 | D24: 3040 | M24: 5020 | N24: 刘艳林 | O24: 32.425 | P24: 6102 | R24: 5020 | S24: 刘艳林
C25: 三楼展柜 | D25: 三楼自编展柜 | M25: 5023 | N25: 宋丽丽 | O25: 32.425 | P25: 6102 | R25: 5023 | S25: 宋丽丽
C26: 四楼档口 | D26: 4004
C27: 四楼档口 | D27: 4006
C28: 四楼档口 | D28: 4016
C29: 四楼档口 | D29: 4023
C30: 四楼档口 | D30: 4026
C31: 四楼档口 | D31: 4033
C32: 四楼档口 | D32: 4044
C33: 四楼展柜 | D33: 四楼展柜
C34: 五楼档口 | D34: 5011
C35: 五楼档口 | D35: 5013A
C36: 五楼档口 | D36: 5018
C37: 五楼档口 | D37: 5019
C38: 五楼档口 | D38: 5021
C39: 五楼档口 | D39: 5026
C40: 五楼档口 | D40: 5027
C41: 五楼档口 | D41: 5037
C42: 五楼档口 | D42: 5039
C43: 五楼档口 | D43: 5041
C54: 商铺号 | D54: 商户名
C56: 1034
C57: 1061
C58: 1068展柜(全包）
C59: 1069展柜(全包）
C60: 2001
C61: 2019
C62: 2040
C63: 2044
C64: 2045
C65: 2052
C66: 2061
C67: 2062
C68: 2064
C69: 2066
C70: 2067
C71: 2070
... C74: 2087
C75: 2093展柜
C76: 2095展柜
C77: 2096展柜
C78: 3023 | G78: 7个展柜
C79: 3030
C80: 3040
C81: 三楼自编展柜
C82: 4004
C83: 4006
C84: 4010
C85: 4016
C86: 4019
C87: 4023
C88: 4026 | G88: 2063
C89: 4033 | G89: 3009
C90: 4044 | G90: 4007
C91: 四楼展柜 | G91: 4011
C92: 5011 | G92: 4015
C93: 5013A | G93: 4018
C94: 5018 | G94: 4030
C95: 5019 | G95: 5020
C96: 5021 | G96: 5023
C97: 5026
C98: 5027
C99: 5037
C100: 5039
C101: 5041
C102: 4040 | G102: 49档口 7个展柜

Sheet Sheet1
A3: 楼层 | B3: 商铺号 | C3: 商户名 | D3: 面积 | E3: 租金 | F3: 管理费 | H3: 档号 | I3: 档主名 | Q3: 计租日 | R3: 递增日（2021） | S3: 递增金额 | T3: 递增日（2022） | U3: 递增金额
J4: 总租金 | K4: 管理费
A5: 一楼商铺 | B5: 1001-01（临一） | C5: 陈良伟 | D5: 19.5 | E5: 3052 | F5: 210 | H5: 1001-01（临一） | I5: 陈良伟 | J5: =U5 -> 3052 | K5: 210 | M5: =E5-J5 -> 0 | N5: =F5-K5 -> 0 | Q5: 43891 | R5: 44256 | S5: 2906 | T5: 44621 | U5: 3052
A6: 一楼商铺 | B6: 1001 | C6: 邓凤强 | D6: 21.87 | E6: 4202 | F6: 500 | H6: 1001 | I6: 邓凤强 | J6: 4202 | K6: 500 | M6: =E6-J6 -> 0 | N6: =F6-K6 -> 0 | Q6: 44652
A7: 一楼商铺 | B7: 1002 | C7: 苏建柳 | D7: 27.87 | E7: 3000 | H7: 1002 | I7: 苏建柳 | J7: 3000 | M7: =E7-J7 -> 0 | N7: =F7-K7 -> 0 | Q7: 44348
A8: 一楼商铺 | B8: 1003/1004 | C8: 陈汉真 | D8: 49.02 | E8: 2851 | F8: 400 | H8: 1003-1004 | I8: 陈汉真 | J8: 2851 | K8: 400 | M8: =E8-J8 -> 0 | N8: =F8-K8 -> 0 | Q8: 44348
A9: 一楼商铺 | B9: 1005 | C9: 林翠侠 | D9: 27.15 | E9: 2000 | H9: 1005 | I9: 林翠侠 | J9: 2000 | M9: =E9-J9 -> 0 | N9: =F9-K9 -> 0 | Q9: 44548
A10: 一楼商铺 | B10: 1006 | C10: 谢伟明 | D10: 27.15 | E10: 4412 | F10: 500 | H10: 1006 | I10: 谢伟明 | J10: =U10 -> 4412 | K10: 500 | M10: =E10-J10 -> 0 | N10: =F10-K10 -> 0 | Q10: 44440 | T10: 44652 | U10: 4412
A11: 一楼商铺 | B11: 1007 | C11: 苏碧兰 | D11: 27.15 | E11: 3994 | F11: 500 | H11: 1007 | I11: 苏碧兰 | J11: 3994 | K11: 500 | M11: =E11-J11 -> 0 | N11: =F11-K11 -> 0 | Q11: 44378 | T11: 44743 | U11: =1997*2 -> 3994
A12: 一楼商铺 | B12: 1008 | C12: 陈汉真（临租） | D12: 27.15 | E12: 1600 | H12: 1008 | I12: 陈汉真 | J12: 1600 | K12: 0 | M12: =E12-J12 -> 0 | N12: =F12-K12 -> 0 | Q12: 44640
A13: 一楼商铺 | B13: 1009 | C13: 林丽情 | D13: 27.15 | E13: 4202 | F13: 500 | H13: 1009 | I13: 林丽情 | J13: 4202 | K13: 500 | M13: =E13-J13 -> 0 | N13: =F13-K13 -> 0 | Q13: 44621
A14: 一楼商铺 | B14: 1010 | C14: 包君威 | D14: 23.77 | E14: 4202 | F14: 500 | H14: 1010 | I14: 魏丽绚 | J14: =S14 -> 4202 | K14: 500 | M14: =E14-J14 -> 0 | N14: =F14-K14 -> 0 | Q14: 43556 | R14: 44287 | S14: 4202
A15: 一楼商铺 | B15: 1011 | C15: 唐丹凤 | D15: 27.15 | E15: 3000 | H15: 1011 | I15: 唐丹凤 | J15: 3000 | M15: =E15-J15 -> 0 | N15: =F15-K15 -> 0 | Q15: 44531
A16: 一楼商铺 | B16: 1012 | C16: 薛扬 | D16: 27.5 | E16: 2500 | H16: 1012 | I16: 薛扬 | J16: 2500 | M16: =E16-J16 -> 0 | N16: =F16-K16 -> 0 | Q16: 44531
A17: 一楼商铺 | B17: 1013 | C17: 陈金俊 | D17: 27.15 | E17: 2500 | H17: 1013 | I17: 陈金俊 | J17: 2500 | M17: =E17-J17 -> 0 | N17: =F17-K17 -> 0 | Q17: 44378 | T17: 44743 | U17: 2500
A18: 一楼商铺 | B18: 1014/1015 | C18: 王奎（临租） | D18: 54.3 | E18: 3000 | H18: 1014-15 | I18: 王奎 | J18: 3000 | M18: =E18-J18 -> 0 | N18: =F18-K18 -> 0 | Q18: 43937
A19: 一楼商铺 | B19: 1016/1017 | C19: 王燕华 | D19: 54.3 | E19: 3800 | F19: 400 | H19: 1016-17 | I19: 王燕华 | J19: 3800 | K19: 400 | M19: =E19-J19 -> 0 | N19: =F19-K19 -> 0 | Q19: 44423
A20: 一楼商铺 | B20: 1018 | C20: 白成滔 | D20: 27.5 | E20: 2700 | H20: 1018 | I20: 白成滔 | J20: 2700 | M20: =E20-J20 -> 0 | N20: =F20-K20 -> 0 | Q20: 44348
A21: 一楼商铺 | B21: 1019 | C21: 杨桂芹（临） | D21: 27.15 | E21: 1600 | F21: 200 | H21: 1019 | I21: 杨桂芹 | J21: 1600 | K21: 200 | M21: =E21-J21 -> 0 | N21: =F21-K21 -> 0
A22: 一楼商铺 | B22: 1020 | C22: 林茂 | D22: 27.15 | E22: 4000 | H22: 1020 | I22: 林茂 | J22: 4000 | M22: =E22-J22 -> 0 | N22: =F22-K22 -> 0 | Q22: 44362 | T22: 44727 | U22: 4000
A23: 一楼商铺 | B23: 1021 | C23: 林春铸 | D23: 27.15 | E23: 4226 | F23: 500 | H23: 1021 | I23: 林春铸 | J23: =S23 -> 4226 | K23: 500 | M23: =E23-J23 -> 0 | N23: =F23-K23 -> 0 | Q23: 43682 | R23: 44413 | S23: 4226
A24: 一楼商铺 | B24: 1022 | C24: 庄诗霖（临租） | D24: 56.26 | E24: 2531 | H24: 1022 | I24: 庄诗霖 | J24: 2531 | M24: =E24-J24 -> 0 | N24: =F24-K24 -> 0
A25: 一楼商铺 | B25: 1023 | C25: 赵德花（临仓） | D25: 31.79 | E25: 1000 | H25: 1023 | I25: 赵德花 | J25: 1000 | M25: =E25-J25 -> 0 | N25: =F25-K25 -> 0 | Q25: 43831
A26: 一楼商铺 | B26: 1024 | C26: 王小军（临仓） | D26: 43.89 | E26: 1448 | H26: 1024 | I26: 王小军 | J26: 1448 | M26: =E26-J26 -> 0 | N26: =F26-K26 -> 0
A27: 一楼商铺 | B27: 1025 | C27: 林小武 | D27: 27.15 | E27: 4202 | F27: 500 | H27: 1025 | I27: 林小武 | J27: 4202 | K27: 500 | M27: =E27-J27 -> 0 | N27: =F27-K27 -> 0 | Q27: 44652
A28: 一楼商铺 | B28: 1025-A | C28: 苏建柳 | D28: 26.45 | E28: 4202 | F28: 500 | H28: 1025-A | I28: 苏建柳 | J28: 4202 | K28: 500 | M28: =E28-J28 -> 0 | N28: =F28-K28 -> 0 | Q28: 44621
A29: 一楼商铺 | B29: 1026 | C29: 林百光 | D29: 27.15 | E29: 4202 | F29: 500 | H29: 1026 | I29: 林百光 | J29: 4202 | K29: 500 | M29: =E29-J29 -> 0 | N29: =F29-K29 -> 0 | Q29: 44652
A30: 一楼商铺 | B30: 1027 | C30: 吴建忠 | D30: 27.15 | E30: 4202 | F30: 500 | H30: 1027 | I30: 吴建忠 | J30: =S30 -> 4202 | K30: 500 | M30: =E30-J30 -> 0 | N30: =F30-K30 -> 0 | Q30: 43739 | R30: 44287 | S30: 4202
A31: 一楼商铺 | B31: 1028 | C31: 李晓彩 | D31: 27.15 | E31: 4202 | F31: 500 | H31: 1028 | I31: 李晓彩 | J31: =S31 -> 4202 | K31: 500 | M31: =E31-J31 -> 0 | N31: =F31-K31 -> 0 | Q31: 43556 | R31: 44287 | S31: 4202
A32: 一楼商铺 | B32: 1029 | C32: 陈文超 | D32: 27.15 | E32: 4202 | F32: 500 | H32: 1029 | I32: 陈文超 | J32: 4202 | K32: 500 | M32: =E32-J32 -> 0 | N32: =F32-K32 -> 0 | Q32: 44652
A33: 一楼商铺 | B33: 1030 | C33: 覃燕芬 | D33: 27.15 | E33: 4202 | F33: 500 | H33: 1030 | I33: 覃燕芬 | J33: =S33 -> 4202 | K33: 500 | M33: =E33-J33 -> 0 | N33: =F33-K33 -> 0 | Q33: 43739 | R33: 44470 | S33: 4202
A34: 一楼商铺 | B34: 1031 | C34: 方海潮 | D34: 23.77 | E34: 4202 | F34: 500 | H34: 1031 | I34: 方海潮 | J34: 4202 | K34: 500 | M34: =E34-J34 -> 0 | N34: =F34-K34 -> 0 | Q34: 44652
A35: 一楼商铺 | B35: 1032 | C35: 范琼静 | D35: 27.15 | E35: 4202 | F35: 500 | H35: 1032 | I35: 范琼静 | J35: 4202 | K35: 500 | M35: =E35-J35 -> 0 | N35: =F35-K35 -> 0 | Q35: 44652
A36: 一楼商铺 | B36: 1033 | C36: 文千红 | D36: 27.15 | E36: 4202 | F36: 500 | H36: 1033 | I36: 文千红 | J36: =S36 -> 4202 | K36: 500 | M36: =E36-J36 -> 0 | N36: =F36-K36 -> 0 | Q36: 43556 | R36: 44287 | S36: 4202
A37: 一楼商铺 | B37: 1034 | H37: 1034 | M37: =E37-J37 -> 0 | N37: =F37-K37 -> 0
A38: 一楼商铺 | B38: 1035 | C38: 廖文怀 | D38: 27.15 | E38: 4202 | F38: 500 | H38: 1035 | I38: 廖文怀 | J38: 4202 | K38: 500 | M38: =E38-J38 -> 0 | N38: =F38-K38 -> 0 | Q38: 44652
A39: 一楼商铺 | B39: 1036 | C39: 谢玲华 | D39: 27.15 | E39: 4202 | F39: 500 | H39: 1036 | I39: 谢玲华 | J39: 4202 | K39: 500 | M39: =E39-J39 -> 0 | N39: =F39-K39 -> 0 | Q39: 44652
A40: 一楼商铺 | B40: 1037 | C40: 杨志鸿 | D40: 27.15 | E40: 4202 | H40: 1037 | I40: 杨志鸿 | J40: =S40 -> 4202 | K40: 500 | M40: =E40-J40 -> 0 | N40: =F40-K40 -> -500 | Q40: 43556 | R40: 44287 | S40: 4202
A41: 一楼商铺 | B41: 1038 | C41: 黄夏琼 | D41: 27.15 | E41: 4202 | F41: 500 | H41: 1038 | I41: 黄夏琼 | J41: 4202 | K41: 500 | M41: =E41-J41 -> 0 | N41: =F41-K41 -> 0 | Q41: 44652
A42: 一楼商铺 | B42: 1039 | C42: 吴玉荡 | D42: 27.15 | E42: 4624 | F42: 500 | H42: 1039 | I42: 吴玉荡 | J42: =U42 -> 4624 | K42: 500 | M42: =E42-J42 -> 0 | N42: =F42-K42 -> 0 | Q42: 44228 | T42: 44593 | U42: 4624
A43: 一楼商铺 | B43: 1040 | C43: 陈少华 | D43: 27.15 | E43: =5076-600 -> 4476 | F43: 500 | H43: 1040 | I43: 陈少华 | J43: 5076 | K43: 500 | M43: =E43-J43 -> -600 | N43: =F43-K43 -> 0 | Q43: 44501 | T43: 44866 | U43: =2665*2 -> 5330
A44: 一楼商铺 | B44: 1041 | C44: 涂珍珍 | D44: 27.15 | E44: 4202 | F44: 500 | H44: 1041 | I44: 涂珍珍 | J44: =S44 -> 4202 | K44: 500 | M44: =E44-J44 -> 0 | N44: =F44-K44 -> 0 | Q44: 43556 | R44: 44287 | S44: 4202
A45: 一楼商铺 | B45: 1042 | C45: 陈俊炳 | D45: 27.15 | E45: 4202 | F45: 500 | H45: 1042 | I45: 陈俊炳 | J45: 4202 | K45: 500 | M45: =E45-J45 -> 0 | N45: =F45-K45 -> 0 | Q45: 44652
A46: 一楼商铺 | B46: 1043 | C46: 刘怡 | D46: 27.15 | E46: 4202 | F46: 500 | H46: 1043 | I46: 刘怡 | J46: 4202 | K46: 500 | M46: =E46-J46 -> 0 | N46: =F46-K46 -> 0 | Q46: 44652
A47: 一楼商铺 | B47: 1044 | C47: 陈秋香 | D47: 27.15 | E47: 4202 | F47: 500 | H47: 1044 | I47: 陈秋香 | J47: =U47 -> 4202 | K47: 500 | M47: =E47-J47 -> 0 | N47: =F47-K47 -> 0 | Q47: 44612 | T47: 44612 | U47: =2101+2101 -> 4202
A48: 一楼商铺 | B48: 1045 | C48: 黄金龙 | D48: 26.49 | E48: 4474 | F48: 500 | H48: 1045 | I48: 黄金龙 | J48: =S48 -> 4474 | K48: 500 | M48: =E48-J48 -> 0 | N48: =F48-K48 -> 0 | Q48: 43739 | R48: 44287 | S48: 4474
A49: 一楼商铺 | B49: 1046 | C49: 胡命礼 | D49: 26.49 | E49: 4202 | F49: 500 | H49: 1046 | I49: 胡命礼 | J49: 4202 | K49: 500 | M49: =E49-J49 -> 0 | N49: =F49-K49 -> 0 | Q49: 44652
A50: 一楼商铺 | B50: 1047 | C50: 庄展锐 | D50: 26.49 | E50: 4202 | F50: 500 | H50: 1047 | I50: 庄展锐 | J50: =S50 -> 4202 | K50: 500 | M50: =E50-J50 -> 0 | N50: =F50-K50 -> 0 | Q50: 43983 | R50: 44470 | S50: 4202
A51: 一楼商铺 | B51: 1048 | C51: 刘云娇 | D51: 26.49 | E51: 4202 | F51: 500 | H51: 1048 | I51: 刘云娇 | J51: =S51 -> 4202 | K51: 500 | M51: =E51-J51 -> 0 | N51: =F51-K51 -> 0 | Q51: 43739 | R51: 44470 | S51: 4202
A52: 一楼商铺 | B52: 1049 | C52: 何飞 | D52: 26.49 | E52: 4202 | F52: 500 | H52: 1049 | I52: 何飞 | J52: 4202 | K52: 500 | M52: =E52-J52 -> 0 | N52: =F52-K52 -> 0 | Q52: 44652
A53: 一楼商铺 | B53: 1050 | C53: 易金启 | D53: 26.49 | E53: 4202 | F53: 500 | H53: 1050 | I53: 易金启 | J53: 4202 | K53: 500 | M53: =E53-J53 -> 0 | N53: =F53-K53 -> 0 | Q53: 44652
A54: 一楼商铺 | B54: 1051 | C54: 余华生 | D54: 26.49 | E54: 4202 | F54: 500 | H54: 1051 | I54: 余华生 | J54: 4202 | K54: 500 | M54: =E54-J54 -> 0 | N54: =F54-K54 -> 0 | Q54: 44652
A55: 一楼商铺 | B55: 1052 | C55: 范琼妹 | D55: 26.49 | E55: 4410 | F55: 500 | H55: 1052 | I55: 范琼妹 | J55: =U55 -> 4410 | K55: 500 | M55: =E55-J55 -> 0 | N55: =F55-K55 -> 0 | Q55: 43922 | R55: 44287 | S55: 4200 | T55: 44652 | U55: 4410
A56: 一楼商铺 | B56: 1053 | C56: 肖勇 | D56: 26.15 | E56: 4202 | F56: 500 | H56: 1053 | I56: 肖勇 | J56: 4202 | K56: 500 | M56: =E56-J56 -> 0 | N56: =F56-K56 -> 0 | Q56: 44652
A57: 一楼商铺 | B57: 1054 | C57: 沈飞艳 | D57: 27.15 | E57: 4202 | F57: 500 | H57: 1054 | I57: 沈飞艳 | J57: 4202 | K57: 500 | M57: =E57-J57 -> 0 | N57: =F57-K57 -> 0 | Q57: 44652
A58: 一楼商铺 | B58: 1055 | C58: 林健辉 | D58: 26.49 | E58: 4624 | F58: 500 | H58: 1055 | I58: 林健辉 | J58: =U58 -> 4624 | K58: 500 | M58: =E58-J58 -> 0 | N58: =F58-K58 -> 0 | Q58: 44287 | T58: 44652 | U58: =2312+2312 -> 4624
A59: 一楼商铺 | B59: 1056 | C59: 赵东芳 | D59: 26.49 | E59: 4202 | F59: 500 | H59: 1056 | I59: 赵东芳 | J59: 4202 | K59: 500 | M59: =E59-J59 -> 0 | N59: =F59-K59 -> 0 | Q59: 44652
A60: 一楼商铺 | B60: 1057 | C60: 肖梓尧 | D60: 26.49 | E60: 4202 | F60: 500 | H60: 1057 | I60: 肖梓尧 | J60: 4202 | K60: 500 | M60: =E60-J60 -> 0 | N60: =F60-K60 -> 0 | Q60: 44652
A61: 一楼商铺 | B61: 1058 | C61: 诸美华 | D61: 26.49 | E61: 4202 | F61: 500 | H61: 1058 | I61: 褚美华 | J61: 4202 | K61: 500 | M61: =E61-J61 -> 0 | N61: =F61-K61 -> 0 | Q61: 44652
A62: 一楼商铺 | B62: 1059 | C62: 林思萍 | D62: 26.49 | E62: 4202 | F62: 500 | H62: 1059 | I62: 林思萍 | J62: 4202 | K62: 500 | M62: =E62-J62 -> 0 | N62: =F62-K62 -> 0 | Q62: 44652
A63: 一楼商铺 | B63: 1060 | C63: 陈爱媛 | D63: 26.49 | E63: 4202 | F63: 500 | H63: 1060 | I63: 陈爱媛 | J63: 4202 | K63: 500 | M63: =E63-J63 -> 0 | N63: =F63-K63 -> 0 | Q63: 44652
A64: 一楼商铺 | B64: 1061 | H64: 1061 | M64: =E64-J64 -> 0 | N64: =F64-K64 -> 0
A65: 一楼商铺 | B65: 1062 | C65: 李嘉格 | D65: 27.15 | E65: 4202 | F65: 500 | H65: 1062 | I65: 李嘉格 | J65: 4202 | K65: 500 | M65: =E65-J65 -> 0 | N65: =F65-K65 -> 0 | Q65: 44612
A66: 一楼商铺 | B66: 1063 | C66: 余迎龙 | D66: 6.21 | E66: 2240 | F66: 200 | H66: 1063 | I66: 余迎龙 | J66: 2240 | K66: 200 | M66: =E66-J66 -> 0 | N66: =F66-K66 -> 0 | Q66: 44652
A67: 一楼商铺 | B67: 1065 | C67: 章芳琴 | D67: 6.21 | E67: 2240 | F67: 200 | H67: 1065 | I67: 章芳琴 | J67: 2240 | K67: 200 | M67: =E67-J67 -> 0 | N67: =F67-K67 -> 0 | Q67: 44652
A68: 一楼商铺 | B68: 1066 | C68: 郭飞 | D68: 27.15 | E68: 5370 | F68: 500 | H68: 1066 | I68: 郭飞 | J68: =S68 -> 5370 | K68: 500 | M68: =E68-J68 -> 0 | N68: =F68-K68 -> 0 | Q68: 43739 | R68: 44470 | S68: 5370
A69: 一楼展柜 | B69: 1067展柜(全包） | C69: 贺文清 | E69: 1600 | H69: 1067展柜 | I69: 张小芳 | J69: 1600 | M69: =E69-J69 -> 0 | N69: =F69-K69 -> 0 | Q69: 44602
A70: 一楼展柜 | B70: 1068展柜(全包） | H70: 1068展柜 | M70: =E70-J70 -> 0 | N70: =F70-K70 -> 0
A71: 一楼展柜 | B71: 1069展柜(全包） | H71: 1069展柜 | M71: =E71-J71 -> 0 | N71: =F71-K71 -> 0
A72: 二楼档口 | B72: 2001 | H72: 2001 | I72: 拆迁 | M72: =E72-J72 -> 0 | N72: =F72-K72 -> 0
A73: 二楼档口 | B73: 2002 | C73: 孙标然(临) | D73: 19.54 | E73: 4000 | H73: 2002 | I73: 孙标然 | J73: 4000 | M73: =E73-J73 -> 0 | N73: =F73-K73 -> 0 | Q73: 43922
A74: 二楼档口 | B74: 2003 | C74: 胡文英（临） | D74: 19.54 | E74: 4000 | H74: 2003 | I74: 胡文英 | J74: 4000 | M74: =E74-J74 -> 0 | N74: =F74-K74 -> 0 | Q74: 44105
A75: 二楼档口 | B75: 2004 | C75: 张谷香 | D75: 19.54 | E75: 4000 | H75: 2004 | I75: 张谷香 | J75: 4000 | M75: =E75-J75 -> 0 | N75: =F75-K75 -> 0 | Q75: 44652
A76: 二楼档口 | B76: 2005 | C76: 宋高杨 | D76: 19.54 | E76: 4000 | H76: 2005 | I76: 卢永果 | J76: 4000 | M76: =E76-J76 -> 0 | N76: =F76-K76 -> 0 | Q76: 44480 | T76: 44845 | U76: 4000
A77: 二楼档口 | B77: 2006 | C77: 周丽红 | D77: 19.54 | E77: 4000 | H77: 2006 | I77: 周丽红 | J77: 4000 | M77: =E77-J77 -> 0 | N77: =F77-K77 -> 0 | Q77: 44470 | T77: 44835 | U77: 4000
A78: 二楼档口 | B78: 2007 | C78: 杨斌 | D78: 19.54 | E78: 4000 | H78: 2007 | I78: 杨斌 | J78: 4100 | M78: =E78-J78 -> -100 | N78: =F78-K78 -> 0 | Q78: 44044
A79: 二楼档口 | B79: 2008 | C79: 白保倩 | D79: 19.54 | E79: =4000 -> 4000 | H79: 2008 | I79: 白保倩 | J79: 4000 | M79: =E79-J79 -> 0 | N79: =F79-K79 -> 0 | Q79: 44053
A80: 二楼档口 | B80: 2009 | C80: 白保辉（临） | D80: 19.54 | E80: 4000 | H80: 2009 | I80: 白保辉 | J80: 4000 | M80: =E80-J80 -> 0 | N80: =F80-K80 -> 0 | Q80: 44287
A81: 二楼档口 | B81: 2010 | C81: 王既异 | D81: 19.54 | E81: 4000 | H81: 2010 | I81: 王既异 | J81: 4000 | M81: =E81-J81 -> 0 | N81: =F81-K81 -> 0 | Q81: 44105
A82: 二楼档口 | B82: 2011 | C82: 颜艳军 | D82: 19.54 | E82: 4000 | H82: 2011 | I82: 颜艳军 | J82: =U82 -> 4000 | M82: =E82-J82 -> 0 | N82: =F82-K82 -> 0 | Q82: 44287 | T82: 44652 | U82: 4000
A83: 二楼档口 | B83: 2012 | C83: 孙建峰 | D83: 19.54 | E83: 4000 | H83: 2012 | I83: 孙建峰 | J83: =U83 -> 4000 | M83: =E83-J83 -> 0 | N83: =F83-K83 -> 0 | Q83: 44287 | T83: 44652 | U83: 4000
A84: 二楼档口 | B84: 2013 | C84: 阎新萍（临租） | D84: 19.54 | E84: 4000 | H84: 2013 | I84: 阎新萍 | J84: 4000 | M84: =E84-J84 -> 0 | N84: =F84-K84 -> 0 | Q84: 44044
A85: 二楼档口 | B85: 2014 | C85: 张明富（临租） | D85: 19.54 | E85: 4000 | H85: 2014 | I85: 张明富 | J85: 4000 | M85: =E85-J85 -> 0 | N85: =F85-K85 -> 0 | Q85: 44044
A86: 二楼档口 | B86: 2015 | C86: 张顶（临） | D86: 19.54 | E86: 4000 | H86: 2015 | I86: 张顶 | J86: 4000 | M86: =E86-J86 -> 0 | N86: =F86-K86 -> 0 | Q86: 44136
A87: 二楼档口 | B87: 2016 | C87: 黎晓菲 | D87: 19.54 | E87: 4000 | H87: 2016 | I87: 黎慧敏 | J87: 4000 | M87: =E87-J87 -> 0 | N87: =F87-K87 -> 0 | Q87: 44323 | T87: 44688 | U87: 4000
A88: 二楼档口 | B88: 2017 | C88: 黎慧敏 | D88: 19.54 | E88: 4000 | H88: 2017 | I88: 黎慧敏 | J88: 4000 | M88: =E88-J88 -> 0 | N88: =F88-K88 -> 0 | Q88: 44636
A89: 二楼档口 | B89: 2018 | C89: 林建婵（临） | D89: 19.54 | E89: 4000 | H89: 2018 | I89: 林建婵 | J89: 4000 | M89: =E89-J89 -> 0 | N89: =F89-K89 -> 0 | Q89: 44044
A90: 二楼档口 | B90: 2019 | H90: 2019 | M90: =E90-J90 -> 0 | N90: =F90-K90 -> 0
A91: 二楼档口 | B91: 2020 | C91: 张晓璇 | E91: 4000 | H91: 2020 | I91: 张晓璇 | J91: 4000 | K91: 0 | M91: =E91-J91 -> 0 | N91: =F91-K91 -> 0 | Q91: 44636
A92: 二楼档口 | B92: 2021 | C92: 卢世聪 | D92: 19.54 | E92: 4000 | H92: 2021 | I92: 卢世聪 | J92: 4000 | M92: =E92-J92 -> 0 | N92: =F92-K92 -> 0 | Q92: 44397 | T92: 44762 | U92: 4000
A93: 二楼档口 | B93: 2022-2023 | C93: 余养康 | D93: 39.08 | E93: =7500 -> 7500 | H93: 2022 | I93: 余康养 | J93: 7500 | M93: =E93-J93 -> 0 | N93: =F93-K93 -> 0 | Q93: 44397 | T93: 44762 | U93: 7500
A94: 二楼档口 | B94: 2024 | C94: 余小帆 | D94: 19.54 | E94: 4000 | H94: 2024 | I94: 余小帆 | J94: 4000 | M94: =E94-J94 -> 0 | N94: =F94-K94 -> 0 | Q94: 44373 | T94: 44738 | U94: 4000
A95: 二楼档口 | B95: 2025 | C95: 高韦铃 | D95: 23.84 | E95: 4000 | H95: 2025 | I95: 高韦铃 | J95: 4000 | M95: =E95-J95 -> 0 | N95: =F95-K95 -> 0 | Q95: 44367 | T95: 44732 | U95: 4000
A96: 二楼档口 | B96: 2026 | C96: 林樊杰（临仓） | D96: 38.03 | E96: 1800 | H96: 2026 | I96: 林樊杰 | J96: 1800 | M96: =E96-J96 -> 0 | N96: =F96-K96 -> 0 | Q96: 44501
A97: 二楼档口 | B97: 2027 | C97: 焦红楼（临仓全包） | D97: 39.33 | E97: 1180 | H97: 2027 | I97: 焦红楼 | J97: 1180 | M97: =E97-J97 -> 0 | N97: =F97-K97 -> 0
A98: 二楼档口 | B98: 2029 | C98: 郭林红 | D98: 19.54 | E98: 1500 | H98: 2029 | I98: 郭林红 | J98: 1500 | M98: =E98-J98 -> 0 | N98: =F98-K98 -> 0 | Q98: 44440
A99: 二楼档口 | B99: 2030 | C99: 陈顺生 | D99: 16.54 | E99: 4000 | H99: 2030 | I99: 陈顺生 | J99: 4000 | M99: =E99-J99 -> 0 | N99: =F99-K99 -> 0 | Q99: 44136
A100: 二楼档口 | B100: 2031 | C100: 习国斌 | D100: 16.54 | E100: 4000 | H100: 2031 | I100: 习国斌 | J100: 4000 | M100: =E100-J100 -> 0 | N100: =F100-K100 -> 0 | Q100: 44105
A101: 二楼档口 | B101: 2032 | C101: 陈华彬（临） | D101: 16.54 | E101: 4000 | H101: 2032 | I101: 陈华彬 | J101: =U101 -> 4000 | M101: =E101-J101 -> 0 | N101: =F101-K101 -> 0 | Q101: 44287 | T101: 44652 | U101: 4000
A102: 二楼档口 | B102: 2033 | C102: 杨友明 | D102: 16.54 | E102: 4000 | H102: 2033 | I102: 杨友明 | J102: 4000 | M102: =E102-J102 -> 0 | N102: =F102-K102 -> 0 | Q102: 44136
...
